[
  {
    "segmentnr":"ZH_T26_1543_004:0784c02_0",
    "original":"阿毘曇八犍度論卷第四",
    "folio":4,
    "analyzed":"阿 毘 曇 八 犍 度 論 卷 第 四 "
  },
  {
    "segmentnr":"ZH_T26_1543_004:0784c04_0",
    "original":"迦旃延子造",
    "folio":4,
    "analyzed":"迦 旃 延 子 造 "
  },
  {
    "segmentnr":"ZH_T26_1543_004:0784c05_0",
    "original":"符秦罽賓三藏僧伽提婆",
    "folio":4,
    "analyzed":"符 秦 罽 賓 三 藏 僧 伽 提 婆 "
  },
  {
    "segmentnr":"ZH_T26_1543_004:0784c08_0",
    "original":"不善有報，　　見亦見苦，　　若見有覺，",
    "folio":4,
    "analyzed":"不 善 有 報    見 亦 見 苦    若 見 有 覺  "
  },
  {
    "segmentnr":"ZH_T26_1543_004:0784c09_4",
    "original":"如相應根；",
    "folio":4,
    "analyzed":"如 相 應 根  "
  },
  {
    "segmentnr":"ZH_T26_1543_004:0784c10_11",
    "original":"　　欲界獲得，　　斷亦五人，身見如是，　　一切遍後。",
    "folio":4,
    "analyzed":"  欲 界 獲 得    斷 亦 五 人  身 見 如 是    一 切 遍 後  "
  },
  {
    "segmentnr":"ZH_T26_1543_004:0784c13_6",
    "original":"三結、三不善根、三有漏，四流、四軛、四受、四縛，五蓋、五結、五下分結、五見，六身愛，七使，九結，九十八使。",
    "folio":4,
    "analyzed":"三 結  三不善根  三 有 漏  四 流  四 軛  四 受  四 縛  五 蓋  五 結  五下分結  五 見  六 身 愛  七 使  九 結  九 十 八 使  "
  },
  {
    "segmentnr":"ZH_T26_1543_004:0784c13_18",
    "original":"此三結，幾不善、幾無記；",
    "folio":4,
    "analyzed":"此 三 結  幾 不 善  幾 無 記  "
  },
  {
    "segmentnr":"ZH_T26_1543_004:0784c14_12",
    "original":"此乃至九十八使，幾不善、幾無記？",
    "folio":4,
    "analyzed":"此 乃 至 九 十 八 使  幾 不 善  幾 無 記  "
  },
  {
    "segmentnr":"ZH_T26_1543_004:0784c15_2",
    "original":"此三結，幾有報，幾無報；",
    "folio":4,
    "analyzed":"此 三 結  幾 有 報  幾 無 報  "
  },
  {
    "segmentnr":"ZH_T26_1543_004:0784c15_18",
    "original":"此乃至九十八使，幾有報、幾無報？",
    "folio":4,
    "analyzed":"此 乃 至 九 十 八 使  幾 有 報  幾 無 報  "
  },
  {
    "segmentnr":"ZH_T26_1543_004:0784c16_11",
    "original":"此三結，幾見諦斷、幾思惟斷；",
    "folio":4,
    "analyzed":"此 三 結  幾 見 諦 斷  幾 思 惟 斷  "
  },
  {
    "segmentnr":"ZH_T26_1543_004:0784c17_8",
    "original":"此乃至九十八使，幾見諦斷、幾思惟斷？",
    "folio":4,
    "analyzed":"此 乃 至 九 十 八 使  幾 見 諦 斷  幾 思 惟 斷  "
  },
  {
    "segmentnr":"ZH_T26_1543_004:0784c18_11",
    "original":"此三結，幾見苦諦斷、幾見習盡道諦斷、幾思惟斷；",
    "folio":4,
    "analyzed":"此 三 結  幾 見 苦 諦 斷  幾 見 習 盡 道 諦 斷  幾 思 惟 斷  "
  },
  {
    "segmentnr":"ZH_T26_1543_004:0784c19_18",
    "original":"此乃至九十八使，幾見苦諦斷、幾見習盡道諦斷、幾思惟斷？",
    "folio":4,
    "analyzed":"此 乃 至 九 十 八 使  幾 見 苦 諦 斷  幾 見 習 盡 道 諦 斷  幾 思 惟 斷  "
  },
  {
    "segmentnr":"ZH_T26_1543_004:0784c20_9",
    "original":"此三結，幾見、幾不見；",
    "folio":4,
    "analyzed":"此 三 結  幾 見  幾 不 見  "
  },
  {
    "segmentnr":"ZH_T26_1543_004:0784c21_2",
    "original":"此乃至九十八使，幾見、幾不見？",
    "folio":4,
    "analyzed":"此 乃 至 九 十 八 使  幾 見  幾 不 見  "
  },
  {
    "segmentnr":"ZH_T26_1543_004:0784c22_4",
    "original":"此三結，幾有覺有觀、幾無覺有觀、幾無覺無觀；",
    "folio":4,
    "analyzed":"此 三 結  幾 有 覺 有 觀  幾 無 覺 有 觀  幾 無 覺 無 觀  "
  },
  {
    "segmentnr":"ZH_T26_1543_004:0784c23_10",
    "original":"此乃至九十八使，幾有覺有觀、幾無覺有觀、幾無覺無觀？",
    "folio":4,
    "analyzed":"此 乃 至 九 十 八 使  幾 有 覺 有 觀  幾 無 覺 有 觀  幾 無 覺 無 觀  "
  },
  {
    "segmentnr":"ZH_T26_1543_004:0784c25_4",
    "original":"此三結，幾樂根相應、幾苦根相應、幾喜根相應、幾憂根相應、幾護根相應；",
    "folio":4,
    "analyzed":"此 三 結  幾 樂 根 相 應  幾 苦 根 相 應  幾 喜 根 相 應  幾 憂 根 相 應  幾 護 根 相 應  "
  },
  {
    "segmentnr":"ZH_T26_1543_004:0784c27_2",
    "original":"此乃至九十八使，幾樂根相應、幾苦根相應、幾喜根相應、幾憂根相應、幾護根相應？",
    "folio":4,
    "analyzed":"此 乃 至 九 十 八 使  幾 樂 根 相 應  幾 苦 根 相 應  幾 喜 根 相 應  幾 憂 根 相 應  幾 護 根 相 應  "
  },
  {
    "segmentnr":"ZH_T26_1543_004:0784c28_1",
    "original":"此三結，幾欲界繫、幾色界繫、幾無色界繫；",
    "folio":4,
    "analyzed":"此 三 結  幾 欲 界 繫  幾 色 界 繫  幾 無 色 界 繫  "
  },
  {
    "segmentnr":"ZH_T26_1543_004:0784c29_5",
    "original":"此乃至九十八使，幾欲界繫、幾色界繫、幾無色界繫？",
    "folio":4,
    "analyzed":"此 乃 至 九 十 八 使  幾 欲 界 繫  幾 色 界 繫  幾 無 色 界 繫  "
  },
  {
    "segmentnr":"ZH_T26_1543_004:0785a01_1",
    "original":"諸結是欲界者，此結在欲界耶？",
    "folio":4,
    "analyzed":"諸 結 是 欲 界 者  此 結 在 欲 界 耶  "
  },
  {
    "segmentnr":"ZH_T26_1543_004:0785a01_13",
    "original":"設在欲界結，是欲界結耶？",
    "folio":4,
    "analyzed":"設 在 欲 界 結  是 欲 界 結 耶  "
  },
  {
    "segmentnr":"ZH_T26_1543_004:0785a02_13",
    "original":"所有結是色無色界結，此結在色無色界耶？",
    "folio":4,
    "analyzed":"所 有 結 是 色無色界 結  此 結 在 色無色界 耶  "
  },
  {
    "segmentnr":"ZH_T26_1543_004:0785a03_10",
    "original":"設結在色無色界，是色無色界結耶？",
    "folio":4,
    "analyzed":"設 結 在 色無色界  是 色無色界 結 耶  "
  },
  {
    "segmentnr":"ZH_T26_1543_004:0785a04_7",
    "original":"所有結非欲界結，此結不在欲界耶？",
    "folio":4,
    "analyzed":"所 有 結 非 欲 界 結  此 結 不 在 欲 界 耶  "
  },
  {
    "segmentnr":"ZH_T26_1543_004:0785a05_2",
    "original":"設不在欲界，此結非欲界結耶？",
    "folio":4,
    "analyzed":"設 不 在 欲 界  此 結 非 欲 界 結 耶  "
  },
  {
    "segmentnr":"ZH_T26_1543_004:0785a06_4",
    "original":"所有結不是色無色界，此不在色無色界結耶？",
    "folio":4,
    "analyzed":"所 有 結 不 是 色無色界  此 不 在 色無色界 結 耶  "
  },
  {
    "segmentnr":"ZH_T26_1543_004:0785a07_4",
    "original":"設結不在色無色界，此非色無色界結耶？",
    "folio":4,
    "analyzed":"設 結 不 在 色無色界  此 非 色無色界 結 耶  "
  },
  {
    "segmentnr":"ZH_T26_1543_004:0785a08_2",
    "original":"見諦成就世尊弟子，色未盡，為色繫耶？",
    "folio":4,
    "analyzed":"見 諦 成 就 世 尊 弟 子  色 未 盡  為 色 繫 耶  "
  },
  {
    "segmentnr":"ZH_T26_1543_004:0785a08_13",
    "original":"設為色繫，此色未盡耶？",
    "folio":4,
    "analyzed":"設 為 色 繫  此 色 未 盡 耶  "
  },
  {
    "segmentnr":"ZH_T26_1543_004:0785a09_7",
    "original":"若痛想行識未盡，為識所繫耶？",
    "folio":4,
    "analyzed":"若 痛 想 行 識 未 盡  為 識 所 繫 耶  "
  },
  {
    "segmentnr":"ZH_T26_1543_004:0785a09_18",
    "original":"設為識所繫，識未盡耶？",
    "folio":4,
    "analyzed":"設 為 識 所 繫  識 未 盡 耶  "
  },
  {
    "segmentnr":"ZH_T26_1543_004:0785a10_15",
    "original":"見諦成就世尊弟子，色已盡，此色解耶？",
    "folio":4,
    "analyzed":"見 諦 成 就 世 尊 弟 子  色 已 盡  此 色 解 耶  "
  },
  {
    "segmentnr":"ZH_T26_1543_004:0785a11_4",
    "original":"設色解者，此色盡耶？",
    "folio":4,
    "analyzed":"設 色 解 者  此 色 盡 耶  "
  },
  {
    "segmentnr":"ZH_T26_1543_004:0785a11_16",
    "original":"若痛想行識盡，此識解耶？",
    "folio":4,
    "analyzed":"若 痛 想 行 識 盡  此 識 解 耶  "
  },
  {
    "segmentnr":"ZH_T26_1543_004:0785a12_6",
    "original":"設識解者，此識盡耶？",
    "folio":4,
    "analyzed":"設 識 解 者  此 識 盡 耶  "
  },
  {
    "segmentnr":"ZH_T26_1543_004:0785a13_2",
    "original":"五人，堅信、堅法、信解脫、見到、身證。",
    "folio":4,
    "analyzed":"五 人  堅 信  堅 法  信 解 脫  見 到  身 證  "
  },
  {
    "segmentnr":"ZH_T26_1543_004:0785a13_19",
    "original":"堅信人於此三結，幾成就、幾不成就？",
    "folio":4,
    "analyzed":"堅 信 人 於 此 三 結  幾 成 就  幾 不 成 就  "
  },
  {
    "segmentnr":"ZH_T26_1543_004:0785a14_15",
    "original":"此乃至九十八使，幾成就、幾不成就。",
    "folio":4,
    "analyzed":"此 乃 至 九 十 八 使  幾 成 就  幾 不 成 就  "
  },
  {
    "segmentnr":"ZH_T26_1543_004:0785a15_14",
    "original":"乃至身證人，此三結，幾成就、幾不成就；",
    "folio":4,
    "analyzed":"乃 至 身 證 人  此 三 結  幾 成 就  幾 不 成 就  "
  },
  {
    "segmentnr":"ZH_T26_1543_004:0785a16_10",
    "original":"此乃至九十八使，幾成就、幾不成就。",
    "folio":4,
    "analyzed":"此 乃 至 九 十 八 使  幾 成 就  幾 不 成 就  "
  },
  {
    "segmentnr":"ZH_T26_1543_004:0785a16_20",
    "original":"身見，彼身見幾緣緣？",
    "folio":4,
    "analyzed":"身 見  彼 身 見 幾 緣 緣  "
  },
  {
    "segmentnr":"ZH_T26_1543_004:0785a18_2",
    "original":"身見、戒、盜、疑，乃至無色界思惟所斷無明使幾緣緣？",
    "folio":4,
    "analyzed":"身 見  戒  盜  疑  乃 至 無 色 界 思惟所斷 無 明 使 幾 緣 緣  "
  },
  {
    "segmentnr":"ZH_T26_1543_004:0785a19_10",
    "original":"無色界思惟所斷無明使，彼無色界思惟所斷無明使，幾緣緣？",
    "folio":4,
    "analyzed":"無 色 界 思惟所斷 無 明 使  彼 無 色 界 思惟所斷 無 明 使  幾 緣 緣  "
  },
  {
    "segmentnr":"ZH_T26_1543_004:0785a21_7",
    "original":"無色界思惟所斷無明使，欲界身見、戒、盜、疑，乃至無色界思惟所斷慢使，幾緣緣？",
    "folio":4,
    "analyzed":"無 色 界 思惟所斷 無 明 使  欲 界 身 見  戒  盜  疑  乃 至 無 色 界 思惟所斷 慢 使  幾 緣 緣  "
  },
  {
    "segmentnr":"ZH_T26_1543_004:0785a21_15",
    "original":"此章義願具演說。",
    "folio":4,
    "analyzed":"此 章 義 願 具 演 說  "
  },
  {
    "segmentnr":"ZH_T26_1543_004:0785a22_15",
    "original":"三結乃至九十八使，彼三結幾不善、幾無記？",
    "folio":4,
    "analyzed":"三 結 乃 至 九 十 八 使  彼 三 結 幾 不 善  幾 無 記  "
  },
  {
    "segmentnr":"ZH_T26_1543_004:0785a22_18",
    "original":"答曰：",
    "folio":4,
    "analyzed":"答 曰  "
  },
  {
    "segmentnr":"ZH_T26_1543_004:0785a23_6",
    "original":"一無記，二當分別。",
    "folio":4,
    "analyzed":"一 無 記  二 當 分 別  "
  },
  {
    "segmentnr":"ZH_T26_1543_004:0785a24_6",
    "original":"戒、盜、疑在欲界者則不善，在色無色界則無記。",
    "folio":4,
    "analyzed":"戒  盜  疑 在 欲 界 者 則 不 善  在 色無色界 則 無 記  "
  },
  {
    "segmentnr":"ZH_T26_1543_004:0785a24_17",
    "original":"貪、瞋恚、愚癡定不善。",
    "folio":4,
    "analyzed":"貪  瞋 恚  愚 癡 定 不 善  "
  },
  {
    "segmentnr":"ZH_T26_1543_004:0785a25_10",
    "original":"有漏中，一無記，二當分別。",
    "folio":4,
    "analyzed":"有 漏 中  一 無 記  二 當 分 別  "
  },
  {
    "segmentnr":"ZH_T26_1543_004:0785a25_21",
    "original":"欲漏，或不善、或無記。",
    "folio":4,
    "analyzed":"欲 漏  或 不 善  或 無 記  "
  },
  {
    "segmentnr":"ZH_T26_1543_004:0785a26_4",
    "original":"云何不善？",
    "folio":4,
    "analyzed":"云 何 不 善  "
  },
  {
    "segmentnr":"ZH_T26_1543_004:0785a26_7",
    "original":"答曰：",
    "folio":4,
    "analyzed":"答 曰  "
  },
  {
    "segmentnr":"ZH_T26_1543_004:0785a27_2",
    "original":"無慚、無愧彼相應欲漏，是謂不善。",
    "folio":4,
    "analyzed":"無 慚  無 愧 彼 相 應 欲 漏  是 謂 不 善  "
  },
  {
    "segmentnr":"ZH_T26_1543_004:0785a27_7",
    "original":"云何無記？",
    "folio":4,
    "analyzed":"云 何 無 記  "
  },
  {
    "segmentnr":"ZH_T26_1543_004:0785a27_10",
    "original":"答曰：",
    "folio":4,
    "analyzed":"答 曰  "
  },
  {
    "segmentnr":"ZH_T26_1543_004:0785a28_4",
    "original":"無慚、無愧不相應欲漏，是謂無記。",
    "folio":4,
    "analyzed":"無 慚  無 愧 不 相 應 欲 漏  是 謂 無 記  "
  },
  {
    "segmentnr":"ZH_T26_1543_004:0785a28_16",
    "original":"無明漏，或不善、或無記。",
    "folio":4,
    "analyzed":"無 明 漏  或 不 善  或 無 記  "
  },
  {
    "segmentnr":"ZH_T26_1543_004:0785a28_21",
    "original":"云何不善？",
    "folio":4,
    "analyzed":"云 何 不 善  "
  },
  {
    "segmentnr":"ZH_T26_1543_004:0785a29_2",
    "original":"答曰：",
    "folio":4,
    "analyzed":"答 曰  "
  },
  {
    "segmentnr":"ZH_T26_1543_004:0785a29_18",
    "original":"無慚、無愧相應無明漏，是謂不善。",
    "folio":4,
    "analyzed":"無 慚  無 愧 相 應 無 明 漏  是 謂 不 善  "
  },
  {
    "segmentnr":"ZH_T26_1543_004:0785b01_2",
    "original":"云何無記？",
    "folio":4,
    "analyzed":"云 何 無 記  "
  },
  {
    "segmentnr":"ZH_T26_1543_004:0785b01_5",
    "original":"答曰：",
    "folio":4,
    "analyzed":"答 曰  "
  },
  {
    "segmentnr":"ZH_T26_1543_004:0785b02_1",
    "original":"無慚、無愧不相應無明漏，是謂無記。",
    "folio":4,
    "analyzed":"無 慚  無 愧 不 相 應 無 明 漏  是 謂 無 記  "
  },
  {
    "segmentnr":"ZH_T26_1543_004:0785b02_13",
    "original":"流中，一無記，三當分別。",
    "folio":4,
    "analyzed":"流 中  一 無 記  三 當 分 別  "
  },
  {
    "segmentnr":"ZH_T26_1543_004:0785b03_1",
    "original":"欲流，或不善、或無記。",
    "folio":4,
    "analyzed":"欲 流  或 不 善  或 無 記  "
  },
  {
    "segmentnr":"ZH_T26_1543_004:0785b03_6",
    "original":"云何不善？",
    "folio":4,
    "analyzed":"云 何 不 善  "
  },
  {
    "segmentnr":"ZH_T26_1543_004:0785b03_9",
    "original":"答曰：",
    "folio":4,
    "analyzed":"答 曰  "
  },
  {
    "segmentnr":"ZH_T26_1543_004:0785b04_3",
    "original":"無慚、無愧彼相應欲流，是謂不善。",
    "folio":4,
    "analyzed":"無 慚  無 愧 彼 相 應 欲 流  是 謂 不 善  "
  },
  {
    "segmentnr":"ZH_T26_1543_004:0785b04_8",
    "original":"云何無記？",
    "folio":4,
    "analyzed":"云 何 無 記  "
  },
  {
    "segmentnr":"ZH_T26_1543_004:0785b04_11",
    "original":"答曰：",
    "folio":4,
    "analyzed":"答 曰  "
  },
  {
    "segmentnr":"ZH_T26_1543_004:0785b05_6",
    "original":"無慚、無愧不相應欲流，是謂無記。",
    "folio":4,
    "analyzed":"無 慚  無 愧 不 相 應 欲 流  是 謂 無 記  "
  },
  {
    "segmentnr":"ZH_T26_1543_004:0785b05_18",
    "original":"無明流，或不善、或無記。",
    "folio":4,
    "analyzed":"無 明 流  或 不 善  或 無 記  "
  },
  {
    "segmentnr":"ZH_T26_1543_004:0785b06_1",
    "original":"云何不善？",
    "folio":4,
    "analyzed":"云 何 不 善  "
  },
  {
    "segmentnr":"ZH_T26_1543_004:0785b06_4",
    "original":"答曰：",
    "folio":4,
    "analyzed":"答 曰  "
  },
  {
    "segmentnr":"ZH_T26_1543_004:0785b06_20",
    "original":"無慚、無愧相應無明流，是謂不善。",
    "folio":4,
    "analyzed":"無 慚  無 愧 相 應 無 明 流  是 謂 不 善  "
  },
  {
    "segmentnr":"ZH_T26_1543_004:0785b07_3",
    "original":"云何無記？",
    "folio":4,
    "analyzed":"云 何 無 記  "
  },
  {
    "segmentnr":"ZH_T26_1543_004:0785b07_6",
    "original":"答曰：",
    "folio":4,
    "analyzed":"答 曰  "
  },
  {
    "segmentnr":"ZH_T26_1543_004:0785b08_2",
    "original":"無慚無愧不相應無明流，是謂無記。",
    "folio":4,
    "analyzed":"無慚無愧 不 相 應 無 明 流  是 謂 無 記  "
  },
  {
    "segmentnr":"ZH_T26_1543_004:0785b08_13",
    "original":"見流，或不善、或無記。",
    "folio":4,
    "analyzed":"見 流  或 不 善  或 無 記  "
  },
  {
    "segmentnr":"ZH_T26_1543_004:0785b08_18",
    "original":"云何不善？",
    "folio":4,
    "analyzed":"云 何 不 善  "
  },
  {
    "segmentnr":"ZH_T26_1543_004:0785b08_21",
    "original":"答曰：",
    "folio":4,
    "analyzed":"答 曰  "
  },
  {
    "segmentnr":"ZH_T26_1543_004:0785b09_8",
    "original":"欲界三見，是謂不善。",
    "folio":4,
    "analyzed":"欲 界 三 見  是 謂 不 善  "
  },
  {
    "segmentnr":"ZH_T26_1543_004:0785b09_13",
    "original":"云何無記？",
    "folio":4,
    "analyzed":"云 何 無 記  "
  },
  {
    "segmentnr":"ZH_T26_1543_004:0785b09_16",
    "original":"答曰：",
    "folio":4,
    "analyzed":"答 曰  "
  },
  {
    "segmentnr":"ZH_T26_1543_004:0785b10_11",
    "original":"欲界二見、色無色界五見，是謂無記。",
    "folio":4,
    "analyzed":"欲 界 二 見  色無色界 五 見  是 謂 無 記  "
  },
  {
    "segmentnr":"ZH_T26_1543_004:0785b10_16",
    "original":"軛亦如是。",
    "folio":4,
    "analyzed":"軛 亦 如 是  "
  },
  {
    "segmentnr":"ZH_T26_1543_004:0785b11_8",
    "original":"受中，一無記，三當分別。",
    "folio":4,
    "analyzed":"受 中  一 無 記  三 當 分 別  "
  },
  {
    "segmentnr":"ZH_T26_1543_004:0785b11_19",
    "original":"欲受，或不善、或無記。",
    "folio":4,
    "analyzed":"欲 受  或 不 善  或 無 記  "
  },
  {
    "segmentnr":"ZH_T26_1543_004:0785b12_2",
    "original":"云何不善？",
    "folio":4,
    "analyzed":"云 何 不 善  "
  },
  {
    "segmentnr":"ZH_T26_1543_004:0785b12_5",
    "original":"答曰：",
    "folio":4,
    "analyzed":"答 曰  "
  },
  {
    "segmentnr":"ZH_T26_1543_004:0785b12_21",
    "original":"無慚、無愧彼相應欲受，是謂不善。",
    "folio":4,
    "analyzed":"無 慚  無 愧 彼 相 應 欲 受  是 謂 不 善  "
  },
  {
    "segmentnr":"ZH_T26_1543_004:0785b13_4",
    "original":"云何無記？",
    "folio":4,
    "analyzed":"云 何 無 記  "
  },
  {
    "segmentnr":"ZH_T26_1543_004:0785b13_7",
    "original":"答曰：",
    "folio":4,
    "analyzed":"答 曰  "
  },
  {
    "segmentnr":"ZH_T26_1543_004:0785b14_2",
    "original":"無慚、無愧不相應欲受，是謂無記。",
    "folio":4,
    "analyzed":"無 慚  無 愧 不 相 應 欲 受  是 謂 無 記  "
  },
  {
    "segmentnr":"ZH_T26_1543_004:0785b14_13",
    "original":"戒受，或不善、或無記。",
    "folio":4,
    "analyzed":"戒 受  或 不 善  或 無 記  "
  },
  {
    "segmentnr":"ZH_T26_1543_004:0785b14_18",
    "original":"云何不善？",
    "folio":4,
    "analyzed":"云 何 不 善  "
  },
  {
    "segmentnr":"ZH_T26_1543_004:0785b14_21",
    "original":"答曰：",
    "folio":4,
    "analyzed":"答 曰  "
  },
  {
    "segmentnr":"ZH_T26_1543_004:0785b15_8",
    "original":"在欲界者是謂不善。",
    "folio":4,
    "analyzed":"在 欲 界 者 是 謂 不 善  "
  },
  {
    "segmentnr":"ZH_T26_1543_004:0785b15_13",
    "original":"云何無記？",
    "folio":4,
    "analyzed":"云 何 無 記  "
  },
  {
    "segmentnr":"ZH_T26_1543_004:0785b15_16",
    "original":"答曰：",
    "folio":4,
    "analyzed":"答 曰  "
  },
  {
    "segmentnr":"ZH_T26_1543_004:0785b16_8",
    "original":"在色無色界者是謂無記。",
    "folio":4,
    "analyzed":"在 色無色界 者 是 謂 無 記  "
  },
  {
    "segmentnr":"ZH_T26_1543_004:0785b16_19",
    "original":"見受，或不善、或無記。",
    "folio":4,
    "analyzed":"見 受  或 不 善  或 無 記  "
  },
  {
    "segmentnr":"ZH_T26_1543_004:0785b17_4",
    "original":"云何不善？",
    "folio":4,
    "analyzed":"云 何 不 善  "
  },
  {
    "segmentnr":"ZH_T26_1543_004:0785b17_7",
    "original":"答曰：",
    "folio":4,
    "analyzed":"答 曰  "
  },
  {
    "segmentnr":"ZH_T26_1543_004:0785b17_17",
    "original":"欲界二見，是謂不善。",
    "folio":4,
    "analyzed":"欲 界 二 見  是 謂 不 善  "
  },
  {
    "segmentnr":"ZH_T26_1543_004:0785b18_1",
    "original":"云何無記？",
    "folio":4,
    "analyzed":"云 何 無 記  "
  },
  {
    "segmentnr":"ZH_T26_1543_004:0785b18_4",
    "original":"答曰：",
    "folio":4,
    "analyzed":"答 曰  "
  },
  {
    "segmentnr":"ZH_T26_1543_004:0785b19_1",
    "original":"欲界二見、色無色界四見，是謂無記。",
    "folio":4,
    "analyzed":"欲 界 二 見  色無色界 四 見  是 謂 無 記  "
  },
  {
    "segmentnr":"ZH_T26_1543_004:0785b19_13",
    "original":"縛中，二不善，二當分別。",
    "folio":4,
    "analyzed":"縛 中  二 不 善  二 當 分 別  "
  },
  {
    "segmentnr":"ZH_T26_1543_004:0785b20_8",
    "original":"戒盜身縛、我見身縛，在欲界是不善；",
    "folio":4,
    "analyzed":"戒 盜 身 縛  我 見 身 縛  在 欲 界 是 不 善  "
  },
  {
    "segmentnr":"ZH_T26_1543_004:0785b20_17",
    "original":"在色無色界是無記。",
    "folio":4,
    "analyzed":"在 色無色界 是 無 記  "
  },
  {
    "segmentnr":"ZH_T26_1543_004:0785b21_11",
    "original":"蓋及瞋恚、慳、嫉結定不善。",
    "folio":4,
    "analyzed":"蓋 及 瞋 恚  慳  嫉 結 定 不 善  "
  },
  {
    "segmentnr":"ZH_T26_1543_004:0785b22_3",
    "original":"愛結、憍慢結在欲界，是不善；",
    "folio":4,
    "analyzed":"愛 結  憍 慢 結 在 欲 界  是 不 善  "
  },
  {
    "segmentnr":"ZH_T26_1543_004:0785b22_12",
    "original":"在色無色界是無記。",
    "folio":4,
    "analyzed":"在 色無色界 是 無 記  "
  },
  {
    "segmentnr":"ZH_T26_1543_004:0785b23_11",
    "original":"五下分結中，二不善，一無記，二當分別。",
    "folio":4,
    "analyzed":"五下分結 中  二 不 善  一 無 記  二 當 分 別  "
  },
  {
    "segmentnr":"ZH_T26_1543_004:0785b24_10",
    "original":"戒、盜、疑在欲界是不善，在色無色界是無記。",
    "folio":4,
    "analyzed":"戒  盜  疑 在 欲 界 是 不 善  在 色無色界 是 無 記  "
  },
  {
    "segmentnr":"ZH_T26_1543_004:0785b25_1",
    "original":"見中，二無記，三當分別。",
    "folio":4,
    "analyzed":"見 中  二 無 記  三 當 分 別  "
  },
  {
    "segmentnr":"ZH_T26_1543_004:0785b26_5",
    "original":"邪見、見盜、戒盜在欲界是不善，在色無色界是無記。",
    "folio":4,
    "analyzed":"邪 見  見 盜  戒 盜 在 欲 界 是 不 善  在 色無色界 是 無 記  "
  },
  {
    "segmentnr":"ZH_T26_1543_004:0785b26_19",
    "original":"六身愛中，二不善，四當分別。",
    "folio":4,
    "analyzed":"六 身 愛 中  二 不 善  四 當 分 別  "
  },
  {
    "segmentnr":"ZH_T26_1543_004:0785b28_2",
    "original":"眼更愛、耳身更愛在欲界是不善，在色界是無記。",
    "folio":4,
    "analyzed":"眼 更 愛  耳 身 更 愛 在 欲 界 是 不 善  在 色 界 是 無 記  "
  },
  {
    "segmentnr":"ZH_T26_1543_004:0785b29_2",
    "original":"意更愛在欲界是不善，在色無色界是無記。",
    "folio":4,
    "analyzed":"意 更 愛 在 欲 界 是 不 善  在 色無色界 是 無 記  "
  },
  {
    "segmentnr":"ZH_T26_1543_004:0785b29_19",
    "original":"七使中，二不善，一無記，四當分別。",
    "folio":4,
    "analyzed":"七 使 中  二 不 善  一 無 記  四 當 分 別  "
  },
  {
    "segmentnr":"ZH_T26_1543_004:0785c01_19",
    "original":"憍慢使、疑使在欲界是不善，在色無色界是無記。",
    "folio":4,
    "analyzed":"憍 慢 使  疑 使 在 欲 界 是 不 善  在 色無色界 是 無 記  "
  },
  {
    "segmentnr":"ZH_T26_1543_004:0785c02_11",
    "original":"無明使，或不善、或無記。",
    "folio":4,
    "analyzed":"無 明 使  或 不 善  或 無 記  "
  },
  {
    "segmentnr":"ZH_T26_1543_004:0785c02_16",
    "original":"云何不善？",
    "folio":4,
    "analyzed":"云 何 不 善  "
  },
  {
    "segmentnr":"ZH_T26_1543_004:0785c02_19",
    "original":"答曰：",
    "folio":4,
    "analyzed":"答 曰  "
  },
  {
    "segmentnr":"ZH_T26_1543_004:0785c03_12",
    "original":"無慚、無愧相應無明使，是謂不善。",
    "folio":4,
    "analyzed":"無 慚  無 愧 相 應 無 明 使  是 謂 不 善  "
  },
  {
    "segmentnr":"ZH_T26_1543_004:0785c03_17",
    "original":"云何無記？",
    "folio":4,
    "analyzed":"云 何 無 記  "
  },
  {
    "segmentnr":"ZH_T26_1543_004:0785c03_20",
    "original":"答曰：",
    "folio":4,
    "analyzed":"答 曰  "
  },
  {
    "segmentnr":"ZH_T26_1543_004:0785c04_16",
    "original":"無慚、無愧不相應無明使，是謂無記。",
    "folio":4,
    "analyzed":"無 慚  無 愧 不 相 應 無 明 使  是 謂 無 記  "
  },
  {
    "segmentnr":"ZH_T26_1543_004:0785c05_6",
    "original":"見使，或不善、或無記。",
    "folio":4,
    "analyzed":"見 使  或 不 善  或 無 記  "
  },
  {
    "segmentnr":"ZH_T26_1543_004:0785c05_11",
    "original":"云何不善？",
    "folio":4,
    "analyzed":"云 何 不 善  "
  },
  {
    "segmentnr":"ZH_T26_1543_004:0785c05_14",
    "original":"答曰：",
    "folio":4,
    "analyzed":"答 曰  "
  },
  {
    "segmentnr":"ZH_T26_1543_004:0785c06_2",
    "original":"欲界三見，是謂不善。",
    "folio":4,
    "analyzed":"欲 界 三 見  是 謂 不 善  "
  },
  {
    "segmentnr":"ZH_T26_1543_004:0785c06_7",
    "original":"云何無記？",
    "folio":4,
    "analyzed":"云 何 無 記  "
  },
  {
    "segmentnr":"ZH_T26_1543_004:0785c06_10",
    "original":"答曰：",
    "folio":4,
    "analyzed":"答 曰  "
  },
  {
    "segmentnr":"ZH_T26_1543_004:0785c07_6",
    "original":"欲界二見、色無色界五見，是謂無記。",
    "folio":4,
    "analyzed":"欲 界 二 見  色無色界 五 見  是 謂 無 記  "
  },
  {
    "segmentnr":"ZH_T26_1543_004:0785c08_4",
    "original":"九結中，三不善，六當分別分別不善及無記也。",
    "folio":4,
    "analyzed":"九 結 中  三 不 善  六 當 分 別 分 別 不 善及無記 也  "
  },
  {
    "segmentnr":"ZH_T26_1543_004:0785c09_8",
    "original":"愛結、憍慢結、失願結、疑結在欲界是不善，在色無色界是無記。",
    "folio":4,
    "analyzed":"愛 結  憍 慢 結  失 願 結  疑 結 在 欲 界 是 不 善  在 色無色界 是 無 記  "
  },
  {
    "segmentnr":"ZH_T26_1543_004:0785c09_20",
    "original":"無明結，或不善，或無記。",
    "folio":4,
    "analyzed":"無 明 結  或 不 善  或 無 記  "
  },
  {
    "segmentnr":"ZH_T26_1543_004:0785c10_4",
    "original":"云何不善？",
    "folio":4,
    "analyzed":"云 何 不 善  "
  },
  {
    "segmentnr":"ZH_T26_1543_004:0785c10_7",
    "original":"答曰：",
    "folio":4,
    "analyzed":"答 曰  "
  },
  {
    "segmentnr":"ZH_T26_1543_004:0785c11_2",
    "original":"無慚、無愧相應無明結，是謂不善。",
    "folio":4,
    "analyzed":"無 慚  無 愧 相 應 無 明 結  是 謂 不 善  "
  },
  {
    "segmentnr":"ZH_T26_1543_004:0785c11_7",
    "original":"云何無記？",
    "folio":4,
    "analyzed":"云 何 無 記  "
  },
  {
    "segmentnr":"ZH_T26_1543_004:0785c11_10",
    "original":"答曰：",
    "folio":4,
    "analyzed":"答 曰  "
  },
  {
    "segmentnr":"ZH_T26_1543_004:0785c12_6",
    "original":"無慚、無愧不相應無明結，是謂無記。",
    "folio":4,
    "analyzed":"無 慚  無 愧 不 相 應 無 明 結  是 謂 無 記  "
  },
  {
    "segmentnr":"ZH_T26_1543_004:0785c12_17",
    "original":"見結，或不善、或無記。",
    "folio":4,
    "analyzed":"見 結  或 不 善  或 無 記  "
  },
  {
    "segmentnr":"ZH_T26_1543_004:0785c12_22",
    "original":"云何不善？",
    "folio":4,
    "analyzed":"云 何 不 善  "
  },
  {
    "segmentnr":"ZH_T26_1543_004:0785c13_2",
    "original":"答曰：",
    "folio":4,
    "analyzed":"答 曰  "
  },
  {
    "segmentnr":"ZH_T26_1543_004:0785c13_12",
    "original":"欲界一見，是謂不善。",
    "folio":4,
    "analyzed":"欲 界 一 見  是 謂 不 善  "
  },
  {
    "segmentnr":"ZH_T26_1543_004:0785c13_17",
    "original":"云何無記？",
    "folio":4,
    "analyzed":"云 何 無 記  "
  },
  {
    "segmentnr":"ZH_T26_1543_004:0785c13_20",
    "original":"答曰：",
    "folio":4,
    "analyzed":"答 曰  "
  },
  {
    "segmentnr":"ZH_T26_1543_004:0785c14_16",
    "original":"欲界二見、色無色界三見，是謂無記。",
    "folio":4,
    "analyzed":"欲 界 二 見  色無色界 三 見  是 謂 無 記  "
  },
  {
    "segmentnr":"ZH_T26_1543_004:0785c15_19",
    "original":"九十八使，三十三不善，六十四無記，一當分別。",
    "folio":4,
    "analyzed":"九 十 八 使  三 十 三 不 善  六 十四無記  一 當 分 別  "
  },
  {
    "segmentnr":"ZH_T26_1543_004:0785c16_16",
    "original":"欲界苦諦所斷無明使，或不善、或無記。",
    "folio":4,
    "analyzed":"欲 界 苦 諦 所 斷 無 明 使  或 不 善  或 無 記  "
  },
  {
    "segmentnr":"ZH_T26_1543_004:0785c17_1",
    "original":"云何不善？",
    "folio":4,
    "analyzed":"云 何 不 善  "
  },
  {
    "segmentnr":"ZH_T26_1543_004:0785c17_4",
    "original":"答曰：",
    "folio":4,
    "analyzed":"答 曰  "
  },
  {
    "segmentnr":"ZH_T26_1543_004:0785c17_20",
    "original":"無慚、無愧相應無明使，是謂不善。",
    "folio":4,
    "analyzed":"無 慚  無 愧 相 應 無 明 使  是 謂 不 善  "
  },
  {
    "segmentnr":"ZH_T26_1543_004:0785c18_4",
    "original":"云何無記？",
    "folio":4,
    "analyzed":"云 何 無 記  "
  },
  {
    "segmentnr":"ZH_T26_1543_004:0785c18_7",
    "original":"答曰：",
    "folio":4,
    "analyzed":"答 曰  "
  },
  {
    "segmentnr":"ZH_T26_1543_004:0785c19_8",
    "original":"無慚、無愧不相應無明使，是謂無記一門不善竟。",
    "folio":4,
    "analyzed":"無 慚  無 愧 不 相 應 無 明 使  是 謂 無 記 一 門 不 善 竟  "
  },
  {
    "segmentnr":"ZH_T26_1543_004:0785c19_20",
    "original":"此三結，幾有報、幾無報？",
    "folio":4,
    "analyzed":"此 三 結  幾 有 報  幾 無 報  "
  },
  {
    "segmentnr":"ZH_T26_1543_004:0785c19_23",
    "original":"答曰：",
    "folio":4,
    "analyzed":"答 曰  "
  },
  {
    "segmentnr":"ZH_T26_1543_004:0785c20_12",
    "original":"諸不善則有報，諸無記是無報。",
    "folio":4,
    "analyzed":"諸 不 善 則 有 報  諸 無 記 是 無 報  "
  },
  {
    "segmentnr":"ZH_T26_1543_004:0785c21_9",
    "original":"此乃至九十八使，幾有報、幾無報？",
    "folio":4,
    "analyzed":"此 乃 至 九 十 八 使  幾 有 報  幾 無 報  "
  },
  {
    "segmentnr":"ZH_T26_1543_004:0785c21_12",
    "original":"答曰：",
    "folio":4,
    "analyzed":"答 曰  "
  },
  {
    "segmentnr":"ZH_T26_1543_004:0785c22_10",
    "original":"諸不善是有報，諸無記是無報二門報無報竟。",
    "folio":4,
    "analyzed":"諸 不 善 是 有 報  諸 無 記 是 無 報 二 門 報 無 報 竟  "
  },
  {
    "segmentnr":"ZH_T26_1543_004:0785c23_1",
    "original":"此三結，幾見諦斷、幾思惟斷？",
    "folio":4,
    "analyzed":"此 三 結  幾 見 諦 斷  幾 思 惟 斷  "
  },
  {
    "segmentnr":"ZH_T26_1543_004:0785c23_4",
    "original":"答曰：",
    "folio":4,
    "analyzed":"答 曰  "
  },
  {
    "segmentnr":"ZH_T26_1543_004:0785c23_10",
    "original":"身見，見諦。",
    "folio":4,
    "analyzed":"身 見  見 諦  "
  },
  {
    "segmentnr":"ZH_T26_1543_004:0785c24_3",
    "original":"初二種，或見諦斷、或見諦思惟斷。",
    "folio":4,
    "analyzed":"初 二 種  或 見 諦 斷  或 見 諦 思 惟 斷  "
  },
  {
    "segmentnr":"ZH_T26_1543_004:0785c24_9",
    "original":"云何見諦斷？",
    "folio":4,
    "analyzed":"云 何 見 諦 斷  "
  },
  {
    "segmentnr":"ZH_T26_1543_004:0785c24_12",
    "original":"答曰：",
    "folio":4,
    "analyzed":"答 曰  "
  },
  {
    "segmentnr":"ZH_T26_1543_004:0785c26_1",
    "original":"若身見，尼維先、若那阿先、若繫，堅信堅法行苦忍斷，是謂見諦斷。",
    "folio":4,
    "analyzed":"若 身 見  尼 維 先  若 那 阿 先  若 繫  堅 信 堅 法 行 苦 忍 斷  是 謂 見 諦 斷  "
  },
  {
    "segmentnr":"ZH_T26_1543_004:0785c26_20",
    "original":"餘殘，若凡夫斷思惟斷進學分別意根似也；",
    "folio":4,
    "analyzed":"餘 殘  若 凡 夫 斷 思 惟 斷 進 學 分 別 意 根 似 也  "
  },
  {
    "segmentnr":"ZH_T26_1543_004:0785c27_5",
    "original":"世尊弟子斷見諦斷。",
    "folio":4,
    "analyzed":"世 尊 弟 子 斷 見 諦 斷  "
  },
  {
    "segmentnr":"ZH_T26_1543_004:0785c27_13",
    "original":"戒盜、疑，見諦。",
    "folio":4,
    "analyzed":"戒 盜  疑  見 諦  "
  },
  {
    "segmentnr":"ZH_T26_1543_004:0785c28_6",
    "original":"初二種，或見諦斷、或見諦思惟斷。",
    "folio":4,
    "analyzed":"初 二 種  或 見 諦 斷  或 見 諦 思 惟 斷  "
  },
  {
    "segmentnr":"ZH_T26_1543_004:0785c28_12",
    "original":"云何見諦斷？",
    "folio":4,
    "analyzed":"云 何 見 諦 斷  "
  },
  {
    "segmentnr":"ZH_T26_1543_004:0785c28_15",
    "original":"答曰：",
    "folio":4,
    "analyzed":"答 曰  "
  },
  {
    "segmentnr":"ZH_T26_1543_004:0786a01_4",
    "original":"若戒盜、疑，尼維先、若那阿先、若繫，堅信堅法行忍斷，是謂見諦斷。",
    "folio":4,
    "analyzed":"若 戒 盜  疑  尼 維 先  若 那 阿 先  若 繫  堅 信 堅 法 行 忍 斷  是 謂 見 諦 斷  "
  },
  {
    "segmentnr":"ZH_T26_1543_004:0786a01_15",
    "original":"餘殘，若凡夫斷思惟斷；",
    "folio":4,
    "analyzed":"餘 殘  若 凡 夫 斷 思 惟 斷  "
  },
  {
    "segmentnr":"ZH_T26_1543_004:0786a02_4",
    "original":"世尊弟子斷見諦斷。",
    "folio":4,
    "analyzed":"世 尊 弟 子 斷 見 諦 斷  "
  },
  {
    "segmentnr":"ZH_T26_1543_004:0786a02_18",
    "original":"貪、瞋恚、愚癡及欲漏，思惟。",
    "folio":4,
    "analyzed":"貪  瞋 恚  愚 癡 及 欲 漏  思 惟  "
  },
  {
    "segmentnr":"ZH_T26_1543_004:0786a03_11",
    "original":"初二種，或思惟斷、或見諦思惟斷。",
    "folio":4,
    "analyzed":"初 二 種  或 思 惟 斷  或 見 諦 思 惟 斷  "
  },
  {
    "segmentnr":"ZH_T26_1543_004:0786a03_17",
    "original":"云何思惟斷？",
    "folio":4,
    "analyzed":"云 何 思 惟 斷  "
  },
  {
    "segmentnr":"ZH_T26_1543_004:0786a03_20",
    "original":"答曰：",
    "folio":4,
    "analyzed":"答 曰  "
  },
  {
    "segmentnr":"ZH_T26_1543_004:0786a04_13",
    "original":"若學見迹思惟斷，是謂思惟斷。",
    "folio":4,
    "analyzed":"若 學 見 迹 思 惟 斷  是 謂 思 惟 斷  "
  },
  {
    "segmentnr":"ZH_T26_1543_004:0786a05_4",
    "original":"餘殘，若凡夫斷思惟斷；",
    "folio":4,
    "analyzed":"餘 殘  若 凡 夫 斷 思 惟 斷  "
  },
  {
    "segmentnr":"ZH_T26_1543_004:0786a05_13",
    "original":"世尊弟子斷見諦斷。",
    "folio":4,
    "analyzed":"世 尊 弟 子 斷 見 諦 斷  "
  },
  {
    "segmentnr":"ZH_T26_1543_004:0786a06_2",
    "original":"有漏、無明漏，見諦。",
    "folio":4,
    "analyzed":"有 漏  無 明 漏  見 諦  "
  },
  {
    "segmentnr":"ZH_T26_1543_004:0786a07_2",
    "original":"初三種，或見諦斷、或思惟斷、或見諦思惟斷。",
    "folio":4,
    "analyzed":"初 三 種  或 見 諦 斷  或 思 惟 斷  或 見 諦 思 惟 斷  "
  },
  {
    "segmentnr":"ZH_T26_1543_004:0786a07_8",
    "original":"云何見諦斷？",
    "folio":4,
    "analyzed":"云 何 見 諦 斷  "
  },
  {
    "segmentnr":"ZH_T26_1543_004:0786a07_11",
    "original":"答曰：",
    "folio":4,
    "analyzed":"答 曰  "
  },
  {
    "segmentnr":"ZH_T26_1543_004:0786a09_2",
    "original":"若有漏、無明漏，尼維先、若那阿先、若繫，堅信堅法行忍斷，是謂見諦斷。",
    "folio":4,
    "analyzed":"若 有 漏  無 明 漏  尼 維 先  若 那 阿 先  若 繫  堅 信 堅 法 行 忍 斷  是 謂 見 諦 斷  "
  },
  {
    "segmentnr":"ZH_T26_1543_004:0786a09_8",
    "original":"云何思惟斷？",
    "folio":4,
    "analyzed":"云 何 思 惟 斷  "
  },
  {
    "segmentnr":"ZH_T26_1543_004:0786a09_11",
    "original":"答曰：",
    "folio":4,
    "analyzed":"答 曰  "
  },
  {
    "segmentnr":"ZH_T26_1543_004:0786a10_4",
    "original":"若學見迹思惟斷，是謂思惟斷。",
    "folio":4,
    "analyzed":"若 學 見 迹 思 惟 斷  是 謂 思 惟 斷  "
  },
  {
    "segmentnr":"ZH_T26_1543_004:0786a10_15",
    "original":"餘殘，若凡夫斷思惟斷；",
    "folio":4,
    "analyzed":"餘 殘  若 凡 夫 斷 思 惟 斷  "
  },
  {
    "segmentnr":"ZH_T26_1543_004:0786a11_4",
    "original":"世尊弟子斷見諦斷。",
    "folio":4,
    "analyzed":"世 尊 弟 子 斷 見 諦 斷  "
  },
  {
    "segmentnr":"ZH_T26_1543_004:0786a11_12",
    "original":"流中欲流，思惟。",
    "folio":4,
    "analyzed":"流 中 欲 流  思 惟  "
  },
  {
    "segmentnr":"ZH_T26_1543_004:0786a12_4",
    "original":"初二種有流、無明流，見諦。",
    "folio":4,
    "analyzed":"初 二 種 有 流  無 明 流  見 諦  "
  },
  {
    "segmentnr":"ZH_T26_1543_004:0786a12_13",
    "original":"初三種見流，見諦。",
    "folio":4,
    "analyzed":"初 三 種 見 流  見 諦  "
  },
  {
    "segmentnr":"ZH_T26_1543_004:0786a12_21",
    "original":"初二種軛亦如是。",
    "folio":4,
    "analyzed":"初 二 種 軛 亦 如 是  "
  },
  {
    "segmentnr":"ZH_T26_1543_004:0786a13_7",
    "original":"受中欲受，思惟。",
    "folio":4,
    "analyzed":"受 中 欲 受  思 惟  "
  },
  {
    "segmentnr":"ZH_T26_1543_004:0786a13_19",
    "original":"初二種戒受、見受，見諦。",
    "folio":4,
    "analyzed":"初 二 種 戒 受  見 受  見 諦  "
  },
  {
    "segmentnr":"ZH_T26_1543_004:0786a14_5",
    "original":"初二種我受，見諦。",
    "folio":4,
    "analyzed":"初 二 種 我 受  見 諦  "
  },
  {
    "segmentnr":"ZH_T26_1543_004:0786a15_2",
    "original":"初三種縛中，欲愛身縛、瞋恚身縛，思惟。",
    "folio":4,
    "analyzed":"初 三 種 縛 中  欲 愛 身 縛  瞋 恚 身 縛  思 惟  "
  },
  {
    "segmentnr":"ZH_T26_1543_004:0786a15_18",
    "original":"初二種戒盜身縛、我見身縛，見諦。",
    "folio":4,
    "analyzed":"初 二 種 戒 盜 身 縛  我 見 身 縛  見 諦  "
  },
  {
    "segmentnr":"ZH_T26_1543_004:0786a16_17",
    "original":"初二種蓋中，貪欲、瞋恚、睡眠、掉，思惟。",
    "folio":4,
    "analyzed":"初 二 種 蓋 中  貪 欲  瞋 恚  睡 眠  掉  思 惟  "
  },
  {
    "segmentnr":"ZH_T26_1543_004:0786a17_3",
    "original":"初二種悔，定思惟斷。",
    "folio":4,
    "analyzed":"初 二 種 悔  定 思 惟 斷  "
  },
  {
    "segmentnr":"ZH_T26_1543_004:0786a17_14",
    "original":"疑蓋，若凡夫斷思惟斷；",
    "folio":4,
    "analyzed":"疑 蓋  若 凡 夫 斷 思 惟 斷  "
  },
  {
    "segmentnr":"ZH_T26_1543_004:0786a18_2",
    "original":"世尊弟子斷見諦斷。",
    "folio":4,
    "analyzed":"世 尊 弟 子 斷 見 諦 斷  "
  },
  {
    "segmentnr":"ZH_T26_1543_004:0786a18_11",
    "original":"結中瞋恚結，思惟。",
    "folio":4,
    "analyzed":"結 中 瞋 恚 結  思 惟  "
  },
  {
    "segmentnr":"ZH_T26_1543_004:0786a19_2",
    "original":"初二種愛結、憍慢結，見諦。",
    "folio":4,
    "analyzed":"初 二 種 愛 結  憍 慢 結  見 諦  "
  },
  {
    "segmentnr":"ZH_T26_1543_004:0786a19_16",
    "original":"初三種嫉結、慳結，定思惟斷。",
    "folio":4,
    "analyzed":"初 三 種 嫉 結  慳 結  定 思 惟 斷  "
  },
  {
    "segmentnr":"ZH_T26_1543_004:0786a20_9",
    "original":"五下分結中貪欲、瞋恚，思惟。",
    "folio":4,
    "analyzed":"五下分結 中 貪 欲  瞋 恚  思 惟  "
  },
  {
    "segmentnr":"ZH_T26_1543_004:0786a21_4",
    "original":"初二種身見、戒盜、疑及五見，見諦。",
    "folio":4,
    "analyzed":"初 二 種 身 見  戒 盜  疑 及 五 見  見 諦  "
  },
  {
    "segmentnr":"ZH_T26_1543_004:0786a21_21",
    "original":"初二種六身愛中，五身愛，定思惟斷。",
    "folio":4,
    "analyzed":"初 二 種 六 身 愛 中  五 身 愛  定 思 惟 斷  "
  },
  {
    "segmentnr":"ZH_T26_1543_004:0786a22_6",
    "original":"意更愛，見諦。",
    "folio":4,
    "analyzed":"意 更 愛  見 諦  "
  },
  {
    "segmentnr":"ZH_T26_1543_004:0786a23_2",
    "original":"初三種七使中，貪欲使、瞋恚使，思惟。",
    "folio":4,
    "analyzed":"初 三 種 七 使 中  貪 欲 使  瞋 恚 使  思 惟  "
  },
  {
    "segmentnr":"ZH_T26_1543_004:0786a23_20",
    "original":"初二種有愛使、憍慢使、無明使，見諦。",
    "folio":4,
    "analyzed":"初 二 種 有 愛 使  憍 慢 使  無 明 使  見 諦  "
  },
  {
    "segmentnr":"ZH_T26_1543_004:0786a24_10",
    "original":"初三種見使，疑使，見諦。",
    "folio":4,
    "analyzed":"初 三 種 見 使  疑 使  見 諦  "
  },
  {
    "segmentnr":"ZH_T26_1543_004:0786a25_1",
    "original":"初二種九結中瞋恚結，思惟。",
    "folio":4,
    "analyzed":"初 二 種 九 結 中 瞋 恚 結  思 惟  "
  },
  {
    "segmentnr":"ZH_T26_1543_004:0786a25_18",
    "original":"初二種愛結、憍慢結、無明結，見諦。",
    "folio":4,
    "analyzed":"初 二 種 愛 結  憍 慢 結  無 明 結  見 諦  "
  },
  {
    "segmentnr":"ZH_T26_1543_004:0786a26_12",
    "original":"初三種見結、失願結、疑結，見諦。",
    "folio":4,
    "analyzed":"初 三 種 見 結  失 願 結  疑 結  見 諦  "
  },
  {
    "segmentnr":"ZH_T26_1543_004:0786a27_2",
    "original":"初二種嫉結、慳結，定思惟斷。",
    "folio":4,
    "analyzed":"初 二 種 嫉 結  慳 結  定 思 惟 斷  "
  },
  {
    "segmentnr":"ZH_T26_1543_004:0786a28_1",
    "original":"九十八使中，二十八使見諦斷，十思惟斷。",
    "folio":4,
    "analyzed":"九 十 八 使 中  二 十 八 使 見 諦 斷  十 思 惟 斷  "
  },
  {
    "segmentnr":"ZH_T26_1543_004:0786a28_12",
    "original":"餘殘，若凡夫斷思惟斷；",
    "folio":4,
    "analyzed":"餘 殘  若 凡 夫 斷 思 惟 斷  "
  },
  {
    "segmentnr":"ZH_T26_1543_004:0786a29_7",
    "original":"世尊弟子斷見諦斷三門見諦竟也。",
    "folio":4,
    "analyzed":"世 尊 弟 子 斷 見 諦 斷 三 門 見 諦 竟 也  "
  },
  {
    "segmentnr":"ZH_T26_1543_004:0786b01_6",
    "original":"此三結，幾見苦諦斷、幾見習盡道諦斷、幾思惟斷？",
    "folio":4,
    "analyzed":"此 三 結  幾 見 苦 諦 斷  幾 見 習 盡 道 諦 斷  幾 思 惟 斷  "
  },
  {
    "segmentnr":"ZH_T26_1543_004:0786b01_9",
    "original":"答曰：",
    "folio":4,
    "analyzed":"答 曰  "
  },
  {
    "segmentnr":"ZH_T26_1543_004:0786b01_16",
    "original":"身見，見苦斷。",
    "folio":4,
    "analyzed":"身 見  見 苦 斷  "
  },
  {
    "segmentnr":"ZH_T26_1543_004:0786b02_9",
    "original":"戒盜有二行，或見苦斷、或見道斷。",
    "folio":4,
    "analyzed":"戒 盜 有 二 行  或 見 苦 斷  或 見 道 斷  "
  },
  {
    "segmentnr":"ZH_T26_1543_004:0786b03_5",
    "original":"疑有四行，或見苦斷、或見習盡道斷。",
    "folio":4,
    "analyzed":"疑 有 四 行  或 見 苦 斷  或 見 習 盡 道 斷  "
  },
  {
    "segmentnr":"ZH_T26_1543_004:0786b04_16",
    "original":"貪、瞋恚、愚癡、欲漏、有漏、無明漏、欲流、有流、無明流五行，見流四行。",
    "folio":4,
    "analyzed":"貪  瞋 恚  愚 癡  欲 漏  有 漏  無 明 漏  欲 流  有 流  無 明 流 五 行  見 流 四 行  "
  },
  {
    "segmentnr":"ZH_T26_1543_004:0786b05_1",
    "original":"軛亦如是。",
    "folio":4,
    "analyzed":"軛 亦 如 是  "
  },
  {
    "segmentnr":"ZH_T26_1543_004:0786b05_22",
    "original":"受中，欲受、我受五行，戒受二行，見受四行。",
    "folio":4,
    "analyzed":"受 中  欲 受  我 受 五 行  戒 受 二 行  見 受 四 行  "
  },
  {
    "segmentnr":"ZH_T26_1543_004:0786b07_8",
    "original":"縛中，欲愛身縛、瞋恚身縛五行，戒盜身縛二行，我見身縛四行。",
    "folio":4,
    "analyzed":"縛 中  欲 愛 身 縛  瞋 恚 身 縛 五 行  戒 盜 身 縛 二 行  我 見 身 縛 四 行  "
  },
  {
    "segmentnr":"ZH_T26_1543_004:0786b08_15",
    "original":"蓋中，貪欲蓋、瞋恚、睡眠、掉蓋五行，悔蓋定思惟斷，疑蓋四行。",
    "folio":4,
    "analyzed":"蓋 中  貪 欲 蓋  瞋 恚  睡 眠  掉 蓋 五 行  悔 蓋 定 思 惟 斷  疑 蓋 四 行  "
  },
  {
    "segmentnr":"ZH_T26_1543_004:0786b09_19",
    "original":"結中，愛結、瞋恚結、憍慢結五行，嫉結、慳結定思惟斷。",
    "folio":4,
    "analyzed":"結 中  愛 結  瞋 恚 結  憍 慢 結 五 行  嫉 結  慳 結 定 思 惟 斷  "
  },
  {
    "segmentnr":"ZH_T26_1543_004:0786b11_5",
    "original":"五下分中，貪欲、瞋恚五行，身見見苦斷，戒盜二行，疑四行。",
    "folio":4,
    "analyzed":"五 下 分 中  貪 欲  瞋 恚 五 行  身 見 見 苦 斷  戒 盜 二 行  疑 四 行  "
  },
  {
    "segmentnr":"ZH_T26_1543_004:0786b12_7",
    "original":"見中，身見、邊見見苦斷，邪見、見盜四行，戒盜二行。",
    "folio":4,
    "analyzed":"見 中  身 見  邊 見 見 苦 斷  邪 見  見 盜 四 行  戒 盜 二 行  "
  },
  {
    "segmentnr":"ZH_T26_1543_004:0786b13_3",
    "original":"身愛中，五身愛思惟斷，意更愛五行。",
    "folio":4,
    "analyzed":"身 愛 中  五 身 愛 思 惟 斷  意 更 愛 五 行  "
  },
  {
    "segmentnr":"ZH_T26_1543_004:0786b14_13",
    "original":"使中，貪欲使、瞋恚使、有愛使、憍慢使、無明使五行，見使、疑使四行。",
    "folio":4,
    "analyzed":"使 中  貪 欲 使  瞋 恚 使  有 愛 使  憍 慢 使  無 明 使 五 行  見 使  疑 使 四 行  "
  },
  {
    "segmentnr":"ZH_T26_1543_004:0786b16_12",
    "original":"結中，愛結、瞋恚結、憍慢結、無明結五行，見結、失願結、疑結有四行，嫉結、慳結定思惟斷。",
    "folio":4,
    "analyzed":"結 中  愛 結  瞋 恚 結  憍 慢 結  無 明 結 五 行  見 結  失 願 結  疑 結 有 四 行  嫉 結  慳 結 定 思 惟 斷  "
  },
  {
    "segmentnr":"ZH_T26_1543_004:0786b18_13",
    "original":"九十八使中，二十八見苦斷，十九見習斷，十九見盡斷，二十二見道斷，十思惟斷四門苦諦竟。",
    "folio":4,
    "analyzed":"九 十 八 使 中  二 十 八 見 苦 斷  十 九 見 習 斷  十 九 見 盡 斷  二 十 二 見 道 斷  十 思 惟 斷 四 門 苦 諦 竟  "
  },
  {
    "segmentnr":"ZH_T26_1543_004:0786b19_1",
    "original":"此三結，幾見、幾不見？",
    "folio":4,
    "analyzed":"此 三 結  幾 見  幾 不 見  "
  },
  {
    "segmentnr":"ZH_T26_1543_004:0786b19_4",
    "original":"答曰：",
    "folio":4,
    "analyzed":"答 曰  "
  },
  {
    "segmentnr":"ZH_T26_1543_004:0786b19_11",
    "original":"二見，一不見。",
    "folio":4,
    "analyzed":"二 見  一 不 見  "
  },
  {
    "segmentnr":"ZH_T26_1543_004:0786b19_21",
    "original":"貪、瞋恚、愚癡不見。",
    "folio":4,
    "analyzed":"貪  瞋 恚  愚 癡 不 見  "
  },
  {
    "segmentnr":"ZH_T26_1543_004:0786b20_8",
    "original":"漏中，一不見，二當分別。",
    "folio":4,
    "analyzed":"漏 中  一 不 見  二 當 分 別  "
  },
  {
    "segmentnr":"ZH_T26_1543_004:0786b20_18",
    "original":"欲漏，或見、或不見。",
    "folio":4,
    "analyzed":"欲 漏  或 見  或 不 見  "
  },
  {
    "segmentnr":"ZH_T26_1543_004:0786b20_22",
    "original":"云何見？",
    "folio":4,
    "analyzed":"云 何 見  "
  },
  {
    "segmentnr":"ZH_T26_1543_004:0786b21_2",
    "original":"答曰：",
    "folio":4,
    "analyzed":"答 曰  "
  },
  {
    "segmentnr":"ZH_T26_1543_004:0786b21_11",
    "original":"欲界五見，是謂見。",
    "folio":4,
    "analyzed":"欲 界 五 見  是 謂 見  "
  },
  {
    "segmentnr":"ZH_T26_1543_004:0786b21_16",
    "original":"云何不見？",
    "folio":4,
    "analyzed":"云 何 不 見  "
  },
  {
    "segmentnr":"ZH_T26_1543_004:0786b21_19",
    "original":"答曰：",
    "folio":4,
    "analyzed":"答 曰  "
  },
  {
    "segmentnr":"ZH_T26_1543_004:0786b22_13",
    "original":"除欲界五見，諸餘欲漏是謂不見。",
    "folio":4,
    "analyzed":"除 欲 界 五 見  諸 餘 欲 漏 是 謂 不 見  "
  },
  {
    "segmentnr":"ZH_T26_1543_004:0786b23_2",
    "original":"有漏，或見、或不見。",
    "folio":4,
    "analyzed":"有 漏  或 見  或 不 見  "
  },
  {
    "segmentnr":"ZH_T26_1543_004:0786b23_6",
    "original":"云何見？",
    "folio":4,
    "analyzed":"云 何 見  "
  },
  {
    "segmentnr":"ZH_T26_1543_004:0786b23_9",
    "original":"答曰：",
    "folio":4,
    "analyzed":"答 曰  "
  },
  {
    "segmentnr":"ZH_T26_1543_004:0786b23_20",
    "original":"色無色界五見，是謂見。",
    "folio":4,
    "analyzed":"色無色界 五 見  是 謂 見  "
  },
  {
    "segmentnr":"ZH_T26_1543_004:0786b24_4",
    "original":"云何不見？",
    "folio":4,
    "analyzed":"云 何 不 見  "
  },
  {
    "segmentnr":"ZH_T26_1543_004:0786b24_7",
    "original":"答曰：",
    "folio":4,
    "analyzed":"答 曰  "
  },
  {
    "segmentnr":"ZH_T26_1543_004:0786b25_4",
    "original":"除色無色界五見，諸餘有漏，是謂不見。",
    "folio":4,
    "analyzed":"除 色無色界 五 見  諸 餘 有 漏  是 謂 不 見  "
  },
  {
    "segmentnr":"ZH_T26_1543_004:0786b25_14",
    "original":"流中，一見，三不見。",
    "folio":4,
    "analyzed":"流 中  一 見  三 不 見  "
  },
  {
    "segmentnr":"ZH_T26_1543_004:0786b25_19",
    "original":"軛亦如是。",
    "folio":4,
    "analyzed":"軛 亦 如 是  "
  },
  {
    "segmentnr":"ZH_T26_1543_004:0786b26_8",
    "original":"受中，二見，二不見。",
    "folio":4,
    "analyzed":"受 中  二 見  二 不 見  "
  },
  {
    "segmentnr":"ZH_T26_1543_004:0786b26_18",
    "original":"縛中，二見，二不見。",
    "folio":4,
    "analyzed":"縛 中  二 見  二 不 見  "
  },
  {
    "segmentnr":"ZH_T26_1543_004:0786b26_24",
    "original":"蓋、結不見。",
    "folio":4,
    "analyzed":"蓋  結 不 見  "
  },
  {
    "segmentnr":"ZH_T26_1543_004:0786b27_10",
    "original":"下分中，二見，三不見。",
    "folio":4,
    "analyzed":"下 分 中  二 見  三 不 見  "
  },
  {
    "segmentnr":"ZH_T26_1543_004:0786b27_15",
    "original":"見則見也。",
    "folio":4,
    "analyzed":"見 則 見 也  "
  },
  {
    "segmentnr":"ZH_T26_1543_004:0786b27_20",
    "original":"身愛不見。",
    "folio":4,
    "analyzed":"身 愛 不 見  "
  },
  {
    "segmentnr":"ZH_T26_1543_004:0786b28_8",
    "original":"使中，一見，六不見。",
    "folio":4,
    "analyzed":"使 中  一 見  六 不 見  "
  },
  {
    "segmentnr":"ZH_T26_1543_004:0786b28_18",
    "original":"結中，二見，七不見。",
    "folio":4,
    "analyzed":"結 中  二 見  七 不 見  "
  },
  {
    "segmentnr":"ZH_T26_1543_004:0786b29_17",
    "original":"九十八使中，三十六見，六十二不見五門見門竟。",
    "folio":4,
    "analyzed":"九 十 八 使 中  三 十 六 見  六 十 二 不 見 五 門 見 門 竟  "
  },
  {
    "segmentnr":"ZH_T26_1543_004:0786c01_15",
    "original":"此三結，幾有覺有觀、幾無覺有觀、幾無覺無觀？",
    "folio":4,
    "analyzed":"此 三 結  幾 有 覺 有 觀  幾 無 覺 有 觀  幾 無 覺 無 觀  "
  },
  {
    "segmentnr":"ZH_T26_1543_004:0786c01_18",
    "original":"答曰：",
    "folio":4,
    "analyzed":"答 曰  "
  },
  {
    "segmentnr":"ZH_T26_1543_004:0786c02_18",
    "original":"盡三行或有覺有觀、或無覺有觀、或無覺無觀。",
    "folio":4,
    "analyzed":"盡 三 行 或 有 覺 有 觀  或 無 覺 有 觀  或 無 覺 無 觀  "
  },
  {
    "segmentnr":"ZH_T26_1543_004:0786c03_13",
    "original":"貪、瞋恚、愚癡及欲漏，有覺有觀；",
    "folio":4,
    "analyzed":"貪  瞋 恚  愚 癡 及 欲 漏  有 覺 有 觀  "
  },
  {
    "segmentnr":"ZH_T26_1543_004:0786c04_15",
    "original":"餘殘三行，或有覺有觀、或無覺有觀、或無覺無觀。",
    "folio":4,
    "analyzed":"餘 殘 三 行  或 有 覺 有 觀  或 無 覺 有 觀  或 無 覺 無 觀  "
  },
  {
    "segmentnr":"ZH_T26_1543_004:0786c05_4",
    "original":"流中，欲流有覺有觀；",
    "folio":4,
    "analyzed":"流 中  欲 流 有 覺 有 觀  "
  },
  {
    "segmentnr":"ZH_T26_1543_004:0786c06_7",
    "original":"餘殘三行，或有覺有觀、或無覺有觀、或無覺無觀。",
    "folio":4,
    "analyzed":"餘 殘 三 行  或 有 覺 有 觀  或 無 覺 有 觀  或 無 覺 無 觀  "
  },
  {
    "segmentnr":"ZH_T26_1543_004:0786c06_12",
    "original":"軛亦如是。",
    "folio":4,
    "analyzed":"軛 亦 如 是  "
  },
  {
    "segmentnr":"ZH_T26_1543_004:0786c07_2",
    "original":"受中，欲受有覺有觀；",
    "folio":4,
    "analyzed":"受 中  欲 受 有 覺 有 觀  "
  },
  {
    "segmentnr":"ZH_T26_1543_004:0786c08_4",
    "original":"餘殘三行，或有覺有觀、或無覺有觀、或無覺無觀。",
    "folio":4,
    "analyzed":"餘 殘 三 行  或 有 覺 有 觀  或 無 覺 有 觀  或 無 覺 無 觀  "
  },
  {
    "segmentnr":"ZH_T26_1543_004:0786c09_1",
    "original":"縛中，欲愛身縛、瞋恚身縛，有覺有觀；",
    "folio":4,
    "analyzed":"縛 中  欲 愛 身 縛  瞋 恚 身 縛  有 覺 有 觀  "
  },
  {
    "segmentnr":"ZH_T26_1543_004:0786c10_4",
    "original":"餘殘三行，或有覺有觀、或無覺有觀、或無覺無觀。",
    "folio":4,
    "analyzed":"餘 殘 三 行  或 有 覺 有 觀  或 無 覺 有 觀  或 無 覺 無 觀  "
  },
  {
    "segmentnr":"ZH_T26_1543_004:0786c12_2",
    "original":"蓋及瞋恚結、嫉結、慳結，有覺有觀，餘殘三行，或有覺有觀、或無覺有觀、或無覺無觀。",
    "folio":4,
    "analyzed":"蓋 及 瞋 恚 結  嫉 結  慳 結  有 覺 有 觀  餘 殘 三 行  或 有 覺 有 觀  或 無 覺 有 觀  或 無 覺 無 觀  "
  },
  {
    "segmentnr":"ZH_T26_1543_004:0786c12_16",
    "original":"下分中，貪欲、瞋恚有覺有觀；",
    "folio":4,
    "analyzed":"下 分 中  貪 欲  瞋 恚 有 覺 有 觀  "
  },
  {
    "segmentnr":"ZH_T26_1543_004:0786c13_20",
    "original":"餘殘及見三行，或有覺有觀、或無覺有觀、或無覺無觀。",
    "folio":4,
    "analyzed":"餘 殘 及 見 三 行  或 有 覺 有 觀  或 無 覺 有 觀  或 無 覺 無 觀  "
  },
  {
    "segmentnr":"ZH_T26_1543_004:0786c15_15",
    "original":"身愛中，五身愛有覺有觀，意更愛三行，或有覺有觀、或無覺有觀、或無覺無觀。",
    "folio":4,
    "analyzed":"身 愛 中  五 身 愛 有 覺 有 觀  意 更 愛 三 行  或 有 覺 有 觀  或 無 覺 有 觀  或 無 覺 無 觀  "
  },
  {
    "segmentnr":"ZH_T26_1543_004:0786c16_10",
    "original":"使中，貪欲使、瞋恚使，有覺有觀；",
    "folio":4,
    "analyzed":"使 中  貪 欲 使  瞋 恚 使  有 覺 有 觀  "
  },
  {
    "segmentnr":"ZH_T26_1543_004:0786c17_11",
    "original":"餘殘三行，或有覺有觀、或無覺有觀、或無覺無觀。",
    "folio":4,
    "analyzed":"餘 殘 三 行  或 有 覺 有 觀  或 無 覺 有 觀  或 無 覺 無 觀  "
  },
  {
    "segmentnr":"ZH_T26_1543_004:0786c18_7",
    "original":"結中，瞋恚結、嫉結、慳結，有覺有觀；",
    "folio":4,
    "analyzed":"結 中  瞋 恚 結  嫉 結  慳 結  有 覺 有 觀  "
  },
  {
    "segmentnr":"ZH_T26_1543_004:0786c19_9",
    "original":"餘殘三行，或有覺有觀、或無覺有觀、或無覺無觀。",
    "folio":4,
    "analyzed":"餘 殘 三 行  或 有 覺 有 觀  或 無 覺 有 觀  或 無 覺 無 觀  "
  },
  {
    "segmentnr":"ZH_T26_1543_004:0786c20_2",
    "original":"九十八使中，欲界有覺有觀；",
    "folio":4,
    "analyzed":"九 十 八 使 中  欲 界 有 覺 有 觀  "
  },
  {
    "segmentnr":"ZH_T26_1543_004:0786c21_4",
    "original":"色界三行，或有覺有觀、或無覺有觀、或無覺無觀；",
    "folio":4,
    "analyzed":"色 界 三 行  或 有 覺 有 觀  或 無 覺 有 觀  或 無 覺 無 觀  "
  },
  {
    "segmentnr":"ZH_T26_1543_004:0786c21_18",
    "original":"無色界，無覺無觀六門覺觀竟。",
    "folio":4,
    "analyzed":"無 色 界  無 覺 無 觀 六 門 覺 觀 竟  "
  },
  {
    "segmentnr":"ZH_T26_1543_004:0786c23_9",
    "original":"此三結，幾樂根相應、幾苦根相應、幾喜根相應、幾憂根相應、幾護根相應？",
    "folio":4,
    "analyzed":"此 三 結  幾 樂 根 相 應  幾 苦 根 相 應  幾 喜 根 相 應  幾 憂 根 相 應  幾 護 根 相 應  "
  },
  {
    "segmentnr":"ZH_T26_1543_004:0786c23_12",
    "original":"答曰：",
    "folio":4,
    "analyzed":"答 曰  "
  },
  {
    "segmentnr":"ZH_T26_1543_004:0786c24_4",
    "original":"身見、戒盜三，除苦根、憂根。",
    "folio":4,
    "analyzed":"身 見  戒 盜 三  除 苦 根  憂 根  "
  },
  {
    "segmentnr":"ZH_T26_1543_004:0786c24_11",
    "original":"疑四，除苦根。",
    "folio":4,
    "analyzed":"疑 四  除 苦 根  "
  },
  {
    "segmentnr":"ZH_T26_1543_004:0786c24_21",
    "original":"貪三，除苦根，憂根。",
    "folio":4,
    "analyzed":"貪 三  除 苦 根  憂 根  "
  },
  {
    "segmentnr":"ZH_T26_1543_004:0786c25_8",
    "original":"瞋恚三，除樂根、喜根。",
    "folio":4,
    "analyzed":"瞋 恚 三  除 樂 根  喜 根  "
  },
  {
    "segmentnr":"ZH_T26_1543_004:0786c25_19",
    "original":"愚癡及欲漏、無明漏五。",
    "folio":4,
    "analyzed":"愚 癡 及 欲 漏  無 明 漏 五  "
  },
  {
    "segmentnr":"ZH_T26_1543_004:0786c26_8",
    "original":"有漏三，除苦根、憂根。",
    "folio":4,
    "analyzed":"有 漏 三  除 苦 根  憂 根  "
  },
  {
    "segmentnr":"ZH_T26_1543_004:0786c26_19",
    "original":"流中，欲流、無明流五。",
    "folio":4,
    "analyzed":"流 中  欲 流  無 明 流 五  "
  },
  {
    "segmentnr":"ZH_T26_1543_004:0786c27_6",
    "original":"有流三，除苦根、憂根。",
    "folio":4,
    "analyzed":"有 流 三  除 苦 根  憂 根  "
  },
  {
    "segmentnr":"ZH_T26_1543_004:0786c27_14",
    "original":"見流四，除苦根。",
    "folio":4,
    "analyzed":"見 流 四  除 苦 根  "
  },
  {
    "segmentnr":"ZH_T26_1543_004:0786c27_19",
    "original":"軛亦如是。",
    "folio":4,
    "analyzed":"軛 亦 如 是  "
  },
  {
    "segmentnr":"ZH_T26_1543_004:0786c28_5",
    "original":"受中，欲受五。",
    "folio":4,
    "analyzed":"受 中  欲 受 五  "
  },
  {
    "segmentnr":"ZH_T26_1543_004:0786c28_19",
    "original":"戒受、我受三，除苦根、憂根。",
    "folio":4,
    "analyzed":"戒 受  我 受 三  除 苦 根  憂 根  "
  },
  {
    "segmentnr":"ZH_T26_1543_004:0786c29_3",
    "original":"見受四，除苦根。",
    "folio":4,
    "analyzed":"見 受 四  除 苦 根  "
  },
  {
    "segmentnr":"ZH_T26_1543_004:0786c29_19",
    "original":"縛中，瞋恚身縛三，除樂根、喜根。",
    "folio":4,
    "analyzed":"縛 中  瞋 恚 身 縛 三  除 樂 根  喜 根  "
  },
  {
    "segmentnr":"ZH_T26_1543_004:0787a01_9",
    "original":"餘殘縛三，除苦根、憂根。",
    "folio":4,
    "analyzed":"餘 殘 縛 三  除 苦 根  憂 根  "
  },
  {
    "segmentnr":"ZH_T26_1543_004:0787a02_1",
    "original":"蓋中，貪欲蓋三，除苦根、憂根。",
    "folio":4,
    "analyzed":"蓋 中  貪 欲 蓋 三  除 苦 根  憂 根  "
  },
  {
    "segmentnr":"ZH_T26_1543_004:0787a02_13",
    "original":"瞋恚蓋三，除樂根、喜根。",
    "folio":4,
    "analyzed":"瞋 恚 蓋 三  除 樂 根  喜 根  "
  },
  {
    "segmentnr":"ZH_T26_1543_004:0787a02_18",
    "original":"睡、掉五。",
    "folio":4,
    "analyzed":"睡  掉 五  "
  },
  {
    "segmentnr":"ZH_T26_1543_004:0787a03_4",
    "original":"眠三，除樂根、苦根。",
    "folio":4,
    "analyzed":"眠 三  除 樂 根  苦 根  "
  },
  {
    "segmentnr":"ZH_T26_1543_004:0787a03_18",
    "original":"悔、疑二根相應，憂根及護根。",
    "folio":4,
    "analyzed":"悔  疑 二 根 相 應  憂 根 及 護 根  "
  },
  {
    "segmentnr":"ZH_T26_1543_004:0787a04_10",
    "original":"結中，瞋恚結三，除樂根、喜根。",
    "folio":4,
    "analyzed":"結 中  瞋 恚 結 三  除 樂 根  喜 根  "
  },
  {
    "segmentnr":"ZH_T26_1543_004:0787a05_2",
    "original":"愛結、憍慢結三，除苦根、憂根。",
    "folio":4,
    "analyzed":"愛 結  憍 慢 結 三  除 苦 根  憂 根  "
  },
  {
    "segmentnr":"ZH_T26_1543_004:0787a05_19",
    "original":"嫉結、慳結二根相應，憂根及護根也。",
    "folio":4,
    "analyzed":"嫉 結  慳 結 二 根 相 應  憂 根 及 護 根 也  "
  },
  {
    "segmentnr":"ZH_T26_1543_004:0787a06_13",
    "original":"下分中，貪欲三，除苦根、憂根。",
    "folio":4,
    "analyzed":"下 分 中  貪 欲 三  除 苦 根  憂 根  "
  },
  {
    "segmentnr":"ZH_T26_1543_004:0787a07_2",
    "original":"瞋恚三，除樂根、喜根。",
    "folio":4,
    "analyzed":"瞋 恚 三  除 樂 根  喜 根  "
  },
  {
    "segmentnr":"ZH_T26_1543_004:0787a07_16",
    "original":"身見、戒盜三，除苦根、憂根。",
    "folio":4,
    "analyzed":"身 見  戒 盜 三  除 苦 根  憂 根  "
  },
  {
    "segmentnr":"ZH_T26_1543_004:0787a08_1",
    "original":"疑四，除苦根。",
    "folio":4,
    "analyzed":"疑 四  除 苦 根  "
  },
  {
    "segmentnr":"ZH_T26_1543_004:0787a08_12",
    "original":"見中，邪見四，除苦根。",
    "folio":4,
    "analyzed":"見 中  邪 見 四  除 苦 根  "
  },
  {
    "segmentnr":"ZH_T26_1543_004:0787a09_1",
    "original":"餘殘見三，除苦根、憂根。",
    "folio":4,
    "analyzed":"餘 殘 見 三  除 苦 根  憂 根  "
  },
  {
    "segmentnr":"ZH_T26_1543_004:0787a09_19",
    "original":"身愛中，五身愛二根相應，樂根、護根。",
    "folio":4,
    "analyzed":"身 愛 中  五 身 愛 二 根 相 應  樂 根  護 根  "
  },
  {
    "segmentnr":"ZH_T26_1543_004:0787a10_9",
    "original":"意更愛三，除苦根、憂根。",
    "folio":4,
    "analyzed":"意 更 愛 三  除 苦 根  憂 根  "
  },
  {
    "segmentnr":"ZH_T26_1543_004:0787a11_9",
    "original":"使中，貪欲使、有愛使、憍慢使三，除苦根、憂根。",
    "folio":4,
    "analyzed":"使 中  貪 欲 使  有 愛 使  憍 慢 使 三  除 苦 根  憂 根  "
  },
  {
    "segmentnr":"ZH_T26_1543_004:0787a11_21",
    "original":"瞋恚使三，除樂根、喜根。",
    "folio":4,
    "analyzed":"瞋 恚 使 三  除 樂 根  喜 根  "
  },
  {
    "segmentnr":"ZH_T26_1543_004:0787a12_3",
    "original":"無明使五。",
    "folio":4,
    "analyzed":"無 明 使 五  "
  },
  {
    "segmentnr":"ZH_T26_1543_004:0787a12_14",
    "original":"見使、疑使四，除苦根。",
    "folio":4,
    "analyzed":"見 使  疑 使 四  除 苦 根  "
  },
  {
    "segmentnr":"ZH_T26_1543_004:0787a13_6",
    "original":"結中，瞋恚結三，除樂根、喜根。",
    "folio":4,
    "analyzed":"結 中  瞋 恚 結 三  除 樂 根  喜 根  "
  },
  {
    "segmentnr":"ZH_T26_1543_004:0787a14_2",
    "original":"愛結、憍慢結、失願結三，除苦根、憂根。",
    "folio":4,
    "analyzed":"愛 結  憍 慢 結  失 願 結 三  除 苦 根  憂 根  "
  },
  {
    "segmentnr":"ZH_T26_1543_004:0787a14_7",
    "original":"無明結五。",
    "folio":4,
    "analyzed":"無 明 結 五  "
  },
  {
    "segmentnr":"ZH_T26_1543_004:0787a14_18",
    "original":"見結、疑結四，除苦根。",
    "folio":4,
    "analyzed":"見 結  疑 結 四  除 苦 根  "
  },
  {
    "segmentnr":"ZH_T26_1543_004:0787a15_11",
    "original":"嫉結、慳結二根相應，憂根、護根。",
    "folio":4,
    "analyzed":"嫉 結  慳 結 二 根 相 應  憂 根  護 根  "
  },
  {
    "segmentnr":"ZH_T26_1543_004:0787a17_8",
    "original":"九十八使中，欲界中身見、邊見、見盜、戒盜、見諦所斷欲、憍慢，二根相應，喜根及護根。",
    "folio":4,
    "analyzed":"九 十 八 使 中  欲 界 中 身 見  邊 見  見 盜  戒 盜  見 諦 所 斷 欲  憍 慢  二 根 相 應  喜 根 及 護 根  "
  },
  {
    "segmentnr":"ZH_T26_1543_004:0787a18_7",
    "original":"疑、見諦所斷瞋恚，二根相應，憂根及護根。",
    "folio":4,
    "analyzed":"疑  見 諦 所 斷 瞋 恚  二 根 相 應  憂 根 及 護 根  "
  },
  {
    "segmentnr":"ZH_T26_1543_004:0787a19_5",
    "original":"邪見、見諦所斷無明三，除樂根、苦根。",
    "folio":4,
    "analyzed":"邪 見  見 諦 所 斷 無 明 三  除 樂 根  苦 根  "
  },
  {
    "segmentnr":"ZH_T26_1543_004:0787a19_20",
    "original":"思惟所斷貪欲三，除苦根、憂根。",
    "folio":4,
    "analyzed":"思惟所斷 貪 欲 三  除 苦 根  憂 根  "
  },
  {
    "segmentnr":"ZH_T26_1543_004:0787a20_9",
    "original":"瞋恚三，除樂根、喜根。",
    "folio":4,
    "analyzed":"瞋 恚 三  除 樂 根  喜 根  "
  },
  {
    "segmentnr":"ZH_T26_1543_004:0787a21_1",
    "original":"憍慢二根相應，喜根及護根。",
    "folio":4,
    "analyzed":"憍 慢 二 根 相 應  喜 根 及 護 根  "
  },
  {
    "segmentnr":"ZH_T26_1543_004:0787a21_6",
    "original":"無明使五。",
    "folio":4,
    "analyzed":"無 明 使 五  "
  },
  {
    "segmentnr":"ZH_T26_1543_004:0787a21_17",
    "original":"色界三，除苦根、憂根。",
    "folio":4,
    "analyzed":"色 界 三  除 苦 根  憂 根  "
  },
  {
    "segmentnr":"ZH_T26_1543_004:0787a22_12",
    "original":"無色界一，護根相應也七門根門竟。",
    "folio":4,
    "analyzed":"無 色 界 一  護 根 相 應 也 七 門 根 門 竟  "
  },
  {
    "segmentnr":"ZH_T26_1543_004:0787a23_9",
    "original":"此三結，幾欲界繫、幾色界繫、幾無色界繫？",
    "folio":4,
    "analyzed":"此 三 結  幾 欲 界 繫  幾 色 界 繫  幾 無 色 界 繫  "
  },
  {
    "segmentnr":"ZH_T26_1543_004:0787a23_12",
    "original":"答曰：",
    "folio":4,
    "analyzed":"答 曰  "
  },
  {
    "segmentnr":"ZH_T26_1543_004:0787a24_12",
    "original":"盡有三行，或欲界繫、或色界繫、或無色界繫。",
    "folio":4,
    "analyzed":"盡 有 三 行  或 欲 界 繫  或 色 界 繫  或 無 色 界 繫  "
  },
  {
    "segmentnr":"ZH_T26_1543_004:0787a25_5",
    "original":"貪、瞋恚、愚癡及欲漏，欲界繫；",
    "folio":4,
    "analyzed":"貪  瞋 恚  愚 癡 及 欲 漏  欲 界 繫  "
  },
  {
    "segmentnr":"ZH_T26_1543_004:0787a25_19",
    "original":"有漏，或色界繫、或無色界繫；",
    "folio":4,
    "analyzed":"有 漏  或 色 界 繫  或 無 色 界 繫  "
  },
  {
    "segmentnr":"ZH_T26_1543_004:0787a26_18",
    "original":"餘殘三行，或欲界繫、或色界繫、或無色界繫。",
    "folio":4,
    "analyzed":"餘 殘 三 行  或 欲 界 繫  或 色 界 繫  或 無 色 界 繫  "
  },
  {
    "segmentnr":"ZH_T26_1543_004:0787a27_5",
    "original":"流中，欲流欲界繫；",
    "folio":4,
    "analyzed":"流 中  欲 流 欲 界 繫  "
  },
  {
    "segmentnr":"ZH_T26_1543_004:0787a27_19",
    "original":"有流，或色界繫、或無色界繫；",
    "folio":4,
    "analyzed":"有 流  或 色 界 繫  或 無 色 界 繫  "
  },
  {
    "segmentnr":"ZH_T26_1543_004:0787a28_15",
    "original":"餘殘三行，或欲界繫、或色無色界繫。",
    "folio":4,
    "analyzed":"餘 殘 三 行  或 欲 界 繫  或 色無色界 繫  "
  },
  {
    "segmentnr":"ZH_T26_1543_004:0787a29_1",
    "original":"軛亦如是。",
    "folio":4,
    "analyzed":"軛 亦 如 是  "
  },
  {
    "segmentnr":"ZH_T26_1543_004:0787a29_10",
    "original":"受中，欲受欲界繫。",
    "folio":4,
    "analyzed":"受 中  欲 受 欲 界 繫  "
  },
  {
    "segmentnr":"ZH_T26_1543_004:0787b01_2",
    "original":"我受，或色界繫、或無色界繫；",
    "folio":4,
    "analyzed":"我 受  或 色 界 繫  或 無 色 界 繫  "
  },
  {
    "segmentnr":"ZH_T26_1543_004:0787b01_19",
    "original":"餘殘三行，或欲界繫、或色無色界繫。",
    "folio":4,
    "analyzed":"餘 殘 三 行  或 欲 界 繫  或 色無色界 繫  "
  },
  {
    "segmentnr":"ZH_T26_1543_004:0787b02_14",
    "original":"縛中，欲愛身縛、瞋恚身縛欲界繫；",
    "folio":4,
    "analyzed":"縛 中  欲 愛 身 縛  瞋 恚 身 縛 欲 界 繫  "
  },
  {
    "segmentnr":"ZH_T26_1543_004:0787b03_10",
    "original":"餘殘三行，或欲界繫、或色無色界繫。",
    "folio":4,
    "analyzed":"餘 殘 三 行  或 欲 界 繫  或 色無色界 繫  "
  },
  {
    "segmentnr":"ZH_T26_1543_004:0787b04_5",
    "original":"五蓋及瞋恚結、嫉結、慳結欲界繫；",
    "folio":4,
    "analyzed":"五 蓋 及 瞋 恚 結  嫉 結  慳 結 欲 界 繫  "
  },
  {
    "segmentnr":"ZH_T26_1543_004:0787b05_2",
    "original":"餘殘三行，或欲界繫、或色無色界繫。",
    "folio":4,
    "analyzed":"餘 殘 三 行  或 欲 界 繫  或 色無色界 繫  "
  },
  {
    "segmentnr":"ZH_T26_1543_004:0787b05_15",
    "original":"下分中，貪欲、瞋恚欲界繫；",
    "folio":4,
    "analyzed":"下 分 中  貪 欲  瞋 恚 欲 界 繫  "
  },
  {
    "segmentnr":"ZH_T26_1543_004:0787b06_14",
    "original":"餘殘及五見三行，或欲界繫、或色無色界繫。",
    "folio":4,
    "analyzed":"餘 殘 及 五 見 三 行  或 欲 界 繫  或 色無色界 繫  "
  },
  {
    "segmentnr":"ZH_T26_1543_004:0787b07_8",
    "original":"身愛中，鼻更愛、舌更愛欲界繫；",
    "folio":4,
    "analyzed":"身 愛 中  鼻 更 愛  舌 更 愛 欲 界 繫  "
  },
  {
    "segmentnr":"ZH_T26_1543_004:0787b08_6",
    "original":"眼更愛、耳身更愛，或欲界繫、或色界繫；",
    "folio":4,
    "analyzed":"眼 更 愛  耳 身 更 愛  或 欲 界 繫  或 色 界 繫  "
  },
  {
    "segmentnr":"ZH_T26_1543_004:0787b09_3",
    "original":"意更愛三行，或欲界繫、或色無色界繫。",
    "folio":4,
    "analyzed":"意 更 愛 三 行  或 欲 界 繫  或 色無色界 繫  "
  },
  {
    "segmentnr":"ZH_T26_1543_004:0787b09_17",
    "original":"使中，貪欲使、瞋恚使欲界繫；",
    "folio":4,
    "analyzed":"使 中  貪 欲 使  瞋 恚 使 欲 界 繫  "
  },
  {
    "segmentnr":"ZH_T26_1543_004:0787b10_12",
    "original":"有愛使，或色界繫、或無色界繫；",
    "folio":4,
    "analyzed":"有 愛 使  或 色 界 繫  或 無 色 界 繫  "
  },
  {
    "segmentnr":"ZH_T26_1543_004:0787b11_9",
    "original":"餘殘三行，或欲界繫、或色無色界繫。",
    "folio":4,
    "analyzed":"餘 殘 三 行  或 欲 界 繫  或 色無色界 繫  "
  },
  {
    "segmentnr":"ZH_T26_1543_004:0787b12_3",
    "original":"結中，瞋恚結、嫉結、慳結欲界繫；",
    "folio":4,
    "analyzed":"結 中  瞋 恚 結  嫉 結  慳 結 欲 界 繫  "
  },
  {
    "segmentnr":"ZH_T26_1543_004:0787b12_20",
    "original":"餘殘三行，或欲界繫、或色無色界繫。",
    "folio":4,
    "analyzed":"餘 殘 三 行  或 欲 界 繫  或 色無色界 繫  "
  },
  {
    "segmentnr":"ZH_T26_1543_004:0787b14_13",
    "original":"九十八使中，三十六欲界繫，三十一色界繫，三十一無色界繫八門繫門竟也。",
    "folio":4,
    "analyzed":"九 十 八 使 中  三 十 六 欲 界 繫  三 十 一 色 界 繫  三 十 一 無 色 界 繫 八 門 繫 門 竟 也  "
  },
  {
    "segmentnr":"ZH_T26_1543_004:0787b15_9",
    "original":"諸所有結使是欲界者，彼結使在欲界耶？",
    "folio":4,
    "analyzed":"諸 所 有 結 使 是 欲 界 者  彼 結 使 在 欲 界 耶  "
  },
  {
    "segmentnr":"ZH_T26_1543_004:0787b15_12",
    "original":"答曰：",
    "folio":4,
    "analyzed":"答 曰  "
  },
  {
    "segmentnr":"ZH_T26_1543_004:0787b16_6",
    "original":"或是欲界結使、彼結使不在欲界。",
    "folio":4,
    "analyzed":"或 是 欲 界 結 使  彼 結 使 不 在 欲 界  "
  },
  {
    "segmentnr":"ZH_T26_1543_004:0787b17_3",
    "original":"云何是欲界結使、彼結使不在欲界？",
    "folio":4,
    "analyzed":"云 何 是 欲 界 結 使  彼 結 使 不 在 欲 界  "
  },
  {
    "segmentnr":"ZH_T26_1543_004:0787b17_6",
    "original":"答曰：",
    "folio":4,
    "analyzed":"答 曰  "
  },
  {
    "segmentnr":"ZH_T26_1543_004:0787b19_17",
    "original":"結使所纏魔波旬住梵天上，如來語言亦結使所纏，從色界沒辦欲界中陰，是謂是欲界結使、彼結使不在欲界。",
    "folio":4,
    "analyzed":"結 使 所 纏 魔 波 旬 住 梵 天 上  如 來 語 言 亦 結 使 所 纏  從 色 界 沒 辦 欲 界 中 陰  是 謂 是 欲 界 結 使  彼 結 使 不 在 欲 界  "
  },
  {
    "segmentnr":"ZH_T26_1543_004:0787b20_14",
    "original":"云何結使在欲界、彼結使不是欲界？",
    "folio":4,
    "analyzed":"云 何 結 使 在 欲 界  彼 結 使 不 是 欲 界  "
  },
  {
    "segmentnr":"ZH_T26_1543_004:0787b20_17",
    "original":"答曰：",
    "folio":4,
    "analyzed":"答 曰  "
  },
  {
    "segmentnr":"ZH_T26_1543_004:0787b21_12",
    "original":"結使所纏，從欲界沒辦色界中陰。",
    "folio":4,
    "analyzed":"結 使 所 纏  從 欲 界 沒 辦 色 界 中 陰  "
  },
  {
    "segmentnr":"ZH_T26_1543_004:0787b23_7",
    "original":"亦所有結使是色無色界，住欲界現在前，是謂在欲界結使、彼結使不是欲界。",
    "folio":4,
    "analyzed":"亦 所 有 結 使 是 色無色界  住 欲 界 現 在 前  是 謂 在 欲 界 結 使  彼 結 使 不 是 欲 界  "
  },
  {
    "segmentnr":"ZH_T26_1543_004:0787b24_4",
    "original":"云何是欲界結使、彼結使亦在欲界？",
    "folio":4,
    "analyzed":"云 何 是 欲 界 結 使  彼 結 使 亦 在 欲 界  "
  },
  {
    "segmentnr":"ZH_T26_1543_004:0787b24_7",
    "original":"答曰：",
    "folio":4,
    "analyzed":"答 曰  "
  },
  {
    "segmentnr":"ZH_T26_1543_004:0787b25_5",
    "original":"結使所纏，從欲界沒辦欲界中陰生陰。",
    "folio":4,
    "analyzed":"結 使 所 纏  從 欲 界 沒 辦 欲 界 中 陰 生 陰  "
  },
  {
    "segmentnr":"ZH_T26_1543_004:0787b26_18",
    "original":"亦諸結使在欲界者，住欲界現在前，是謂結使是欲界、彼結使亦在欲界。",
    "folio":4,
    "analyzed":"亦 諸 結 使 在 欲 界 者  住 欲 界 現 在 前  是 謂 結 使 是 欲 界  彼 結 使 亦 在 欲 界  "
  },
  {
    "segmentnr":"ZH_T26_1543_004:0787b27_17",
    "original":"云何亦不是欲界結使、彼結使亦不在欲界？",
    "folio":4,
    "analyzed":"云 何 亦 不 是 欲 界 結 使  彼 結 使 亦 不 在 欲 界  "
  },
  {
    "segmentnr":"ZH_T26_1543_004:0787b28_18",
    "original":"答曰諸結使所纏，從色界沒辦色界中陰生陰。",
    "folio":4,
    "analyzed":"答 曰 諸 結 使 所 纏  從 色 界 沒 辦 色 界 中 陰 生 陰  "
  },
  {
    "segmentnr":"ZH_T26_1543_004:0787c01_5",
    "original":"色界沒生無色界，無色界沒生無色界，無色界沒生色界。",
    "folio":4,
    "analyzed":"色 界 沒 生無色界  無 色 界 沒 生無色界  無 色 界 沒 生 色 界  "
  },
  {
    "segmentnr":"ZH_T26_1543_004:0787c04_3",
    "original":"亦所有結使在色無色界，住色界現在前，諸所有結使在無色界，住無色界現在前，是謂結使亦不是欲界、彼結使亦不在欲界。",
    "folio":4,
    "analyzed":"亦 所 有 結 使 在 色無色界  住 色 界 現 在 前  諸 所 有 結 使 在 無 色 界  住 無 色 界 現 在 前  是 謂 結 使 亦 不 是 欲 界  彼 結 使 亦 不 在 欲 界  "
  },
  {
    "segmentnr":"ZH_T26_1543_004:0787c05_1",
    "original":"諸所有結使是色界、彼結使在色界耶？",
    "folio":4,
    "analyzed":"諸 所 有 結 使 是 色 界  彼 結 使 在 色 界 耶  "
  },
  {
    "segmentnr":"ZH_T26_1543_004:0787c05_4",
    "original":"答曰：",
    "folio":4,
    "analyzed":"答 曰  "
  },
  {
    "segmentnr":"ZH_T26_1543_004:0787c05_20",
    "original":"或有結使是色界、彼結使不在色界。",
    "folio":4,
    "analyzed":"或 有 結 使 是 色 界  彼 結 使 不 在 色 界  "
  },
  {
    "segmentnr":"ZH_T26_1543_004:0787c06_15",
    "original":"云何結使是色界、彼結使不在色界？",
    "folio":4,
    "analyzed":"云 何 結 使 是 色 界  彼 結 使 不 在 色 界  "
  },
  {
    "segmentnr":"ZH_T26_1543_004:0787c06_18",
    "original":"答曰：",
    "folio":4,
    "analyzed":"答 曰  "
  },
  {
    "segmentnr":"ZH_T26_1543_004:0787c07_13",
    "original":"結使所纏，從欲界沒辦色界中陰。",
    "folio":4,
    "analyzed":"結 使 所 纏  從 欲 界 沒 辦 色 界 中 陰  "
  },
  {
    "segmentnr":"ZH_T26_1543_004:0787c09_6",
    "original":"亦所有結使是色界，住欲界現在前，是謂色界結使、彼結使不在色界。",
    "folio":4,
    "analyzed":"亦 所 有 結 使 是 色 界  住 欲 界 現 在 前  是 謂 色 界 結 使  彼 結 使 不 在 色 界  "
  },
  {
    "segmentnr":"ZH_T26_1543_004:0787c10_3",
    "original":"云何在色界結使、彼結使不是色界？",
    "folio":4,
    "analyzed":"云 何 在 色 界 結 使  彼 結 使 不 是 色 界  "
  },
  {
    "segmentnr":"ZH_T26_1543_004:0787c10_6",
    "original":"答曰：",
    "folio":4,
    "analyzed":"答 曰  "
  },
  {
    "segmentnr":"ZH_T26_1543_004:0787c12_2",
    "original":"諸結使所纏魔波旬住梵天上，如來語言亦結使所纏，從色界沒辦欲界中陰。",
    "folio":4,
    "analyzed":"諸 結 使 所 纏 魔 波 旬 住 梵 天 上  如 來 語 言 亦 結 使 所 纏  從 色 界 沒 辦 欲 界 中 陰  "
  },
  {
    "segmentnr":"ZH_T26_1543_004:0787c13_17",
    "original":"亦所有結使在無色界，住色界現在前，是謂在色界結使、彼結使不是色界。",
    "folio":4,
    "analyzed":"亦 所 有 結 使 在 無 色 界  住 色 界 現 在 前  是 謂 在 色 界 結 使  彼 結 使 不 是 色 界  "
  },
  {
    "segmentnr":"ZH_T26_1543_004:0787c14_13",
    "original":"云何是色界結使、彼結使亦在色界？",
    "folio":4,
    "analyzed":"云 何 是 色 界 結 使  彼 結 使 亦 在 色 界  "
  },
  {
    "segmentnr":"ZH_T26_1543_004:0787c14_16",
    "original":"答曰：",
    "folio":4,
    "analyzed":"答 曰  "
  },
  {
    "segmentnr":"ZH_T26_1543_004:0787c15_14",
    "original":"諸結使所纏，從色界沒辦色界中陰生陰。",
    "folio":4,
    "analyzed":"諸 結 使 所 纏  從 色 界 沒 辦 色 界 中 陰 生 陰  "
  },
  {
    "segmentnr":"ZH_T26_1543_004:0787c17_9",
    "original":"亦所有結使是色界，住色界現在前，是謂是色界結使、彼結使亦在色界。",
    "folio":4,
    "analyzed":"亦 所 有 結 使 是 色 界  住 色 界 現 在 前  是 謂 是 色 界 結 使  彼 結 使 亦 在 色 界  "
  },
  {
    "segmentnr":"ZH_T26_1543_004:0787c18_7",
    "original":"云何結使不是色界、彼結使亦不在色界。",
    "folio":4,
    "analyzed":"云 何 結 使 不 是 色 界  彼 結 使 亦 不 在 色 界  "
  },
  {
    "segmentnr":"ZH_T26_1543_004:0787c18_10",
    "original":"答曰：",
    "folio":4,
    "analyzed":"答 曰  "
  },
  {
    "segmentnr":"ZH_T26_1543_004:0787c19_8",
    "original":"諸結使所纏，從欲界沒辦欲界中陰生陰。",
    "folio":4,
    "analyzed":"諸 結 使 所 纏  從 欲 界 沒 辦 欲 界 中 陰 生 陰  "
  },
  {
    "segmentnr":"ZH_T26_1543_004:0787c20_16",
    "original":"從欲界沒生無色界，無色界沒生無色界，無色界沒生欲界。",
    "folio":4,
    "analyzed":"從 欲 界 沒 生無色界  無 色 界 沒 生無色界  無 色 界 沒 生 欲 界  "
  },
  {
    "segmentnr":"ZH_T26_1543_004:0787c21_14",
    "original":"亦所有結使在無色界，住欲界現在前。",
    "folio":4,
    "analyzed":"亦 所 有 結 使 在 無 色 界  住 欲 界 現 在 前  "
  },
  {
    "segmentnr":"ZH_T26_1543_004:0787c23_12",
    "original":"亦所有結使在無色界，住無色界現在前，是謂結使不是色界、彼結使亦不在色界。",
    "folio":4,
    "analyzed":"亦 所 有 結 使 在 無 色 界  住 無 色 界 現 在 前  是 謂 結 使 不 是 色 界  彼 結 使 亦 不 在 色 界  "
  },
  {
    "segmentnr":"ZH_T26_1543_004:0787c23_17",
    "original":"非亦如是。",
    "folio":4,
    "analyzed":"非 亦 如 是  "
  },
  {
    "segmentnr":"ZH_T26_1543_004:0787c24_16",
    "original":"諸所有結使是無色界、彼結使在無色界耶？",
    "folio":4,
    "analyzed":"諸 所 有 結 使 是 無 色 界  彼 結 使 在 無 色 界 耶  "
  },
  {
    "segmentnr":"ZH_T26_1543_004:0787c24_19",
    "original":"答曰：",
    "folio":4,
    "analyzed":"答 曰  "
  },
  {
    "segmentnr":"ZH_T26_1543_004:0787c26_2",
    "original":"如是，諸所有結使在無色界、彼結使是無色界也。",
    "folio":4,
    "analyzed":"如 是  諸 所 有 結 使 在 無 色 界  彼 結 使 是 無 色 界 也  "
  },
  {
    "segmentnr":"ZH_T26_1543_004:0787c27_1",
    "original":"頗是無色界結使、彼結使不在無色界耶？",
    "folio":4,
    "analyzed":"頗 是 無 色 界 結 使  彼 結 使 不 在 無 色 界 耶  "
  },
  {
    "segmentnr":"ZH_T26_1543_004:0787c27_4",
    "original":"答曰：",
    "folio":4,
    "analyzed":"答 曰  "
  },
  {
    "segmentnr":"ZH_T26_1543_004:0787c28_3",
    "original":"有，諸所有結使是無色界，住欲色界現在前。",
    "folio":4,
    "analyzed":"有  諸 所 有 結 使 是 無 色 界  住 欲 色 界 現 在 前  "
  },
  {
    "segmentnr":"ZH_T26_1543_004:0787c29_6",
    "original":"諸所有結使不是無色界、彼結使亦不在無色界耶？",
    "folio":4,
    "analyzed":"諸 所 有 結 使 不 是 無 色 界  彼 結 使 亦 不 在 無 色 界 耶  "
  },
  {
    "segmentnr":"ZH_T26_1543_004:0787c29_9",
    "original":"答曰：",
    "folio":4,
    "analyzed":"答 曰  "
  },
  {
    "segmentnr":"ZH_T26_1543_004:0788a01_13",
    "original":"如是，諸所有結使不是無色界、彼結使亦不在無色界。",
    "folio":4,
    "analyzed":"如 是  諸 所 有 結 使 不 是 無 色 界  彼 結 使 亦 不 在 無 色 界  "
  },
  {
    "segmentnr":"ZH_T26_1543_004:0788a02_14",
    "original":"頗結使不在無色界、彼結使非不是無色界耶？",
    "folio":4,
    "analyzed":"頗 結 使 不 在 無 色 界  彼 結 使 非 不 是 無 色 界 耶  "
  },
  {
    "segmentnr":"ZH_T26_1543_004:0788a02_17",
    "original":"答曰：",
    "folio":4,
    "analyzed":"答 曰  "
  },
  {
    "segmentnr":"ZH_T26_1543_004:0788a04_1",
    "original":"有，諸所有結使是無色界，住欲界色界現在前九門竟。",
    "folio":4,
    "analyzed":"有  諸 所 有 結 使 是 無 色 界  住 欲界色界 現 在 前 九 門 竟  "
  },
  {
    "segmentnr":"ZH_T26_1543_004:0788a04_19",
    "original":"見諦成就世尊弟子色未盡，為色所繫耶？",
    "folio":4,
    "analyzed":"見 諦 成 就 世 尊 弟 子 色 未 盡  為 色 所 繫 耶  "
  },
  {
    "segmentnr":"ZH_T26_1543_004:0788a05_2",
    "original":"答曰：",
    "folio":4,
    "analyzed":"答 曰  "
  },
  {
    "segmentnr":"ZH_T26_1543_004:0788a05_5",
    "original":"如是。",
    "folio":4,
    "analyzed":"如 是  "
  },
  {
    "segmentnr":"ZH_T26_1543_004:0788a05_16",
    "original":"設為色所繫，色不盡耶？",
    "folio":4,
    "analyzed":"設 為 色 所 繫  色 不 盡 耶  "
  },
  {
    "segmentnr":"ZH_T26_1543_004:0788a05_19",
    "original":"答曰：",
    "folio":4,
    "analyzed":"答 曰  "
  },
  {
    "segmentnr":"ZH_T26_1543_004:0788a05_22",
    "original":"如是。",
    "folio":4,
    "analyzed":"如 是  "
  },
  {
    "segmentnr":"ZH_T26_1543_004:0788a06_10",
    "original":"若痛未盡，為痛所繫耶？",
    "folio":4,
    "analyzed":"若 痛 未 盡  為 痛 所 繫 耶  "
  },
  {
    "segmentnr":"ZH_T26_1543_004:0788a06_13",
    "original":"答曰：",
    "folio":4,
    "analyzed":"答 曰  "
  },
  {
    "segmentnr":"ZH_T26_1543_004:0788a07_3",
    "original":"如是，痛未盡為痛所繫。",
    "folio":4,
    "analyzed":"如 是  痛 未 盡 為 痛 所 繫  "
  },
  {
    "segmentnr":"ZH_T26_1543_004:0788a07_15",
    "original":"頗為痛所繫，非痛未盡耶？",
    "folio":4,
    "analyzed":"頗 為 痛 所 繫  非 痛 未 盡 耶  "
  },
  {
    "segmentnr":"ZH_T26_1543_004:0788a07_18",
    "original":"答曰：",
    "folio":4,
    "analyzed":"答 曰  "
  },
  {
    "segmentnr":"ZH_T26_1543_004:0788a09_10",
    "original":"有，家家斯陀含，一種欲界繫增上中思惟所斷結盡，彼相應痛下結使繫。",
    "folio":4,
    "analyzed":"有  家 家 斯 陀 含  一 種 欲 界 繫 增 上 中 思惟所斷 結 盡  彼 相 應 痛 下 結 使 繫  "
  },
  {
    "segmentnr":"ZH_T26_1543_004:0788a10_1",
    "original":"想行識亦復如是十門竟。",
    "folio":4,
    "analyzed":"想 行 識 亦復如是 十 門 竟  "
  },
  {
    "segmentnr":"ZH_T26_1543_004:0788a10_19",
    "original":"見諦成就世尊弟子若色已盡，彼色脫耶？",
    "folio":4,
    "analyzed":"見 諦 成 就 世 尊 弟 子 若 色 已 盡  彼 色 脫 耶  "
  },
  {
    "segmentnr":"ZH_T26_1543_004:0788a11_2",
    "original":"答曰：",
    "folio":4,
    "analyzed":"答 曰  "
  },
  {
    "segmentnr":"ZH_T26_1543_004:0788a11_5",
    "original":"如是。",
    "folio":4,
    "analyzed":"如 是  "
  },
  {
    "segmentnr":"ZH_T26_1543_004:0788a11_15",
    "original":"若色不繫，彼色盡耶？",
    "folio":4,
    "analyzed":"若 色 不 繫  彼 色 盡 耶  "
  },
  {
    "segmentnr":"ZH_T26_1543_004:0788a11_18",
    "original":"答曰：",
    "folio":4,
    "analyzed":"答 曰  "
  },
  {
    "segmentnr":"ZH_T26_1543_004:0788a11_21",
    "original":"如是。",
    "folio":4,
    "analyzed":"如 是  "
  },
  {
    "segmentnr":"ZH_T26_1543_004:0788a12_10",
    "original":"若痛已盡，彼痛不繫耶？",
    "folio":4,
    "analyzed":"若 痛 已 盡  彼 痛 不 繫 耶  "
  },
  {
    "segmentnr":"ZH_T26_1543_004:0788a12_13",
    "original":"答曰：",
    "folio":4,
    "analyzed":"答 曰  "
  },
  {
    "segmentnr":"ZH_T26_1543_004:0788a12_16",
    "original":"如是。",
    "folio":4,
    "analyzed":"如 是  "
  },
  {
    "segmentnr":"ZH_T26_1543_004:0788a13_4",
    "original":"若痛不繫，彼痛盡耶？",
    "folio":4,
    "analyzed":"若 痛 不 繫  彼 痛 盡 耶  "
  },
  {
    "segmentnr":"ZH_T26_1543_004:0788a13_15",
    "original":"頗痛盡，彼痛非不繫耶？",
    "folio":4,
    "analyzed":"頗 痛 盡  彼 痛 非 不 繫 耶  "
  },
  {
    "segmentnr":"ZH_T26_1543_004:0788a13_18",
    "original":"答曰：",
    "folio":4,
    "analyzed":"答 曰  "
  },
  {
    "segmentnr":"ZH_T26_1543_004:0788a15_11",
    "original":"有，家家斯陀含，一種欲界繫增上中思惟所斷結盡，彼相應痛下結使繫。",
    "folio":4,
    "analyzed":"有  家 家 斯 陀 含  一 種 欲 界 繫 增 上 中 思惟所斷 結 盡  彼 相 應 痛 下 結 使 繫  "
  },
  {
    "segmentnr":"ZH_T26_1543_004:0788a16_4",
    "original":"想行識亦復如是十一門竟。",
    "folio":4,
    "analyzed":"想 行 識 亦復如是 十 一 門 竟  "
  },
  {
    "segmentnr":"ZH_T26_1543_004:0788a16_23",
    "original":"五人，堅信、堅法、信解脫、見到、身證。",
    "folio":4,
    "analyzed":"五 人  堅 信  堅 法  信 解 脫  見 到  身 證  "
  },
  {
    "segmentnr":"ZH_T26_1543_004:0788a17_14",
    "original":"堅信人於此三結，成就幾、不成就幾？",
    "folio":4,
    "analyzed":"堅 信 人 於 此 三 結  成 就 幾  不 成 就 幾  "
  },
  {
    "segmentnr":"ZH_T26_1543_004:0788a17_17",
    "original":"答曰：",
    "folio":4,
    "analyzed":"答 曰  "
  },
  {
    "segmentnr":"ZH_T26_1543_004:0788a18_8",
    "original":"苦未知智未生，一切成就。",
    "folio":4,
    "analyzed":"苦 未 知 智 未 生  一切成就  "
  },
  {
    "segmentnr":"ZH_T26_1543_004:0788a19_2",
    "original":"苦未知智生，二成就，一不成就。",
    "folio":4,
    "analyzed":"苦 未 知 智 生  二 成 就  一 不 成 就  "
  },
  {
    "segmentnr":"ZH_T26_1543_004:0788a19_20",
    "original":"貪瞋、恚愚、癡、欲愛未盡，一切成就。",
    "folio":4,
    "analyzed":"貪 瞋  恚 愚  癡  欲 愛 未 盡  一切成就  "
  },
  {
    "segmentnr":"ZH_T26_1543_004:0788a20_8",
    "original":"欲愛已盡，一切不成就。",
    "folio":4,
    "analyzed":"欲 愛 已 盡  一 切 不 成 就  "
  },
  {
    "segmentnr":"ZH_T26_1543_004:0788a21_1",
    "original":"有漏中，欲愛未盡，一切成就；",
    "folio":4,
    "analyzed":"有 漏 中  欲 愛 未 盡  一切成就  "
  },
  {
    "segmentnr":"ZH_T26_1543_004:0788a21_15",
    "original":"欲愛已盡，二成就，一不成就。",
    "folio":4,
    "analyzed":"欲 愛 已 盡  二 成 就  一 不 成 就  "
  },
  {
    "segmentnr":"ZH_T26_1543_004:0788a22_6",
    "original":"流中，欲愛未盡，一切成就；",
    "folio":4,
    "analyzed":"流 中  欲 愛 未 盡  一切成就  "
  },
  {
    "segmentnr":"ZH_T26_1543_004:0788a22_20",
    "original":"欲愛已盡，三成就，一不成就。",
    "folio":4,
    "analyzed":"欲 愛 已 盡  三 成 就  一 不 成 就  "
  },
  {
    "segmentnr":"ZH_T26_1543_004:0788a23_6",
    "original":"軛、受亦如是。",
    "folio":4,
    "analyzed":"軛  受 亦 如 是  "
  },
  {
    "segmentnr":"ZH_T26_1543_004:0788a23_19",
    "original":"縛中，欲愛未盡，一切成就；",
    "folio":4,
    "analyzed":"縛 中  欲 愛 未 盡  一切成就  "
  },
  {
    "segmentnr":"ZH_T26_1543_004:0788a24_11",
    "original":"欲愛已盡，二成就，二不成就。",
    "folio":4,
    "analyzed":"欲 愛 已 盡  二 成 就  二 不 成 就  "
  },
  {
    "segmentnr":"ZH_T26_1543_004:0788a25_8",
    "original":"蓋中，欲愛未盡、道法智未生，一切成就；",
    "folio":4,
    "analyzed":"蓋 中  欲 愛 未 盡  道 法 智 未 生  一切成就  "
  },
  {
    "segmentnr":"ZH_T26_1543_004:0788a26_7",
    "original":"若欲愛未盡、道法智生，四成就，一不成就；",
    "folio":4,
    "analyzed":"若 欲 愛 未 盡  道 法 智 生  四 成 就  一 不 成 就  "
  },
  {
    "segmentnr":"ZH_T26_1543_004:0788a26_18",
    "original":"欲愛已盡，一切不成就。",
    "folio":4,
    "analyzed":"欲 愛 已 盡  一 切 不 成 就  "
  },
  {
    "segmentnr":"ZH_T26_1543_004:0788a27_9",
    "original":"結中，欲愛未盡，一切成就；",
    "folio":4,
    "analyzed":"結 中  欲 愛 未 盡  一切成就  "
  },
  {
    "segmentnr":"ZH_T26_1543_004:0788a28_2",
    "original":"欲愛已盡，二成就，三不成就。",
    "folio":4,
    "analyzed":"欲 愛 已 盡  二 成 就  三 不 成 就  "
  },
  {
    "segmentnr":"ZH_T26_1543_004:0788a29_2",
    "original":"下分中，欲愛未盡、苦未知智未生，一切成就；",
    "folio":4,
    "analyzed":"下 分 中  欲 愛 未 盡  苦 未 知 智 未 生  一切成就  "
  },
  {
    "segmentnr":"ZH_T26_1543_004:0788b01_2",
    "original":"若欲愛未盡、苦未知智生，四成就，一不成就；",
    "folio":4,
    "analyzed":"若 欲 愛 未 盡  苦 未 知 智 生  四 成 就  一 不 成 就  "
  },
  {
    "segmentnr":"ZH_T26_1543_004:0788b02_2",
    "original":"欲愛已盡、苦未知智未生，三成就，二不成就；",
    "folio":4,
    "analyzed":"欲 愛 已 盡  苦 未 知 智 未 生  三 成 就  二 不 成 就  "
  },
  {
    "segmentnr":"ZH_T26_1543_004:0788b03_2",
    "original":"若欲愛已盡、苦未知智生，二成就，三不成就。",
    "folio":4,
    "analyzed":"若 欲 愛 已 盡  苦 未 知 智 生  二 成 就  三 不 成 就  "
  },
  {
    "segmentnr":"ZH_T26_1543_004:0788b03_17",
    "original":"見中，苦未知智未生，一切成就；",
    "folio":4,
    "analyzed":"見 中  苦 未 知 智 未 生  一切成就  "
  },
  {
    "segmentnr":"ZH_T26_1543_004:0788b04_11",
    "original":"苦未知智生，三成就，二不成就。",
    "folio":4,
    "analyzed":"苦 未 知 智 生  三 成 就  二 不 成 就  "
  },
  {
    "segmentnr":"ZH_T26_1543_004:0788b05_3",
    "original":"身愛中，欲愛未盡，一切成就；",
    "folio":4,
    "analyzed":"身 愛 中  欲 愛 未 盡  一切成就  "
  },
  {
    "segmentnr":"ZH_T26_1543_004:0788b06_2",
    "original":"欲愛已盡、梵天愛未盡，四成就，二不成就；",
    "folio":4,
    "analyzed":"欲 愛 已 盡  梵 天 愛 未 盡  四 成 就  二 不 成 就  "
  },
  {
    "segmentnr":"ZH_T26_1543_004:0788b06_16",
    "original":"梵天愛盡，一成就，五不成就。",
    "folio":4,
    "analyzed":"梵 天 愛 盡  一 成 就  五 不 成 就  "
  },
  {
    "segmentnr":"ZH_T26_1543_004:0788b07_8",
    "original":"使中，欲愛未盡，一切成就；",
    "folio":4,
    "analyzed":"使 中  欲 愛 未 盡  一切成就  "
  },
  {
    "segmentnr":"ZH_T26_1543_004:0788b08_1",
    "original":"欲愛已盡，五成就，二不成就。",
    "folio":4,
    "analyzed":"欲 愛 已 盡  五 成 就  二 不 成 就  "
  },
  {
    "segmentnr":"ZH_T26_1543_004:0788b08_14",
    "original":"結中，欲愛未盡，一切成就；",
    "folio":4,
    "analyzed":"結 中  欲 愛 未 盡  一切成就  "
  },
  {
    "segmentnr":"ZH_T26_1543_004:0788b09_7",
    "original":"欲愛已盡，六成就，三不成就。",
    "folio":4,
    "analyzed":"欲 愛 已 盡  六 成 就  三 不 成 就  "
  },
  {
    "segmentnr":"ZH_T26_1543_004:0788b10_8",
    "original":"九十八使中，欲愛未盡、苦法智未生，一切成就。",
    "folio":4,
    "analyzed":"九 十 八 使 中  欲 愛 未 盡  苦 法 智 未 生  一切成就  "
  },
  {
    "segmentnr":"ZH_T26_1543_004:0788b11_14",
    "original":"苦法智生、苦未知智未生，欲界苦諦所斷不成就，餘殘成就。",
    "folio":4,
    "analyzed":"苦 法 智 生  苦 未 知 智 未 生  欲 界 苦 諦 所 斷 不 成 就  餘 殘 成 就  "
  },
  {
    "segmentnr":"ZH_T26_1543_004:0788b13_2",
    "original":"苦未知智生、習法智未生，三界苦諦所斷不成就，餘殘成就。",
    "folio":4,
    "analyzed":"苦 未 知 智 生  習 法 智 未 生  三 界 苦 諦 所 斷 不 成 就  餘 殘 成 就  "
  },
  {
    "segmentnr":"ZH_T26_1543_004:0788b14_16",
    "original":"習法智生、習未知智未生，三界苦諦所斷不成就，及欲界習諦所斷餘殘成就。",
    "folio":4,
    "analyzed":"習 法 智 生  習 未 知 智 未 生  三 界 苦 諦 所 斷 不 成 就  及 欲 界 習 諦 所 斷 餘 殘 成 就  "
  },
  {
    "segmentnr":"ZH_T26_1543_004:0788b16_4",
    "original":"習未知智生、盡法智未生，三界苦習所斷不成就，餘殘成就。",
    "folio":4,
    "analyzed":"習 未 知 智 生  盡 法 智 未 生  三 界 苦 習 所 斷 不 成 就  餘 殘 成 就  "
  },
  {
    "segmentnr":"ZH_T26_1543_004:0788b18_2",
    "original":"盡法智生、盡未知智未生，三界苦諦習諦所斷不成就，及欲界盡諦所斷餘殘成就。",
    "folio":4,
    "analyzed":"盡 法 智 生  盡 未 知 智 未 生  三 界 苦 諦 習 諦 所 斷 不 成 就  及 欲 界 盡 諦 所 斷 餘 殘 成 就  "
  },
  {
    "segmentnr":"ZH_T26_1543_004:0788b19_13",
    "original":"盡未知智生、道法智未生，三界苦諦習諦盡諦所斷不成就，餘殘成就。",
    "folio":4,
    "analyzed":"盡 未 知 智 生  道 法 智 未 生  三 界 苦 諦 習 諦 盡 諦 所 斷 不 成 就  餘 殘 成 就  "
  },
  {
    "segmentnr":"ZH_T26_1543_004:0788b21_4",
    "original":"道法智生，三界苦集盡諦所斷不成就，及欲界道諦所斷餘殘成就。",
    "folio":4,
    "analyzed":"道 法 智 生  三 界 苦 集 盡 諦 所 斷 不 成 就  及 欲 界 道 諦 所 斷 餘 殘 成 就  "
  },
  {
    "segmentnr":"ZH_T26_1543_004:0788b22_14",
    "original":"欲愛已盡、色愛未盡、苦未知智未生，欲界一切不成就，餘殘成就。",
    "folio":4,
    "analyzed":"欲 愛 已 盡  色 愛 未 盡  苦 未 知 智 未 生  欲 界 一 切 不 成 就  餘 殘 成 就  "
  },
  {
    "segmentnr":"ZH_T26_1543_004:0788b24_9",
    "original":"苦未知智生、習未知智未生，欲界一切不成就，及色無色界苦諦所斷餘殘成就。",
    "folio":4,
    "analyzed":"苦 未 知 智 生  習 未 知 智 未 生  欲 界 一 切 不 成 就  及 色無色界 苦 諦 所 斷 餘 殘 成 就  "
  },
  {
    "segmentnr":"ZH_T26_1543_004:0788b26_8",
    "original":"習未知智生、盡未知智未生，欲界一切不成就，及色無色界苦諦習諦所斷餘殘成就。",
    "folio":4,
    "analyzed":"習 未 知 智 生  盡 未 知 智 未 生  欲 界 一 切 不 成 就  及 色無色界 苦 諦 習 諦 所 斷 餘 殘 成 就  "
  },
  {
    "segmentnr":"ZH_T26_1543_004:0788b28_3",
    "original":"盡未知智生，欲界一切不成就，及色無色界苦諦習諦盡諦所斷餘殘成就。",
    "folio":4,
    "analyzed":"盡 未 知 智 生  欲 界 一 切 不 成 就  及 色無色界 苦 諦 習 諦 盡 諦 所 斷 餘 殘 成 就  "
  },
  {
    "segmentnr":"ZH_T26_1543_004:0788b29_15",
    "original":"色愛已盡、無色愛未盡、苦未知智未生，欲色界一切不成就，餘殘成就。",
    "folio":4,
    "analyzed":"色 愛 已 盡  無 色 愛 未 盡  苦 未 知 智 未 生  欲 色 界 一 切 不 成 就  餘 殘 成 就  "
  },
  {
    "segmentnr":"ZH_T26_1543_004:0788c02_10",
    "original":"苦未知智生、習未知智未生，欲色界一切不成就，及無色界苦諦所斷餘殘成就。",
    "folio":4,
    "analyzed":"苦 未 知 智 生  習 未 知 智 未 生  欲 色 界 一 切 不 成 就  及 無 色 界 苦 諦 所 斷 餘 殘 成 就  "
  },
  {
    "segmentnr":"ZH_T26_1543_004:0788c04_9",
    "original":"習未知智生、盡未知智未生，欲色界一切不成就，及無色界苦諦習諦所斷餘殘成就。",
    "folio":4,
    "analyzed":"習 未 知 智 生  盡 未 知 智 未 生  欲 色 界 一 切 不 成 就  及 無 色 界 苦 諦 習 諦 所 斷 餘 殘 成 就  "
  },
  {
    "segmentnr":"ZH_T26_1543_004:0788c06_4",
    "original":"盡未知智生，欲色界一切不成就，及無色界苦諦習諦盡諦所斷餘殘成就。",
    "folio":4,
    "analyzed":"盡 未 知 智 生  欲 色 界 一 切 不 成 就  及 無 色 界 苦 諦 習 諦 盡 諦 所 斷 餘 殘 成 就  "
  },
  {
    "segmentnr":"ZH_T26_1543_004:0788c06_10",
    "original":"堅法亦如是。",
    "folio":4,
    "analyzed":"堅 法 亦 如 是  "
  },
  {
    "segmentnr":"ZH_T26_1543_004:0788c07_7",
    "original":"信解脫人，此三結，幾成就、幾不成就？",
    "folio":4,
    "analyzed":"信 解 脫 人  此 三 結  幾 成 就  幾 不 成 就  "
  },
  {
    "segmentnr":"ZH_T26_1543_004:0788c07_10",
    "original":"答曰：",
    "folio":4,
    "analyzed":"答 曰  "
  },
  {
    "segmentnr":"ZH_T26_1543_004:0788c07_16",
    "original":"一切不成就。",
    "folio":4,
    "analyzed":"一 切 不 成 就  "
  },
  {
    "segmentnr":"ZH_T26_1543_004:0788c08_11",
    "original":"貪、瞋恚、愚癡、欲愛未盡，一切成就；",
    "folio":4,
    "analyzed":"貪  瞋 恚  愚 癡  欲 愛 未 盡  一切成就  "
  },
  {
    "segmentnr":"ZH_T26_1543_004:0788c09_1",
    "original":"欲愛已盡，一切不成就。",
    "folio":4,
    "analyzed":"欲 愛 已 盡  一 切 不 成 就  "
  },
  {
    "segmentnr":"ZH_T26_1543_004:0788c09_15",
    "original":"有漏中，欲愛未盡，一切成就；",
    "folio":4,
    "analyzed":"有 漏 中  欲 愛 未 盡  一切成就  "
  },
  {
    "segmentnr":"ZH_T26_1543_004:0788c10_7",
    "original":"欲愛已盡，二成就，一不成就。",
    "folio":4,
    "analyzed":"欲 愛 已 盡  二 成 就  一 不 成 就  "
  },
  {
    "segmentnr":"ZH_T26_1543_004:0788c11_2",
    "original":"流中，欲愛未盡，三成就，一不成就；",
    "folio":4,
    "analyzed":"流 中  欲 愛 未 盡  三 成 就  一 不 成 就  "
  },
  {
    "segmentnr":"ZH_T26_1543_004:0788c11_16",
    "original":"欲愛已盡，二成就，二不成就。",
    "folio":4,
    "analyzed":"欲 愛 已 盡  二 成 就  二 不 成 就  "
  },
  {
    "segmentnr":"ZH_T26_1543_004:0788c12_1",
    "original":"軛亦如是。",
    "folio":4,
    "analyzed":"軛 亦 如 是  "
  },
  {
    "segmentnr":"ZH_T26_1543_004:0788c12_18",
    "original":"受中，欲愛未盡，二成就，二不成就；",
    "folio":4,
    "analyzed":"受 中  欲 愛 未 盡  二 成 就  二 不 成 就  "
  },
  {
    "segmentnr":"ZH_T26_1543_004:0788c13_11",
    "original":"欲愛已盡，一成就，三不成就。",
    "folio":4,
    "analyzed":"欲 愛 已 盡  一 成 就  三 不 成 就  "
  },
  {
    "segmentnr":"ZH_T26_1543_004:0788c14_6",
    "original":"縛中，欲愛未盡，二成就，二不成就；",
    "folio":4,
    "analyzed":"縛 中  欲 愛 未 盡  二 成 就  二 不 成 就  "
  },
  {
    "segmentnr":"ZH_T26_1543_004:0788c14_17",
    "original":"欲愛已盡，一切不成就。",
    "folio":4,
    "analyzed":"欲 愛 已 盡  一 切 不 成 就  "
  },
  {
    "segmentnr":"ZH_T26_1543_004:0788c15_12",
    "original":"蓋中，欲愛未盡，四成就，一不成就；",
    "folio":4,
    "analyzed":"蓋 中  欲 愛 未 盡  四 成 就  一 不 成 就  "
  },
  {
    "segmentnr":"ZH_T26_1543_004:0788c16_2",
    "original":"欲愛已盡，一切不成就。",
    "folio":4,
    "analyzed":"欲 愛 已 盡  一 切 不 成 就  "
  },
  {
    "segmentnr":"ZH_T26_1543_004:0788c16_15",
    "original":"結中，欲愛未盡，一切成就；",
    "folio":4,
    "analyzed":"結 中  欲 愛 未 盡  一切成就  "
  },
  {
    "segmentnr":"ZH_T26_1543_004:0788c17_7",
    "original":"欲愛已盡，二成就，三不成就。",
    "folio":4,
    "analyzed":"欲 愛 已 盡  二 成 就  三 不 成 就  "
  },
  {
    "segmentnr":"ZH_T26_1543_004:0788c18_3",
    "original":"下分中，欲愛未盡，二成就，三不成就；",
    "folio":4,
    "analyzed":"下 分 中  欲 愛 未 盡  二 成 就  三 不 成 就  "
  },
  {
    "segmentnr":"ZH_T26_1543_004:0788c18_14",
    "original":"欲愛已盡，一切不成就。",
    "folio":4,
    "analyzed":"欲 愛 已 盡  一 切 不 成 就  "
  },
  {
    "segmentnr":"ZH_T26_1543_004:0788c18_19",
    "original":"見不成就。",
    "folio":4,
    "analyzed":"見 不 成 就  "
  },
  {
    "segmentnr":"ZH_T26_1543_004:0788c19_12",
    "original":"身愛中，欲愛未盡，一切成就；",
    "folio":4,
    "analyzed":"身 愛 中  欲 愛 未 盡  一切成就  "
  },
  {
    "segmentnr":"ZH_T26_1543_004:0788c20_12",
    "original":"欲愛已盡、梵天愛未盡，四成就，二不成就；",
    "folio":4,
    "analyzed":"欲 愛 已 盡  梵 天 愛 未 盡  四 成 就  二 不 成 就  "
  },
  {
    "segmentnr":"ZH_T26_1543_004:0788c21_4",
    "original":"梵天愛盡，一成就，五不成就。",
    "folio":4,
    "analyzed":"梵 天 愛 盡  一 成 就  五 不 成 就  "
  },
  {
    "segmentnr":"ZH_T26_1543_004:0788c21_21",
    "original":"使中，欲愛未盡，五成就，二不成就；",
    "folio":4,
    "analyzed":"使 中  欲 愛 未 盡  五 成 就  二 不 成 就  "
  },
  {
    "segmentnr":"ZH_T26_1543_004:0788c22_13",
    "original":"欲愛已盡，三成就，四不成就。",
    "folio":4,
    "analyzed":"欲 愛 已 盡  三 成 就  四 不 成 就  "
  },
  {
    "segmentnr":"ZH_T26_1543_004:0788c23_8",
    "original":"結中，欲愛未盡，六成就，三不成就；",
    "folio":4,
    "analyzed":"結 中  欲 愛 未 盡  六 成 就  三 不 成 就  "
  },
  {
    "segmentnr":"ZH_T26_1543_004:0788c24_1",
    "original":"欲愛已盡，三成就，六不成就。",
    "folio":4,
    "analyzed":"欲 愛 已 盡  三 成 就  六 不 成 就  "
  },
  {
    "segmentnr":"ZH_T26_1543_004:0788c25_2",
    "original":"九十八使中，欲愛未盡，十成就，八十八不成就；",
    "folio":4,
    "analyzed":"九 十 八 使 中  欲 愛 未 盡  十 成 就  八 十 八 不 成 就  "
  },
  {
    "segmentnr":"ZH_T26_1543_004:0788c26_2",
    "original":"欲愛已盡、色愛未盡，六成就，九十二不成就；",
    "folio":4,
    "analyzed":"欲 愛 已 盡  色 愛 未 盡  六 成 就  九 十 二 不 成 就  "
  },
  {
    "segmentnr":"ZH_T26_1543_004:0788c27_3",
    "original":"色愛已盡、無色愛未盡，三成就，九十五不成就。",
    "folio":4,
    "analyzed":"色 愛 已 盡  無 色 愛 未 盡  三 成 就  九 十 五 不 成 就  "
  },
  {
    "segmentnr":"ZH_T26_1543_004:0788c27_10",
    "original":"見到亦復如是。",
    "folio":4,
    "analyzed":"見 到 亦復如是  "
  },
  {
    "segmentnr":"ZH_T26_1543_004:0788c28_6",
    "original":"身證人，此三結，幾成就、幾不成就？",
    "folio":4,
    "analyzed":"身 證 人  此 三 結  幾 成 就  幾 不 成 就  "
  },
  {
    "segmentnr":"ZH_T26_1543_004:0788c28_9",
    "original":"答曰：",
    "folio":4,
    "analyzed":"答 曰  "
  },
  {
    "segmentnr":"ZH_T26_1543_004:0788c28_15",
    "original":"一切不成就。",
    "folio":4,
    "analyzed":"一 切 不 成 就  "
  },
  {
    "segmentnr":"ZH_T26_1543_004:0788c29_3",
    "original":"貪、瞋恚、愚癡不成就。",
    "folio":4,
    "analyzed":"貪  瞋 恚  愚 癡 不 成 就  "
  },
  {
    "segmentnr":"ZH_T26_1543_004:0788c29_16",
    "original":"有漏中，二成就，一不成就。",
    "folio":4,
    "analyzed":"有 漏 中  二 成 就  一 不 成 就  "
  },
  {
    "segmentnr":"ZH_T26_1543_004:0789a01_6",
    "original":"流中，二成就，二不成就。",
    "folio":4,
    "analyzed":"流 中  二 成 就  二 不 成 就  "
  },
  {
    "segmentnr":"ZH_T26_1543_004:0789a01_11",
    "original":"軛亦如是。",
    "folio":4,
    "analyzed":"軛 亦 如 是  "
  },
  {
    "segmentnr":"ZH_T26_1543_004:0789a02_1",
    "original":"受中，一成就，三不成就。",
    "folio":4,
    "analyzed":"受 中  一 成 就  三 不 成 就  "
  },
  {
    "segmentnr":"ZH_T26_1543_004:0789a02_6",
    "original":"縛不成就。",
    "folio":4,
    "analyzed":"縛 不 成 就  "
  },
  {
    "segmentnr":"ZH_T26_1543_004:0789a02_11",
    "original":"蓋不成就。",
    "folio":4,
    "analyzed":"蓋 不 成 就  "
  },
  {
    "segmentnr":"ZH_T26_1543_004:0789a03_1",
    "original":"結中，二成就，三不成就。",
    "folio":4,
    "analyzed":"結 中  二 成 就  三 不 成 就  "
  },
  {
    "segmentnr":"ZH_T26_1543_004:0789a03_7",
    "original":"下分不成就。",
    "folio":4,
    "analyzed":"下 分 不 成 就  "
  },
  {
    "segmentnr":"ZH_T26_1543_004:0789a03_12",
    "original":"見不成就。",
    "folio":4,
    "analyzed":"見 不 成 就  "
  },
  {
    "segmentnr":"ZH_T26_1543_004:0789a04_3",
    "original":"身愛中，一成就，五不成就。",
    "folio":4,
    "analyzed":"身 愛 中  一 成 就  五 不 成 就  "
  },
  {
    "segmentnr":"ZH_T26_1543_004:0789a04_15",
    "original":"使中，三成就，四不成就。",
    "folio":4,
    "analyzed":"使 中  三 成 就  四 不 成 就  "
  },
  {
    "segmentnr":"ZH_T26_1543_004:0789a05_4",
    "original":"結中，三成就，六不成就。",
    "folio":4,
    "analyzed":"結 中  三 成 就  六 不 成 就  "
  },
  {
    "segmentnr":"ZH_T26_1543_004:0789a06_5",
    "original":"九十八使中，三成就，九十五不成就十二門竟。",
    "folio":4,
    "analyzed":"九 十 八 使 中  三 成 就  九 十 五 不 成 就 十 二 門 竟  "
  },
  {
    "segmentnr":"ZH_T26_1543_004:0789a06_15",
    "original":"身見，彼身見幾緣緣？",
    "folio":4,
    "analyzed":"身 見  彼 身 見 幾 緣 緣  "
  },
  {
    "segmentnr":"ZH_T26_1543_004:0789a06_18",
    "original":"答曰：",
    "folio":4,
    "analyzed":"答 曰  "
  },
  {
    "segmentnr":"ZH_T26_1543_004:0789a07_1",
    "original":"或四三二一。",
    "folio":4,
    "analyzed":"或 四 三 二 一  "
  },
  {
    "segmentnr":"ZH_T26_1543_004:0789a07_4",
    "original":"誰四？",
    "folio":4,
    "analyzed":"誰 四  "
  },
  {
    "segmentnr":"ZH_T26_1543_004:0789a07_7",
    "original":"答曰：",
    "folio":4,
    "analyzed":"答 曰  "
  },
  {
    "segmentnr":"ZH_T26_1543_004:0789a08_19",
    "original":"如身見次第生身見，即彼思惟前生後生，因、次第、緣、增上，是謂四。",
    "folio":4,
    "analyzed":"如 身 見 次 第 生 身 見  即 彼 思 惟 前 生 後 生  因  次 第  緣  增 上  是 謂 四  "
  },
  {
    "segmentnr":"ZH_T26_1543_004:0789a08_22",
    "original":"誰三？",
    "folio":4,
    "analyzed":"誰 三  "
  },
  {
    "segmentnr":"ZH_T26_1543_004:0789a09_1",
    "original":"答曰：",
    "folio":4,
    "analyzed":"答 曰  "
  },
  {
    "segmentnr":"ZH_T26_1543_004:0789a10_12",
    "original":"如身見次第生身見，即彼不思惟前生後生，因、次第、增上，無緣。",
    "folio":4,
    "analyzed":"如 身 見 次 第 生 身 見  即 彼 不 思 惟 前 生 後 生  因  次 第  增 上  無 緣  "
  },
  {
    "segmentnr":"ZH_T26_1543_004:0789a12_5",
    "original":"如身見次第生若干心生身見，即彼思惟前生後生，因、緣、增上，無次第，是謂三。",
    "folio":4,
    "analyzed":"如 身 見 次 第 生 若 干 心 生 身 見  即 彼 思 惟 前 生 後 生  因  緣  增 上  無 次 第  是 謂 三  "
  },
  {
    "segmentnr":"ZH_T26_1543_004:0789a12_8",
    "original":"誰二？",
    "folio":4,
    "analyzed":"誰 二  "
  },
  {
    "segmentnr":"ZH_T26_1543_004:0789a12_11",
    "original":"答曰：",
    "folio":4,
    "analyzed":"答 曰  "
  },
  {
    "segmentnr":"ZH_T26_1543_004:0789a14_2",
    "original":"如身見次第生若干心生身見，即彼不思惟前生後生，因、增上，是謂二。",
    "folio":4,
    "analyzed":"如 身 見 次 第 生 若 干 心 生 身 見  即 彼 不 思 惟 前 生 後 生  因  增 上  是 謂 二  "
  },
  {
    "segmentnr":"ZH_T26_1543_004:0789a14_5",
    "original":"誰一？",
    "folio":4,
    "analyzed":"誰 一  "
  },
  {
    "segmentnr":"ZH_T26_1543_004:0789a14_8",
    "original":"答曰：",
    "folio":4,
    "analyzed":"答 曰  "
  },
  {
    "segmentnr":"ZH_T26_1543_004:0789a14_22",
    "original":"後生前生，若與緣，緣、增上；",
    "folio":4,
    "analyzed":"後 生 前 生  若 與 緣  緣  增 上  "
  },
  {
    "segmentnr":"ZH_T26_1543_004:0789a15_7",
    "original":"不與緣，一增上。",
    "folio":4,
    "analyzed":"不 與 緣  一 增 上  "
  },
  {
    "segmentnr":"ZH_T26_1543_004:0789a16_1",
    "original":"未來過去現在，若與緣，緣、增上；",
    "folio":4,
    "analyzed":"未 來 過去現在  若 與 緣  緣  增 上  "
  },
  {
    "segmentnr":"ZH_T26_1543_004:0789a16_9",
    "original":"不與緣，一增上。",
    "folio":4,
    "analyzed":"不 與 緣  一 增 上  "
  },
  {
    "segmentnr":"ZH_T26_1543_004:0789a17_2",
    "original":"未來現在過去，若與緣，緣、增上；",
    "folio":4,
    "analyzed":"未來現在 過 去  若 與 緣  緣  增 上  "
  },
  {
    "segmentnr":"ZH_T26_1543_004:0789a17_10",
    "original":"不與緣，一增上。",
    "folio":4,
    "analyzed":"不 與 緣  一 增 上  "
  },
  {
    "segmentnr":"ZH_T26_1543_004:0789a17_22",
    "original":"欲界繫、色界繫，一增上。",
    "folio":4,
    "analyzed":"欲 界 繫  色 界 繫  一 增 上  "
  },
  {
    "segmentnr":"ZH_T26_1543_004:0789a18_18",
    "original":"色界繫、欲界繫，若與次第，次第、增上；",
    "folio":4,
    "analyzed":"色 界 繫  欲 界 繫  若 與 次 第  次 第  增 上  "
  },
  {
    "segmentnr":"ZH_T26_1543_004:0789a19_5",
    "original":"不與次第，一增上。",
    "folio":4,
    "analyzed":"不 與 次 第  一 增 上  "
  },
  {
    "segmentnr":"ZH_T26_1543_004:0789a19_18",
    "original":"欲界繫、無色界繫，一增上。",
    "folio":4,
    "analyzed":"欲 界 繫  無 色 界 繫  一 增 上  "
  },
  {
    "segmentnr":"ZH_T26_1543_004:0789a20_16",
    "original":"無色界繫、欲界繫，若與次第，次第、增上；",
    "folio":4,
    "analyzed":"無 色 界 繫  欲 界 繫  若 與 次 第  次 第  增 上  "
  },
  {
    "segmentnr":"ZH_T26_1543_004:0789a21_2",
    "original":"不與次第，一增上。",
    "folio":4,
    "analyzed":"不 與 次 第  一 增 上  "
  },
  {
    "segmentnr":"ZH_T26_1543_004:0789a21_15",
    "original":"色界繫、無色界繫，一增上。",
    "folio":4,
    "analyzed":"色 界 繫  無 色 界 繫  一 增 上  "
  },
  {
    "segmentnr":"ZH_T26_1543_004:0789a22_13",
    "original":"無色界繫、色界繫，若與次第，次第、增上；",
    "folio":4,
    "analyzed":"無 色 界 繫  色 界 繫  若 與 次 第  次 第  增 上  "
  },
  {
    "segmentnr":"ZH_T26_1543_004:0789a22_22",
    "original":"不與次第，一增上。",
    "folio":4,
    "analyzed":"不 與 次 第  一 增 上  "
  },
  {
    "segmentnr":"ZH_T26_1543_004:0789a24_5",
    "original":"如身見，身見如是，不一切遍不一切遍，不一切遍一切遍。",
    "folio":4,
    "analyzed":"如 身 見  身 見 如 是  不 一 切 遍 不 一 切 遍  不 一 切 遍 一 切 遍  "
  },
  {
    "segmentnr":"ZH_T26_1543_004:0789a24_15",
    "original":"身見、戒盜有幾緣緣？",
    "folio":4,
    "analyzed":"身 見  戒 盜 有 幾 緣 緣  "
  },
  {
    "segmentnr":"ZH_T26_1543_004:0789a24_18",
    "original":"答曰：",
    "folio":4,
    "analyzed":"答 曰  "
  },
  {
    "segmentnr":"ZH_T26_1543_004:0789a25_3",
    "original":"或四三二一。",
    "folio":4,
    "analyzed":"或 四 三 二 一  "
  },
  {
    "segmentnr":"ZH_T26_1543_004:0789a25_6",
    "original":"誰四？",
    "folio":4,
    "analyzed":"誰 四  "
  },
  {
    "segmentnr":"ZH_T26_1543_004:0789a25_9",
    "original":"答曰：",
    "folio":4,
    "analyzed":"答 曰  "
  },
  {
    "segmentnr":"ZH_T26_1543_004:0789a26_20",
    "original":"如身見次第生戒盜，即彼思惟前生後生，因、次第、緣、增上，是謂四。",
    "folio":4,
    "analyzed":"如 身 見 次 第 生 戒 盜  即 彼 思 惟 前 生 後 生  因  次 第  緣  增 上  是 謂 四  "
  },
  {
    "segmentnr":"ZH_T26_1543_004:0789a26_23",
    "original":"誰三？",
    "folio":4,
    "analyzed":"誰 三  "
  },
  {
    "segmentnr":"ZH_T26_1543_004:0789a27_2",
    "original":"答曰：",
    "folio":4,
    "analyzed":"答 曰  "
  },
  {
    "segmentnr":"ZH_T26_1543_004:0789a28_13",
    "original":"如身見次第生戒盜，即彼不思惟前生後生，因、次第、增上，無緣。",
    "folio":4,
    "analyzed":"如 身 見 次 第 生 戒 盜  即 彼 不 思 惟 前 生 後 生  因  次 第  增 上  無 緣  "
  },
  {
    "segmentnr":"ZH_T26_1543_004:0789b01_6",
    "original":"如身見次第生若干心生戒盜，即彼思惟前生後生，因、緣、增上，無次第，是謂三。",
    "folio":4,
    "analyzed":"如 身 見 次 第 生 若 干 心 生 戒 盜  即 彼 思 惟 前 生 後 生  因  緣  增 上  無 次 第  是 謂 三  "
  },
  {
    "segmentnr":"ZH_T26_1543_004:0789b01_9",
    "original":"誰二？",
    "folio":4,
    "analyzed":"誰 二  "
  },
  {
    "segmentnr":"ZH_T26_1543_004:0789b01_12",
    "original":"答曰：",
    "folio":4,
    "analyzed":"答 曰  "
  },
  {
    "segmentnr":"ZH_T26_1543_004:0789b03_3",
    "original":"如身見次第生若干心生戒盜，即彼不思惟前生後生，因、增上，是謂二。",
    "folio":4,
    "analyzed":"如 身 見 次 第 生 若 干 心 生 戒 盜  即 彼 不 思 惟 前 生 後 生  因  增 上  是 謂 二  "
  },
  {
    "segmentnr":"ZH_T26_1543_004:0789b03_6",
    "original":"誰一？",
    "folio":4,
    "analyzed":"誰 一  "
  },
  {
    "segmentnr":"ZH_T26_1543_004:0789b03_9",
    "original":"答曰：",
    "folio":4,
    "analyzed":"答 曰  "
  },
  {
    "segmentnr":"ZH_T26_1543_004:0789b03_23",
    "original":"後生前生，若與緣，緣、增上；",
    "folio":4,
    "analyzed":"後 生 前 生  若 與 緣  緣  增 上  "
  },
  {
    "segmentnr":"ZH_T26_1543_004:0789b04_7",
    "original":"不與緣，一增上。",
    "folio":4,
    "analyzed":"不 與 緣  一 增 上  "
  },
  {
    "segmentnr":"ZH_T26_1543_004:0789b05_1",
    "original":"未來過去現在，若與緣，緣、增上；",
    "folio":4,
    "analyzed":"未 來 過去現在  若 與 緣  緣  增 上  "
  },
  {
    "segmentnr":"ZH_T26_1543_004:0789b05_9",
    "original":"不與緣，一增上。",
    "folio":4,
    "analyzed":"不 與 緣  一 增 上  "
  },
  {
    "segmentnr":"ZH_T26_1543_004:0789b06_2",
    "original":"未來現在過去，若與緣，緣、增上；",
    "folio":4,
    "analyzed":"未來現在 過 去  若 與 緣  緣  增 上  "
  },
  {
    "segmentnr":"ZH_T26_1543_004:0789b06_10",
    "original":"不與緣，一增上。",
    "folio":4,
    "analyzed":"不 與 緣  一 增 上  "
  },
  {
    "segmentnr":"ZH_T26_1543_004:0789b06_22",
    "original":"欲界繫、色界繫，一增上。",
    "folio":4,
    "analyzed":"欲 界 繫  色 界 繫  一 增 上  "
  },
  {
    "segmentnr":"ZH_T26_1543_004:0789b07_21",
    "original":"色界繫、欲界繫，若與次第、無緣，次第、增上；",
    "folio":4,
    "analyzed":"色 界 繫  欲 界 繫  若 與 次 第  無 緣  次 第  增 上  "
  },
  {
    "segmentnr":"ZH_T26_1543_004:0789b08_11",
    "original":"若與緣、無次第，緣、增上；",
    "folio":4,
    "analyzed":"若 與 緣  無 次 第  緣  增 上  "
  },
  {
    "segmentnr":"ZH_T26_1543_004:0789b09_1",
    "original":"若與次第、緣，次第、緣、增上；",
    "folio":4,
    "analyzed":"若 與 次 第  緣  次 第  緣  增 上  "
  },
  {
    "segmentnr":"ZH_T26_1543_004:0789b09_13",
    "original":"若不與次第、緣，一增上。",
    "folio":4,
    "analyzed":"若 不 與 次 第  緣  一 增 上  "
  },
  {
    "segmentnr":"ZH_T26_1543_004:0789b10_3",
    "original":"欲界繫、無色界繫，一增上。",
    "folio":4,
    "analyzed":"欲 界 繫  無 色 界 繫  一 增 上  "
  },
  {
    "segmentnr":"ZH_T26_1543_004:0789b11_4",
    "original":"無色界繫、欲界繫，若與次第、無緣，次第、增上；",
    "folio":4,
    "analyzed":"無 色 界 繫  欲 界 繫  若 與 次 第  無 緣  次 第  增 上  "
  },
  {
    "segmentnr":"ZH_T26_1543_004:0789b11_17",
    "original":"若與緣、無次第，緣、增上；",
    "folio":4,
    "analyzed":"若 與 緣  無 次 第  緣  增 上  "
  },
  {
    "segmentnr":"ZH_T26_1543_004:0789b12_7",
    "original":"若與次第、緣，次第、緣、增上；",
    "folio":4,
    "analyzed":"若 與 次 第  緣  次 第  緣  增 上  "
  },
  {
    "segmentnr":"ZH_T26_1543_004:0789b12_19",
    "original":"若不與次第、緣，一增上。",
    "folio":4,
    "analyzed":"若 不 與 次 第  緣  一 增 上  "
  },
  {
    "segmentnr":"ZH_T26_1543_004:0789b13_8",
    "original":"色界繫、無色界繫，一增上。",
    "folio":4,
    "analyzed":"色 界 繫  無 色 界 繫  一 增 上  "
  },
  {
    "segmentnr":"ZH_T26_1543_004:0789b14_11",
    "original":"無色界繫、色界繫，若與次第、無緣，次第、增上；",
    "folio":4,
    "analyzed":"無 色 界 繫  色 界 繫  若 與 次 第  無 緣  次 第  增 上  "
  },
  {
    "segmentnr":"ZH_T26_1543_004:0789b14_24",
    "original":"若與緣、無次第，緣、增上；",
    "folio":4,
    "analyzed":"若 與 緣  無 次 第  緣  增 上  "
  },
  {
    "segmentnr":"ZH_T26_1543_004:0789b15_14",
    "original":"若與次第、緣，次第、緣、增上；",
    "folio":4,
    "analyzed":"若 與 次 第  緣  次 第  緣  增 上  "
  },
  {
    "segmentnr":"ZH_T26_1543_004:0789b16_2",
    "original":"若不與次第、緣，一增上。",
    "folio":4,
    "analyzed":"若 不 與 次 第  緣  一 增 上  "
  },
  {
    "segmentnr":"ZH_T26_1543_004:0789b16_11",
    "original":"如身見，戒盜如是。",
    "folio":4,
    "analyzed":"如 身 見  戒 盜 如 是  "
  },
  {
    "segmentnr":"ZH_T26_1543_004:0789b17_7",
    "original":"不一切遍一切遍，一切遍不一切遍。",
    "folio":4,
    "analyzed":"不 一 切 遍 一 切 遍  一 切 遍 不 一 切 遍  "
  },
  {
    "segmentnr":"ZH_T26_1543_004:0789b18_23",
    "original":"阿毘曇不善品第九竟梵本六百二首盧，秦長十四字也。",
    "folio":4,
    "analyzed":"阿 毘 曇 不 善 品 第 九 竟 梵 本 六 百 二 首 盧  秦 長 十 四 字 也  "
  },
  {
    "segmentnr":"ZH_T26_1543_004:0789b19_100",
    "original":"阿毘曇八犍度論卷第四",
    "folio":4,
    "analyzed":"阿 毘 曇 八 犍 度 論 卷 第 四 "
  }
]