[
  {
    "segmentnr":"ZH_T19_0996_001:0522a05_0",
    "original":"仁王般若陀羅尼釋一卷",
    "folio":1,
    "analyzed":"仁 王 般 若 陀 羅 尼 釋 一 卷 "
  },
  {
    "segmentnr":"ZH_T19_0996_001:0522a07_0",
    "original":"開府儀同三司特進試鴻臚卿",
    "folio":1,
    "analyzed":"開 府 儀 同 三 司 特 進 試 鴻 臚 卿 "
  },
  {
    "segmentnr":"ZH_T19_0996_001:0522a08_0",
    "original":"肅國公食邑三千戶賜紫贈司",
    "folio":1,
    "analyzed":"肅 國 公 食 邑 三 千 戶 賜 紫 贈 司 "
  },
  {
    "segmentnr":"ZH_T19_0996_001:0522a11_4",
    "original":"空謚大鑑正號大廣智大興善寺三藏沙門不空奉　詔譯金剛手者。",
    "folio":1,
    "analyzed":"空 謚 大 鑑 正 號 大 廣 智 大 興 善 寺 三 藏 沙 門 不 空 奉  詔 譯 金 剛 手 者  "
  },
  {
    "segmentnr":"ZH_T19_0996_001:0522a11_10",
    "original":"瑜伽經釋云。",
    "folio":1,
    "analyzed":"瑜 伽 經 釋 云  "
  },
  {
    "segmentnr":"ZH_T19_0996_001:0522a11_16",
    "original":"手持金剛杵。",
    "folio":1,
    "analyzed":"手 持 金 剛 杵  "
  },
  {
    "segmentnr":"ZH_T19_0996_001:0522a12_4",
    "original":"表內心具大菩提。",
    "folio":1,
    "analyzed":"表 內 心 具 大 菩 提  "
  },
  {
    "segmentnr":"ZH_T19_0996_001:0522a12_12",
    "original":"外表摧伏諸煩惱。",
    "folio":1,
    "analyzed":"外 表 摧 伏 諸 煩 惱  "
  },
  {
    "segmentnr":"ZH_T19_0996_001:0522a12_18",
    "original":"故名金剛手。",
    "folio":1,
    "analyzed":"故 名 金 剛 手  "
  },
  {
    "segmentnr":"ZH_T19_0996_001:0522a13_3",
    "original":"又釋云。",
    "folio":1,
    "analyzed":"又 釋 云  "
  },
  {
    "segmentnr":"ZH_T19_0996_001:0522a13_11",
    "original":"不被三種魔破壞。",
    "folio":1,
    "analyzed":"不 被 三 種 魔 破 壞  "
  },
  {
    "segmentnr":"ZH_T19_0996_001:0522a14_4",
    "original":"菩提心自體堅固成金剛智。",
    "folio":1,
    "analyzed":"菩 提 心 自 體 堅 固 成 金 剛 智  "
  },
  {
    "segmentnr":"ZH_T19_0996_001:0522a14_13",
    "original":"一切如來之所建立。",
    "folio":1,
    "analyzed":"一 切 如 來 之 所 建 立  "
  },
  {
    "segmentnr":"ZH_T19_0996_001:0522a15_1",
    "original":"能破斷常二邊。",
    "folio":1,
    "analyzed":"能 破 斷 常 二 邊  "
  },
  {
    "segmentnr":"ZH_T19_0996_001:0522a15_12",
    "original":"是故金剛智杵破邪見山。",
    "folio":1,
    "analyzed":"是 故 金 剛 智 杵 破 邪 見 山  "
  },
  {
    "segmentnr":"ZH_T19_0996_001:0522a16_3",
    "original":"證金剛定常持於掌中。",
    "folio":1,
    "analyzed":"證 金 剛 定 常 持 於 掌 中  "
  },
  {
    "segmentnr":"ZH_T19_0996_001:0522a16_9",
    "original":"故名金剛手。",
    "folio":1,
    "analyzed":"故 名 金 剛 手  "
  },
  {
    "segmentnr":"ZH_T19_0996_001:0522a17_7",
    "original":"云何菩提薩埵義。",
    "folio":1,
    "analyzed":"云 何 菩 提 薩 埵 義  "
  },
  {
    "segmentnr":"ZH_T19_0996_001:0522a17_13",
    "original":"覺悟真實法。",
    "folio":1,
    "analyzed":"覺 悟 真 實 法  "
  },
  {
    "segmentnr":"ZH_T19_0996_001:0522a17_19",
    "original":"覺已住生死。",
    "folio":1,
    "analyzed":"覺 已 住 生 死  "
  },
  {
    "segmentnr":"ZH_T19_0996_001:0522a18_7",
    "original":"令覺悟一切有情。",
    "folio":1,
    "analyzed":"令 覺 悟 一切有情  "
  },
  {
    "segmentnr":"ZH_T19_0996_001:0522a18_14",
    "original":"故名菩提薩埵。",
    "folio":1,
    "analyzed":"故 名 菩 提 薩 埵  "
  },
  {
    "segmentnr":"ZH_T19_0996_001:0522a19_4",
    "original":"又云菩提者能覺義。",
    "folio":1,
    "analyzed":"又 云 菩 提 者 能 覺 義  "
  },
  {
    "segmentnr":"ZH_T19_0996_001:0522a19_11",
    "original":"薩埵者有情義。",
    "folio":1,
    "analyzed":"薩 埵 者 有 情 義  "
  },
  {
    "segmentnr":"ZH_T19_0996_001:0522a20_1",
    "original":"亦云心亦云勇健。",
    "folio":1,
    "analyzed":"亦 云 心 亦 云 勇 健  "
  },
  {
    "segmentnr":"ZH_T19_0996_001:0522a20_7",
    "original":"摩賀者大義。",
    "folio":1,
    "analyzed":"摩 賀 者 大 義  "
  },
  {
    "segmentnr":"ZH_T19_0996_001:0522a20_15",
    "original":"薩埵者是勇健義。",
    "folio":1,
    "analyzed":"薩 埵 者 是 勇 健 義  "
  },
  {
    "segmentnr":"ZH_T19_0996_001:0522a20_19",
    "original":"不怯弱。",
    "folio":1,
    "analyzed":"不 怯 弱  "
  },
  {
    "segmentnr":"ZH_T19_0996_001:0522a21_11",
    "original":"三大無數劫積集二種資糧。",
    "folio":1,
    "analyzed":"三 大 無 數 劫 積 集 二 種 資 糧  "
  },
  {
    "segmentnr":"ZH_T19_0996_001:0522a21_18",
    "original":"故名摩訶薩埵。",
    "folio":1,
    "analyzed":"故 名 摩 訶 薩 埵  "
  },
  {
    "segmentnr":"ZH_T19_0996_001:0522a22_10",
    "original":"云何金剛摩尼唐云是寶。",
    "folio":1,
    "analyzed":"云 何 金 剛 摩 尼 唐 云 是 寶  "
  },
  {
    "segmentnr":"ZH_T19_0996_001:0522a22_16",
    "original":"金剛如前釋。",
    "folio":1,
    "analyzed":"金 剛 如 前 釋  "
  },
  {
    "segmentnr":"ZH_T19_0996_001:0522a22_21",
    "original":"寶義有六。",
    "folio":1,
    "analyzed":"寶 義 有 六  "
  },
  {
    "segmentnr":"ZH_T19_0996_001:0522a23_5",
    "original":"一者難得故。",
    "folio":1,
    "analyzed":"一 者 難 得 故  "
  },
  {
    "segmentnr":"ZH_T19_0996_001:0522a23_12",
    "original":"二者淨無垢故。",
    "folio":1,
    "analyzed":"二 者 淨 無 垢 故  "
  },
  {
    "segmentnr":"ZH_T19_0996_001:0522a24_1",
    "original":"三者有大威德故。",
    "folio":1,
    "analyzed":"三 者 有 大 威 德 故  "
  },
  {
    "segmentnr":"ZH_T19_0996_001:0522a24_9",
    "original":"四者莊嚴世間故。",
    "folio":1,
    "analyzed":"四 者 莊 嚴 世 間 故  "
  },
  {
    "segmentnr":"ZH_T19_0996_001:0522a24_17",
    "original":"五者殊勝無比故。",
    "folio":1,
    "analyzed":"五 者 殊 勝 無 比 故  "
  },
  {
    "segmentnr":"ZH_T19_0996_001:0522a25_4",
    "original":"六者不變易故。",
    "folio":1,
    "analyzed":"六 者 不 變 易 故  "
  },
  {
    "segmentnr":"ZH_T19_0996_001:0522a25_9",
    "original":"一難得者。",
    "folio":1,
    "analyzed":"一 難 得 者  "
  },
  {
    "segmentnr":"ZH_T19_0996_001:0522a26_3",
    "original":"如來出現於世間甚難逢遇故。",
    "folio":1,
    "analyzed":"如 來 出 現 於 世 間 甚 難 逢 遇 故  "
  },
  {
    "segmentnr":"ZH_T19_0996_001:0522a26_9",
    "original":"二淨無垢者。",
    "folio":1,
    "analyzed":"二 淨 無 垢 者  "
  },
  {
    "segmentnr":"ZH_T19_0996_001:0522a27_3",
    "original":"依教修行證得菩提淨無垢故。",
    "folio":1,
    "analyzed":"依 教 修 行 證 得 菩 提 淨 無 垢 故  "
  },
  {
    "segmentnr":"ZH_T19_0996_001:0522a27_9",
    "original":"三大威德者。",
    "folio":1,
    "analyzed":"三 大 威 德 者  "
  },
  {
    "segmentnr":"ZH_T19_0996_001:0522a28_4",
    "original":"具六神通變現自在名大威德故。",
    "folio":1,
    "analyzed":"具 六 神通變現 自 在 名 大 威 德 故  "
  },
  {
    "segmentnr":"ZH_T19_0996_001:0522a28_11",
    "original":"四莊嚴世間者。",
    "folio":1,
    "analyzed":"四 莊 嚴 世 間 者  "
  },
  {
    "segmentnr":"ZH_T19_0996_001:0522a29_1",
    "original":"以三種菩薩律儀戒。",
    "folio":1,
    "analyzed":"以 三 種 菩 薩 律 儀 戒  "
  },
  {
    "segmentnr":"ZH_T19_0996_001:0522a29_7",
    "original":"嚴飾身心故。",
    "folio":1,
    "analyzed":"嚴 飾 身 心 故  "
  },
  {
    "segmentnr":"ZH_T19_0996_001:0522a29_14",
    "original":"五殊勝無比者。",
    "folio":1,
    "analyzed":"五 殊 勝 無 比 者  "
  },
  {
    "segmentnr":"ZH_T19_0996_001:0522b01_11",
    "original":"證得無上菩提三界特尊殊勝無比故。",
    "folio":1,
    "analyzed":"證 得 無上菩提 三 界 特 尊 殊 勝 無 比 故  "
  },
  {
    "segmentnr":"ZH_T19_0996_001:0522b01_17",
    "original":"六無變易者。",
    "folio":1,
    "analyzed":"六 無 變 易 者  "
  },
  {
    "segmentnr":"ZH_T19_0996_001:0522b02_11",
    "original":"證得究竟無上菩提不變易故。",
    "folio":1,
    "analyzed":"證 得 究 竟 無上菩提 不 變 易 故  "
  },
  {
    "segmentnr":"ZH_T19_0996_001:0522b02_16",
    "original":"金剛摩尼。",
    "folio":1,
    "analyzed":"金 剛 摩 尼  "
  },
  {
    "segmentnr":"ZH_T19_0996_001:0522b03_6",
    "original":"顯名虛空藏菩薩。",
    "folio":1,
    "analyzed":"顯 名 虛 空 藏 菩 薩  "
  },
  {
    "segmentnr":"ZH_T19_0996_001:0522b03_17",
    "original":"是故此菩薩手捧金剛寶。",
    "folio":1,
    "analyzed":"是 故 此 菩 薩 手 捧 金 剛 寶  "
  },
  {
    "segmentnr":"ZH_T19_0996_001:0522b04_4",
    "original":"金剛利者。",
    "folio":1,
    "analyzed":"金 剛 利 者  "
  },
  {
    "segmentnr":"ZH_T19_0996_001:0522b04_14",
    "original":"般若波羅蜜金剛利劍。",
    "folio":1,
    "analyzed":"般 若 波 羅 蜜 金 剛 利 劍  "
  },
  {
    "segmentnr":"ZH_T19_0996_001:0522b05_1",
    "original":"能斷煩惱種。",
    "folio":1,
    "analyzed":"能 斷 煩 惱 種  "
  },
  {
    "segmentnr":"ZH_T19_0996_001:0522b05_9",
    "original":"一切種金剛利者。",
    "folio":1,
    "analyzed":"一 切 種 金 剛 利 者  "
  },
  {
    "segmentnr":"ZH_T19_0996_001:0522b05_18",
    "original":"顯名文殊師利菩薩。",
    "folio":1,
    "analyzed":"顯 名 文 殊 師 利 菩 薩  "
  },
  {
    "segmentnr":"ZH_T19_0996_001:0522b06_10",
    "original":"是故此菩薩手持金剛劍。",
    "folio":1,
    "analyzed":"是 故 此 菩 薩 手 持 金 剛 劍  "
  },
  {
    "segmentnr":"ZH_T19_0996_001:0522b07_7",
    "original":"金剛藥叉菩薩者。",
    "folio":1,
    "analyzed":"金 剛 藥 叉 菩 薩 者  "
  },
  {
    "segmentnr":"ZH_T19_0996_001:0522b07_14",
    "original":"金剛義如前釋。",
    "folio":1,
    "analyzed":"金 剛 義 如 前 釋  "
  },
  {
    "segmentnr":"ZH_T19_0996_001:0522b08_6",
    "original":"藥叉者威猛義亦云盡義。",
    "folio":1,
    "analyzed":"藥 叉 者 威 猛 義 亦 云 盡 義  "
  },
  {
    "segmentnr":"ZH_T19_0996_001:0522b09_2",
    "original":"十六金剛智普賢行中第十五智。",
    "folio":1,
    "analyzed":"十 六 金 剛 智 普 賢 行 中 第 十 五 智  "
  },
  {
    "segmentnr":"ZH_T19_0996_001:0522b09_8",
    "original":"名金剛盡智。",
    "folio":1,
    "analyzed":"名 金 剛 盡 智  "
  },
  {
    "segmentnr":"ZH_T19_0996_001:0522b09_16",
    "original":"以金剛藥叉智牙。",
    "folio":1,
    "analyzed":"以 金 剛 藥 叉 智 牙  "
  },
  {
    "segmentnr":"ZH_T19_0996_001:0522b10_7",
    "original":"食啗一切煩惱隨煩惱。",
    "folio":1,
    "analyzed":"食 啗 一切煩惱 隨 煩 惱  "
  },
  {
    "segmentnr":"ZH_T19_0996_001:0522b10_11",
    "original":"盡無餘。",
    "folio":1,
    "analyzed":"盡 無 餘  "
  },
  {
    "segmentnr":"ZH_T19_0996_001:0522b11_4",
    "original":"金剛鈴者。",
    "folio":1,
    "analyzed":"金 剛 鈴 者  "
  },
  {
    "segmentnr":"ZH_T19_0996_001:0522b11_12",
    "original":"表般若波羅蜜義。",
    "folio":1,
    "analyzed":"表 般 若 波 羅 蜜 義  "
  },
  {
    "segmentnr":"ZH_T19_0996_001:0522b12_2",
    "original":"振鈴警悟愚昧異生。",
    "folio":1,
    "analyzed":"振 鈴 警 悟 愚 昧 異 生  "
  },
  {
    "segmentnr":"ZH_T19_0996_001:0522b12_7",
    "original":"一聞鈴音。",
    "folio":1,
    "analyzed":"一 聞 鈴 音  "
  },
  {
    "segmentnr":"ZH_T19_0996_001:0522b12_15",
    "original":"覺悟般若波羅蜜。",
    "folio":1,
    "analyzed":"覺 悟 般 若 波 羅 蜜  "
  },
  {
    "segmentnr":"ZH_T19_0996_001:0522b13_5",
    "original":"顯名摧一切魔怨菩薩。",
    "folio":1,
    "analyzed":"顯 名 摧 一 切 魔 怨 菩 薩  "
  },
  {
    "segmentnr":"ZH_T19_0996_001:0522b13_16",
    "original":"是故此菩薩手持金剛鈴。",
    "folio":1,
    "analyzed":"是 故 此 菩 薩 手 持 金 剛 鈴  "
  },
  {
    "segmentnr":"ZH_T19_0996_001:0522b14_9",
    "original":"金剛波羅蜜多菩薩者。",
    "folio":1,
    "analyzed":"金 剛 波羅蜜多 菩 薩 者  "
  },
  {
    "segmentnr":"ZH_T19_0996_001:0522b14_16",
    "original":"金剛義如前釋。",
    "folio":1,
    "analyzed":"金 剛 義 如 前 釋  "
  },
  {
    "segmentnr":"ZH_T19_0996_001:0522b15_7",
    "original":"波羅蜜多如先輩所釋。",
    "folio":1,
    "analyzed":"波羅蜜多 如 先 輩 所 釋  "
  },
  {
    "segmentnr":"ZH_T19_0996_001:0522b15_12",
    "original":"到彼岸義。",
    "folio":1,
    "analyzed":"到 彼 岸 義  "
  },
  {
    "segmentnr":"ZH_T19_0996_001:0522b16_2",
    "original":"今依聲明論分句釋。",
    "folio":1,
    "analyzed":"今 依 聲 明 論 分 句 釋  "
  },
  {
    "segmentnr":"ZH_T19_0996_001:0522b16_8",
    "original":"波藍伊上多。",
    "folio":1,
    "analyzed":"波 藍 伊 上 多  "
  },
  {
    "segmentnr":"ZH_T19_0996_001:0522b16_14",
    "original":"波藍彼岸義。",
    "folio":1,
    "analyzed":"波 藍 彼 岸 義  "
  },
  {
    "segmentnr":"ZH_T19_0996_001:0522b17_2",
    "original":"伊上多此岸義。",
    "folio":1,
    "analyzed":"伊 上 多 此 岸 義  "
  },
  {
    "segmentnr":"ZH_T19_0996_001:0522b17_11",
    "original":"此菩薩由持金剛輪。",
    "folio":1,
    "analyzed":"此 菩 薩 由 持 金 剛 輪  "
  },
  {
    "segmentnr":"ZH_T19_0996_001:0522b18_4",
    "original":"毘盧遮那佛於上界成佛已。",
    "folio":1,
    "analyzed":"毘 盧 遮 那 佛 於 上 界 成 佛 已  "
  },
  {
    "segmentnr":"ZH_T19_0996_001:0522b18_17",
    "original":"此菩薩請如來轉金剛乘法輪。",
    "folio":1,
    "analyzed":"此 菩 薩 請 如 來 轉 金 剛 乘 法 輪  "
  },
  {
    "segmentnr":"ZH_T19_0996_001:0522b19_7",
    "original":"由乘此法輪般若船。",
    "folio":1,
    "analyzed":"由 乘 此 法 輪 般 若 船  "
  },
  {
    "segmentnr":"ZH_T19_0996_001:0522b20_1",
    "original":"從此岸運載無量無邊有情。",
    "folio":1,
    "analyzed":"從 此 岸 運 載 無量無邊 有 情  "
  },
  {
    "segmentnr":"ZH_T19_0996_001:0522b20_8",
    "original":"至無住涅槃岸。",
    "folio":1,
    "analyzed":"至 無住涅槃 岸  "
  },
  {
    "segmentnr":"ZH_T19_0996_001:0522b21_1",
    "original":"顯名纔發心轉法輪菩薩。",
    "folio":1,
    "analyzed":"顯 名 纔 發 心 轉法輪菩薩  "
  },
  {
    "segmentnr":"ZH_T19_0996_001:0522b22_5",
    "original":"娜莫囉怛那。",
    "folio":1,
    "analyzed":"娜 莫 囉 怛 那  "
  },
  {
    "segmentnr":"ZH_T19_0996_001:0522b22_10",
    "original":"怛囉夜耶。",
    "folio":1,
    "analyzed":"怛 囉 夜 耶  "
  },
  {
    "segmentnr":"ZH_T19_0996_001:0522b22_16",
    "original":"歸命三寶義。",
    "folio":1,
    "analyzed":"歸 命 三 寶 義  "
  },
  {
    "segmentnr":"ZH_T19_0996_001:0522b23_3",
    "original":"若持此經人。",
    "folio":1,
    "analyzed":"若 持 此 經 人  "
  },
  {
    "segmentnr":"ZH_T19_0996_001:0522b23_8",
    "original":"歸命佛寶。",
    "folio":1,
    "analyzed":"歸 命 佛 寶  "
  },
  {
    "segmentnr":"ZH_T19_0996_001:0522b23_18",
    "original":"即得五族金剛手菩薩。",
    "folio":1,
    "analyzed":"即 得 五 族 金剛手菩薩  "
  },
  {
    "segmentnr":"ZH_T19_0996_001:0522b24_6",
    "original":"以無量眷屬侍衛。",
    "folio":1,
    "analyzed":"以 無 量 眷 屬 侍 衛  "
  },
  {
    "segmentnr":"ZH_T19_0996_001:0522b24_11",
    "original":"加持其人。",
    "folio":1,
    "analyzed":"加 持 其 人  "
  },
  {
    "segmentnr":"ZH_T19_0996_001:0522b25_1",
    "original":"此菩薩尊貴菩提心。",
    "folio":1,
    "analyzed":"此 菩 薩 尊 貴 菩 提 心  "
  },
  {
    "segmentnr":"ZH_T19_0996_001:0522b25_9",
    "original":"佛從菩提心生故。",
    "folio":1,
    "analyzed":"佛 從 菩 提 心 生 故  "
  },
  {
    "segmentnr":"ZH_T19_0996_001:0522b25_14",
    "original":"歸命法寶。",
    "folio":1,
    "analyzed":"歸 命 法 寶  "
  },
  {
    "segmentnr":"ZH_T19_0996_001:0522b26_10",
    "original":"則得天帝釋并眷屬四天王天加護。",
    "folio":1,
    "analyzed":"則 得 天 帝 釋 并 眷 屬 四天王天 加 護  "
  },
  {
    "segmentnr":"ZH_T19_0996_001:0522b27_1",
    "original":"何以故帝釋在危難。",
    "folio":1,
    "analyzed":"何 以 故 帝 釋 在 危 難  "
  },
  {
    "segmentnr":"ZH_T19_0996_001:0522b27_10",
    "original":"般若加持現獲利益。",
    "folio":1,
    "analyzed":"般 若 加 持 現 獲 利 益  "
  },
  {
    "segmentnr":"ZH_T19_0996_001:0522b28_1",
    "original":"是故天帝釋尊貴法寶。",
    "folio":1,
    "analyzed":"是 故 天 帝 釋 尊 貴 法 寶  "
  },
  {
    "segmentnr":"ZH_T19_0996_001:0522b28_7",
    "original":"歸命僧寶者。",
    "folio":1,
    "analyzed":"歸 命 僧 寶 者  "
  },
  {
    "segmentnr":"ZH_T19_0996_001:0522b29_5",
    "original":"則得阿迦尼吒天王并五淨居天并眷屬。",
    "folio":1,
    "analyzed":"則 得 阿 迦 尼 吒 天 王 并 五淨居天 并 眷 屬  "
  },
  {
    "segmentnr":"ZH_T19_0996_001:0522b29_11",
    "original":"加護持經者。",
    "folio":1,
    "analyzed":"加 護 持 經 者  "
  },
  {
    "segmentnr":"ZH_T19_0996_001:0522b29_16",
    "original":"為五淨居。",
    "folio":1,
    "analyzed":"為 五 淨 居  "
  },
  {
    "segmentnr":"ZH_T19_0996_001:0522c01_5",
    "original":"菩薩僧并聲聞僧眾。",
    "folio":1,
    "analyzed":"菩 薩 僧 并 聲 聞 僧 眾  "
  },
  {
    "segmentnr":"ZH_T19_0996_001:0522c01_14",
    "original":"常居彼天現法樂住。",
    "folio":1,
    "analyzed":"常 居 彼 天 現法樂住  "
  },
  {
    "segmentnr":"ZH_T19_0996_001:0522c02_3",
    "original":"梵天等悉皆貴重。",
    "folio":1,
    "analyzed":"梵 天 等 悉 皆 貴 重  "
  },
  {
    "segmentnr":"ZH_T19_0996_001:0522c04_8",
    "original":"娜莫阿哩夜吠𡀔者娜野怛他孽多夜囉訶諦三藐三沒馱野。",
    "folio":1,
    "analyzed":"娜 莫 阿 哩 夜 吠 𡀔 者 娜 野 怛 他 孽 多 夜 囉 訶 諦 三藐三沒馱 野  "
  },
  {
    "segmentnr":"ZH_T19_0996_001:0522c04_15",
    "original":"娜莫者歸命義。",
    "folio":1,
    "analyzed":"娜 莫 者 歸 命 義  "
  },
  {
    "segmentnr":"ZH_T19_0996_001:0522c05_6",
    "original":"亦云稽首亦云頂禮。",
    "folio":1,
    "analyzed":"亦 云 稽 首 亦 云 頂 禮  "
  },
  {
    "segmentnr":"ZH_T19_0996_001:0522c05_13",
    "original":"阿哩夜遠惡義。",
    "folio":1,
    "analyzed":"阿 哩 夜 遠 惡 義  "
  },
  {
    "segmentnr":"ZH_T19_0996_001:0522c06_2",
    "original":"此方會釋云聖者。",
    "folio":1,
    "analyzed":"此 方 會 釋 云 聖 者  "
  },
  {
    "segmentnr":"ZH_T19_0996_001:0522c06_8",
    "original":"吠𡀔者娜野。",
    "folio":1,
    "analyzed":"吠 𡀔 者 娜 野  "
  },
  {
    "segmentnr":"ZH_T19_0996_001:0522c06_16",
    "original":"遍照義亦云大日。",
    "folio":1,
    "analyzed":"遍 照 義 亦 云 大 日  "
  },
  {
    "segmentnr":"ZH_T19_0996_001:0522c07_3",
    "original":"義如世間日。",
    "folio":1,
    "analyzed":"義 如 世 間 日  "
  },
  {
    "segmentnr":"ZH_T19_0996_001:0522c07_16",
    "original":"照一邊不照一邊照晝不照夜。",
    "folio":1,
    "analyzed":"照 一 邊 不 照 一 邊 照 晝 不 照 夜  "
  },
  {
    "segmentnr":"ZH_T19_0996_001:0522c08_7",
    "original":"照一世界不照餘世界。",
    "folio":1,
    "analyzed":"照 一 世 界 不 照 餘 世 界  "
  },
  {
    "segmentnr":"ZH_T19_0996_001:0522c08_17",
    "original":"但得名日不得名大日。",
    "folio":1,
    "analyzed":"但 得 名 日 不 得 名 大 日  "
  },
  {
    "segmentnr":"ZH_T19_0996_001:0522c09_6",
    "original":"毘盧遮那大日者。",
    "folio":1,
    "analyzed":"毘 盧 遮 那 大 日 者  "
  },
  {
    "segmentnr":"ZH_T19_0996_001:0522c09_11",
    "original":"色身法身。",
    "folio":1,
    "analyzed":"色 身 法 身  "
  },
  {
    "segmentnr":"ZH_T19_0996_001:0522c10_7",
    "original":"普周法界及虛空界無邊十方世界。",
    "folio":1,
    "analyzed":"普 周 法 界 及 虛 空 界 無 邊 十方世界  "
  },
  {
    "segmentnr":"ZH_T19_0996_001:0522c10_12",
    "original":"普皆照曜。",
    "folio":1,
    "analyzed":"普 皆 照 曜  "
  },
  {
    "segmentnr":"ZH_T19_0996_001:0522c11_2",
    "original":"若人知此佛功德利。",
    "folio":1,
    "analyzed":"若 人 知 此 佛 功 德 利  "
  },
  {
    "segmentnr":"ZH_T19_0996_001:0522c11_7",
    "original":"歸命禮拜。",
    "folio":1,
    "analyzed":"歸 命 禮 拜  "
  },
  {
    "segmentnr":"ZH_T19_0996_001:0522c12_15",
    "original":"則得盡虛空遍法界一切諸佛菩薩諸賢聖八部悉共加持護念也。",
    "folio":1,
    "analyzed":"則 得 盡 虛 空 遍 法 界 一切諸佛 菩 薩 諸 賢 聖 八 部 悉 共 加 持 護 念 也  "
  },
  {
    "segmentnr":"ZH_T19_0996_001:0522c13_14",
    "original":"怛他孽多夜囉訶諦三藐三沒馱野。",
    "folio":1,
    "analyzed":"怛 他 孽 多 夜 囉 訶 諦 三藐三沒馱 野  "
  },
  {
    "segmentnr":"ZH_T19_0996_001:0522c14_6",
    "original":"如來應供正遍知義。",
    "folio":1,
    "analyzed":"如 來 應 供 正 遍 知 義  "
  },
  {
    "segmentnr":"ZH_T19_0996_001:0522c14_10",
    "original":"先已釋。",
    "folio":1,
    "analyzed":"先 已 釋  "
  },
  {
    "segmentnr":"ZH_T19_0996_001:0522c15_5",
    "original":"娜莫阿哩野。",
    "folio":1,
    "analyzed":"娜 莫 阿 哩 野  "
  },
  {
    "segmentnr":"ZH_T19_0996_001:0522c15_8",
    "original":"已釋。",
    "folio":1,
    "analyzed":"已 釋  "
  },
  {
    "segmentnr":"ZH_T19_0996_001:0522c16_7",
    "original":"三滿多跋捺囉野。",
    "folio":1,
    "analyzed":"三 滿 多 跋 捺 囉 野  "
  },
  {
    "segmentnr":"ZH_T19_0996_001:0522c16_15",
    "original":"三滿多者是普義。",
    "folio":1,
    "analyzed":"三 滿 多 者 是 普 義  "
  },
  {
    "segmentnr":"ZH_T19_0996_001:0522c17_3",
    "original":"跋捺囉者賢義。",
    "folio":1,
    "analyzed":"跋 捺 囉 者 賢 義  "
  },
  {
    "segmentnr":"ZH_T19_0996_001:0522c18_1",
    "original":"野字者聲明中七例八轉聲中謂聲也。",
    "folio":1,
    "analyzed":"野 字 者 聲 明 中 七 例 八 轉 聲 中 謂 聲 也  "
  },
  {
    "segmentnr":"ZH_T19_0996_001:0522c18_4",
    "original":"下同。",
    "folio":1,
    "analyzed":"下 同  "
  },
  {
    "segmentnr":"ZH_T19_0996_001:0522c18_16",
    "original":"此菩薩說三密門普賢行願。",
    "folio":1,
    "analyzed":"此 菩 薩 說 三 密 門 普 賢 行 願  "
  },
  {
    "segmentnr":"ZH_T19_0996_001:0522c19_8",
    "original":"一切諸佛若不修三密門。",
    "folio":1,
    "analyzed":"一切諸佛 若 不 修 三 密 門  "
  },
  {
    "segmentnr":"ZH_T19_0996_001:0522c19_14",
    "original":"不行普賢行。",
    "folio":1,
    "analyzed":"不 行 普 賢 行  "
  },
  {
    "segmentnr":"ZH_T19_0996_001:0522c20_4",
    "original":"得成佛者無有是處。",
    "folio":1,
    "analyzed":"得 成 佛 者 無 有 是 處  "
  },
  {
    "segmentnr":"ZH_T19_0996_001:0522c21_1",
    "original":"既成佛已於三密門普賢行休息者。",
    "folio":1,
    "analyzed":"既 成 佛 已 於 三 密 門 普 賢 行 休 息 者  "
  },
  {
    "segmentnr":"ZH_T19_0996_001:0522c21_6",
    "original":"亦無是處。",
    "folio":1,
    "analyzed":"亦 無 是 處  "
  },
  {
    "segmentnr":"ZH_T19_0996_001:0522c22_6",
    "original":"冒地薩怛嚩野。",
    "folio":1,
    "analyzed":"冒 地 薩 怛 嚩 野  "
  },
  {
    "segmentnr":"ZH_T19_0996_001:0522c22_10",
    "original":"菩薩義。",
    "folio":1,
    "analyzed":"菩 薩 義  "
  },
  {
    "segmentnr":"ZH_T19_0996_001:0522c23_6",
    "original":"摩賀薩怛嚩野。",
    "folio":1,
    "analyzed":"摩 賀 薩 怛 嚩 野  "
  },
  {
    "segmentnr":"ZH_T19_0996_001:0522c23_11",
    "original":"大菩薩義。",
    "folio":1,
    "analyzed":"大 菩 薩 義  "
  },
  {
    "segmentnr":"ZH_T19_0996_001:0522c24_7",
    "original":"摩賀迦嚕抳迦野。",
    "folio":1,
    "analyzed":"摩 賀 迦 嚕 抳 迦 野  "
  },
  {
    "segmentnr":"ZH_T19_0996_001:0522c24_11",
    "original":"大悲者。",
    "folio":1,
    "analyzed":"大 悲 者  "
  },
  {
    "segmentnr":"ZH_T19_0996_001:0522c25_1",
    "original":"若歸命聖普賢菩薩。",
    "folio":1,
    "analyzed":"若 歸 命 聖 普 賢 菩 薩  "
  },
  {
    "segmentnr":"ZH_T19_0996_001:0522c25_13",
    "original":"則十方諸佛菩薩悉皆加護。",
    "folio":1,
    "analyzed":"則 十方諸佛 菩 薩 悉 皆 加 護  "
  },
  {
    "segmentnr":"ZH_T19_0996_001:0522c26_1",
    "original":"一切諸佛菩薩。",
    "folio":1,
    "analyzed":"一切諸佛 菩 薩  "
  },
  {
    "segmentnr":"ZH_T19_0996_001:0522c26_12",
    "original":"皆因修三密門行普賢行。",
    "folio":1,
    "analyzed":"皆 因 修 三 密 門 行 普 賢 行  "
  },
  {
    "segmentnr":"ZH_T19_0996_001:0522c26_17",
    "original":"得證聖果。",
    "folio":1,
    "analyzed":"得 證 聖 果  "
  },
  {
    "segmentnr":"ZH_T19_0996_001:0522c27_3",
    "original":"是故尊貴。",
    "folio":1,
    "analyzed":"是 故 尊 貴  "
  },
  {
    "segmentnr":"ZH_T19_0996_001:0522c28_6",
    "original":"怛儞也二合他。",
    "folio":1,
    "analyzed":"怛 儞 也 二 合 他  "
  },
  {
    "segmentnr":"ZH_T19_0996_001:0522c28_13",
    "original":"古云即說所謂。",
    "folio":1,
    "analyzed":"古 云 即 說 所 謂  "
  },
  {
    "segmentnr":"ZH_T19_0996_001:0522c29_11",
    "original":"已上文歸命三寶毘盧遮那佛普賢菩薩。",
    "folio":1,
    "analyzed":"已 上 文 歸 命 三 寶 毘 盧 遮 那 佛 普 賢 菩 薩  "
  },
  {
    "segmentnr":"ZH_T19_0996_001:0523a01_7",
    "original":"枳穰娜鉢囉儞閉。",
    "folio":1,
    "analyzed":"枳 穰 娜 鉢 囉 儞 閉  "
  },
  {
    "segmentnr":"ZH_T19_0996_001:0523a01_14",
    "original":"顯句釋智燈義。",
    "folio":1,
    "analyzed":"顯 句 釋 智 燈 義  "
  },
  {
    "segmentnr":"ZH_T19_0996_001:0523a02_8",
    "original":"密句釋智無所得以為方便。",
    "folio":1,
    "analyzed":"密 句 釋 智 無 所 得 以 為 方 便  "
  },
  {
    "segmentnr":"ZH_T19_0996_001:0523a03_4",
    "original":"無智無得即成般若波羅蜜智燈。",
    "folio":1,
    "analyzed":"無 智 無 得 即 成 般 若 波 羅 蜜 智 燈  "
  },
  {
    "segmentnr":"ZH_T19_0996_001:0523a03_11",
    "original":"能照一切佛法。",
    "folio":1,
    "analyzed":"能 照 一切佛法  "
  },
  {
    "segmentnr":"ZH_T19_0996_001:0523a04_10",
    "original":"惡字此惡字梵本是婀字。",
    "folio":1,
    "analyzed":"惡 字 此 惡 字 梵 本 是 婀 字  "
  },
  {
    "segmentnr":"ZH_T19_0996_001:0523a04_16",
    "original":"為隨文句便。",
    "folio":1,
    "analyzed":"為 隨 文 句 便  "
  },
  {
    "segmentnr":"ZH_T19_0996_001:0523a05_1",
    "original":"作惡呼。",
    "folio":1,
    "analyzed":"作 惡 呼  "
  },
  {
    "segmentnr":"ZH_T19_0996_001:0523a06_7",
    "original":"乞叉二合野句勢。",
    "folio":1,
    "analyzed":"乞 叉 二 合 野 句 勢  "
  },
  {
    "segmentnr":"ZH_T19_0996_001:0523a06_14",
    "original":"顯釋無盡藏義。",
    "folio":1,
    "analyzed":"顯 釋 無 盡 藏 義  "
  },
  {
    "segmentnr":"ZH_T19_0996_001:0523a07_5",
    "original":"密句釋婀字一字為種子。",
    "folio":1,
    "analyzed":"密 句 釋 婀 字 一 字 為 種 子  "
  },
  {
    "segmentnr":"ZH_T19_0996_001:0523a07_16",
    "original":"婀字者一切法本不生故。",
    "folio":1,
    "analyzed":"婀 字 者 一 切 法 本 不 生 故  "
  },
  {
    "segmentnr":"ZH_T19_0996_001:0523a08_6",
    "original":"婀字是一切字之母。",
    "folio":1,
    "analyzed":"婀 字 是 一 切 字 之 母  "
  },
  {
    "segmentnr":"ZH_T19_0996_001:0523a08_12",
    "original":"能生一切法。",
    "folio":1,
    "analyzed":"能 生 一 切 法  "
  },
  {
    "segmentnr":"ZH_T19_0996_001:0523a09_1",
    "original":"若能曉婀字門。",
    "folio":1,
    "analyzed":"若 能 曉 婀 字 門  "
  },
  {
    "segmentnr":"ZH_T19_0996_001:0523a09_6",
    "original":"瑜伽相應。",
    "folio":1,
    "analyzed":"瑜 伽 相 應  "
  },
  {
    "segmentnr":"ZH_T19_0996_001:0523a09_14",
    "original":"則得佛法無盡藏。",
    "folio":1,
    "analyzed":"則 得 佛 法 無 盡 藏  "
  },
  {
    "segmentnr":"ZH_T19_0996_001:0523a10_3",
    "original":"則悟一切法本不生。",
    "folio":1,
    "analyzed":"則 悟 一 切 法 本 不 生  "
  },
  {
    "segmentnr":"ZH_T19_0996_001:0523a10_14",
    "original":"猶如虛空一相清淨平等。",
    "folio":1,
    "analyzed":"猶如虛空 一 相 清 淨 平 等  "
  },
  {
    "segmentnr":"ZH_T19_0996_001:0523a11_3",
    "original":"即成無分別智也。",
    "folio":1,
    "analyzed":"即 成 無分別智 也  "
  },
  {
    "segmentnr":"ZH_T19_0996_001:0523a12_9",
    "original":"鉢囉二合底婆娜嚩底。",
    "folio":1,
    "analyzed":"鉢 囉 二 合 底 婆 娜 嚩 底  "
  },
  {
    "segmentnr":"ZH_T19_0996_001:0523a12_16",
    "original":"顯句釋具辯才。",
    "folio":1,
    "analyzed":"顯 句 釋 具 辯 才  "
  },
  {
    "segmentnr":"ZH_T19_0996_001:0523a13_4",
    "original":"密句釋於此句中。",
    "folio":1,
    "analyzed":"密 句 釋 於 此 句 中  "
  },
  {
    "segmentnr":"ZH_T19_0996_001:0523a13_12",
    "original":"取鉢囉二合一字。",
    "folio":1,
    "analyzed":"取 鉢 囉 二 合 一 字  "
  },
  {
    "segmentnr":"ZH_T19_0996_001:0523a13_16",
    "original":"為種子。",
    "folio":1,
    "analyzed":"為 種 子  "
  },
  {
    "segmentnr":"ZH_T19_0996_001:0523a14_10",
    "original":"鉢囉字者般若波羅蜜無所得故。",
    "folio":1,
    "analyzed":"鉢 囉 字 者 般 若 波 羅 蜜 無 所 得 故  "
  },
  {
    "segmentnr":"ZH_T19_0996_001:0523a14_18",
    "original":"以無所得為方便。",
    "folio":1,
    "analyzed":"以 無 所 得 為 方 便  "
  },
  {
    "segmentnr":"ZH_T19_0996_001:0523a16_7",
    "original":"於後得智中悟一切法因緣生諸法故由證一切法本不生故。",
    "folio":1,
    "analyzed":"於 後 得 智 中 悟 一 切 法 因 緣 生 諸 法 故 由 證 一 切 法 本 不 生 故  "
  },
  {
    "segmentnr":"ZH_T19_0996_001:0523a16_15",
    "original":"獲得無盡佛法藏。",
    "folio":1,
    "analyzed":"獲 得 無 盡 佛 法 藏  "
  },
  {
    "segmentnr":"ZH_T19_0996_001:0523a17_7",
    "original":"於後得智中得四無礙解。",
    "folio":1,
    "analyzed":"於 後 得 智 中 得 四無礙解  "
  },
  {
    "segmentnr":"ZH_T19_0996_001:0523a17_12",
    "original":"說法自在。",
    "folio":1,
    "analyzed":"說 法 自 在  "
  },
  {
    "segmentnr":"ZH_T19_0996_001:0523a18_8",
    "original":"薩嚩沒馱嚩𡀔枳諦。",
    "folio":1,
    "analyzed":"薩 嚩 沒 馱 嚩 𡀔 枳 諦  "
  },
  {
    "segmentnr":"ZH_T19_0996_001:0523a19_1",
    "original":"顯句釋一切佛所觀察義。",
    "folio":1,
    "analyzed":"顯 句 釋 一 切 佛 所 觀 察 義  "
  },
  {
    "segmentnr":"ZH_T19_0996_001:0523a19_12",
    "original":"密句釋薩字一字為種子。",
    "folio":1,
    "analyzed":"密 句 釋 薩 字 一 字 為 種 子  "
  },
  {
    "segmentnr":"ZH_T19_0996_001:0523a20_3",
    "original":"薩字者一切法平等義。",
    "folio":1,
    "analyzed":"薩 字 者 一 切 法 平 等 義  "
  },
  {
    "segmentnr":"ZH_T19_0996_001:0523a20_12",
    "original":"能緣所緣平等平等。",
    "folio":1,
    "analyzed":"能 緣 所 緣 平等平等  "
  },
  {
    "segmentnr":"ZH_T19_0996_001:0523a21_2",
    "original":"能取所取無所得故。",
    "folio":1,
    "analyzed":"能取所取 無 所 得 故  "
  },
  {
    "segmentnr":"ZH_T19_0996_001:0523a21_7",
    "original":"則證真如。",
    "folio":1,
    "analyzed":"則 證 真 如  "
  },
  {
    "segmentnr":"ZH_T19_0996_001:0523a22_1",
    "original":"當於法流無邊諸佛觀察護念。",
    "folio":1,
    "analyzed":"當 於 法 流 無 邊 諸 佛 觀 察 護 念  "
  },
  {
    "segmentnr":"ZH_T19_0996_001:0523a23_10",
    "original":"喻誐跛哩儞澁跛二合寧。",
    "folio":1,
    "analyzed":"喻 誐 跛 哩 儞 澁 跛 二 合 寧  "
  },
  {
    "segmentnr":"ZH_T19_0996_001:0523a24_1",
    "original":"顯句釋瑜伽圓成義。",
    "folio":1,
    "analyzed":"顯 句 釋 瑜 伽 圓 成 義  "
  },
  {
    "segmentnr":"ZH_T19_0996_001:0523a24_12",
    "original":"密句釋喻字一字為種子。",
    "folio":1,
    "analyzed":"密 句 釋 喻 字 一 字 為 種 子  "
  },
  {
    "segmentnr":"ZH_T19_0996_001:0523a25_3",
    "original":"喻字者一切乘無所得。",
    "folio":1,
    "analyzed":"喻 字 者 一 切 乘 無 所 得  "
  },
  {
    "segmentnr":"ZH_T19_0996_001:0523a25_11",
    "original":"若瑜伽觀智相應。",
    "folio":1,
    "analyzed":"若 瑜 伽 觀 智 相 應  "
  },
  {
    "segmentnr":"ZH_T19_0996_001:0523a25_16",
    "original":"證得圓成。",
    "folio":1,
    "analyzed":"證 得 圓 成  "
  },
  {
    "segmentnr":"ZH_T19_0996_001:0523a26_5",
    "original":"於諸乘中教理行果。",
    "folio":1,
    "analyzed":"於 諸 乘 中 教 理 行 果  "
  },
  {
    "segmentnr":"ZH_T19_0996_001:0523a26_15",
    "original":"悉皆證得一真如法性。",
    "folio":1,
    "analyzed":"悉 皆 證 得 一 真 如 法 性  "
  },
  {
    "segmentnr":"ZH_T19_0996_001:0523a27_10",
    "original":"儼避引囉弩囉嚩誐引係。",
    "folio":1,
    "analyzed":"儼 避 引 囉 弩 囉 嚩 誐 引 係  "
  },
  {
    "segmentnr":"ZH_T19_0996_001:0523a27_19",
    "original":"顯句釋甚深難測義。",
    "folio":1,
    "analyzed":"顯 句 釋 甚 深 難 測 義  "
  },
  {
    "segmentnr":"ZH_T19_0996_001:0523a28_10",
    "original":"密句釋儼字一字為種子。",
    "folio":1,
    "analyzed":"密 句 釋 儼 字 一 字 為 種 子  "
  },
  {
    "segmentnr":"ZH_T19_0996_001:0523a29_10",
    "original":"儼字者一切真如法無去無來猶證真如海。",
    "folio":1,
    "analyzed":"儼 字 者 一 切 真 如 法 無 去 無 來 猶 證 真 如 海  "
  },
  {
    "segmentnr":"ZH_T19_0996_001:0523b01_2",
    "original":"實相般若不可以言詮。",
    "folio":1,
    "analyzed":"實 相 般 若 不 可 以 言 詮  "
  },
  {
    "segmentnr":"ZH_T19_0996_001:0523b01_12",
    "original":"唯佛境界自覺聖智證。",
    "folio":1,
    "analyzed":"唯 佛 境 界 自覺聖智 證  "
  },
  {
    "segmentnr":"ZH_T19_0996_001:0523b02_13",
    "original":"底哩野二合特嚩跛哩儞澁跛寧。",
    "folio":1,
    "analyzed":"底 哩 野 二 合 特 嚩 跛 哩 儞 澁 跛 寧  "
  },
  {
    "segmentnr":"ZH_T19_0996_001:0523b03_6",
    "original":"顯句釋三世圓滿成就義。",
    "folio":1,
    "analyzed":"顯 句 釋 三 世 圓 滿 成 就 義  "
  },
  {
    "segmentnr":"ZH_T19_0996_001:0523b04_5",
    "original":"密句釋底哩野三合梵字是一字也以此一字為種子。",
    "folio":1,
    "analyzed":"密 句 釋 底 哩 野 三 合 梵 字 是 一 字 也 以 此 一 字 為 種 子  "
  },
  {
    "segmentnr":"ZH_T19_0996_001:0523b05_3",
    "original":"底哩野者一切法真如平等自性成就。",
    "folio":1,
    "analyzed":"底 哩 野 者 一 切 法 真 如 平 等 自 性 成 就  "
  },
  {
    "segmentnr":"ZH_T19_0996_001:0523b05_9",
    "original":"越恒河沙數。",
    "folio":1,
    "analyzed":"越 恒 河 沙 數  "
  },
  {
    "segmentnr":"ZH_T19_0996_001:0523b05_15",
    "original":"功德真如中。",
    "folio":1,
    "analyzed":"功 德 真 如 中  "
  },
  {
    "segmentnr":"ZH_T19_0996_001:0523b07_2",
    "original":"無過去未來現在妄分別不相應行蘊堅執惑亂有為之法。",
    "folio":1,
    "analyzed":"無 過去未來現在 妄 分 別 不相應行 蘊 堅 執 惑 亂 有 為 之 法  "
  },
  {
    "segmentnr":"ZH_T19_0996_001:0523b08_8",
    "original":"冒地質多散惹娜儞。",
    "folio":1,
    "analyzed":"冒地質多 散 惹 娜 儞  "
  },
  {
    "segmentnr":"ZH_T19_0996_001:0523b08_18",
    "original":"顯句釋能生菩提心義。",
    "folio":1,
    "analyzed":"顯 句 釋 能 生 菩 提 心 義  "
  },
  {
    "segmentnr":"ZH_T19_0996_001:0523b09_10",
    "original":"密句釋冒字一字為種子。",
    "folio":1,
    "analyzed":"密 句 釋 冒 字 一 字 為 種 子  "
  },
  {
    "segmentnr":"ZH_T19_0996_001:0523b10_2",
    "original":"冒字者一切法無縛義。",
    "folio":1,
    "analyzed":"冒 字 者 一 切 法 無 縛 義  "
  },
  {
    "segmentnr":"ZH_T19_0996_001:0523b10_11",
    "original":"若知自身中菩提心。",
    "folio":1,
    "analyzed":"若 知 自 身 中 菩 提 心  "
  },
  {
    "segmentnr":"ZH_T19_0996_001:0523b11_1",
    "original":"自性成就三世平等。",
    "folio":1,
    "analyzed":"自 性 成 就 三世平等  "
  },
  {
    "segmentnr":"ZH_T19_0996_001:0523b11_10",
    "original":"猶若虛空離諸萬像。",
    "folio":1,
    "analyzed":"猶 若 虛 空 離 諸 萬 像  "
  },
  {
    "segmentnr":"ZH_T19_0996_001:0523b12_3",
    "original":"則知一切有情心及諸佛心。",
    "folio":1,
    "analyzed":"則 知 一切有情 心 及 諸 佛 心  "
  },
  {
    "segmentnr":"ZH_T19_0996_001:0523b12_9",
    "original":"如自心清淨。",
    "folio":1,
    "analyzed":"如 自 心 清 淨  "
  },
  {
    "segmentnr":"ZH_T19_0996_001:0523b12_18",
    "original":"則生大悲深生矜愍。",
    "folio":1,
    "analyzed":"則 生 大 悲 深 生 矜 愍  "
  },
  {
    "segmentnr":"ZH_T19_0996_001:0523b13_6",
    "original":"則起種種方便。",
    "folio":1,
    "analyzed":"則 起 種 種 方 便  "
  },
  {
    "segmentnr":"ZH_T19_0996_001:0523b13_16",
    "original":"令一切有情至於究竟。",
    "folio":1,
    "analyzed":"令 一切有情 至 於 究 竟  "
  },
  {
    "segmentnr":"ZH_T19_0996_001:0523b14_6",
    "original":"離苦解脫無解無縛。",
    "folio":1,
    "analyzed":"離 苦 解 脫 無 解 無 縛  "
  },
  {
    "segmentnr":"ZH_T19_0996_001:0523b15_9",
    "original":"薩嚩毘曬迦毘色訖諦。",
    "folio":1,
    "analyzed":"薩 嚩 毘 曬 迦 毘 色 訖 諦  "
  },
  {
    "segmentnr":"ZH_T19_0996_001:0523b16_2",
    "original":"顯句釋一切灌灑得頂義。",
    "folio":1,
    "analyzed":"顯 句 釋 一 切 灌 灑 得 頂 義  "
  },
  {
    "segmentnr":"ZH_T19_0996_001:0523b16_13",
    "original":"密句釋薩字一字為種子。",
    "folio":1,
    "analyzed":"密 句 釋 薩 字 一 字 為 種 子  "
  },
  {
    "segmentnr":"ZH_T19_0996_001:0523b17_6",
    "original":"薩字者一切法無染無著義。",
    "folio":1,
    "analyzed":"薩 字 者 一 切 法 無 染 無 著 義  "
  },
  {
    "segmentnr":"ZH_T19_0996_001:0523b18_2",
    "original":"由觀察自他及諸佛心同一真如。",
    "folio":1,
    "analyzed":"由 觀 察 自 他 及 諸 佛 心 同 一 真 如  "
  },
  {
    "segmentnr":"ZH_T19_0996_001:0523b18_7",
    "original":"同體大悲。",
    "folio":1,
    "analyzed":"同 體 大 悲  "
  },
  {
    "segmentnr":"ZH_T19_0996_001:0523b18_14",
    "original":"是故不染不著。",
    "folio":1,
    "analyzed":"是 故 不 染 不 著  "
  },
  {
    "segmentnr":"ZH_T19_0996_001:0523b19_7",
    "original":"則於空中一切如來法水灌頂。",
    "folio":1,
    "analyzed":"則 於 空 中 一 切 如 來 法 水 灌 頂  "
  },
  {
    "segmentnr":"ZH_T19_0996_001:0523b19_14",
    "original":"則獲三業加持。",
    "folio":1,
    "analyzed":"則 獲 三 業 加 持  "
  },
  {
    "segmentnr":"ZH_T19_0996_001:0523b20_3",
    "original":"於無量修多羅藏。",
    "folio":1,
    "analyzed":"於 無 量 修 多 羅 藏  "
  },
  {
    "segmentnr":"ZH_T19_0996_001:0523b20_8",
    "original":"說法自在。",
    "folio":1,
    "analyzed":"說 法 自 在  "
  },
  {
    "segmentnr":"ZH_T19_0996_001:0523b21_8",
    "original":"達摩娑誐囉三步諦。",
    "folio":1,
    "analyzed":"達 摩 娑 誐 囉 三 步 諦  "
  },
  {
    "segmentnr":"ZH_T19_0996_001:0523b21_17",
    "original":"顯句釋法海出生義。",
    "folio":1,
    "analyzed":"顯 句 釋 法 海 出 生 義  "
  },
  {
    "segmentnr":"ZH_T19_0996_001:0523b22_10",
    "original":"密句釋達字一字為種子。",
    "folio":1,
    "analyzed":"密 句 釋 達 字 一 字 為 種 子  "
  },
  {
    "segmentnr":"ZH_T19_0996_001:0523b23_4",
    "original":"達字者一切法界無所得義。",
    "folio":1,
    "analyzed":"達 字 者 一 切 法 界 無 所 得 義  "
  },
  {
    "segmentnr":"ZH_T19_0996_001:0523b23_11",
    "original":"由住無所得心。",
    "folio":1,
    "analyzed":"由 住 無 所 得 心  "
  },
  {
    "segmentnr":"ZH_T19_0996_001:0523b24_2",
    "original":"阿賴耶識中俱生我執。",
    "folio":1,
    "analyzed":"阿賴耶識 中 俱 生 我 執  "
  },
  {
    "segmentnr":"ZH_T19_0996_001:0523b24_9",
    "original":"俱生法執種子。",
    "folio":1,
    "analyzed":"俱 生 法 執 種 子  "
  },
  {
    "segmentnr":"ZH_T19_0996_001:0523b24_19",
    "original":"以文殊大聖金剛利劍。",
    "folio":1,
    "analyzed":"以 文 殊 大 聖 金 剛 利 劍  "
  },
  {
    "segmentnr":"ZH_T19_0996_001:0523b25_6",
    "original":"永截斷無餘義。",
    "folio":1,
    "analyzed":"永 截 斷 無 餘 義  "
  },
  {
    "segmentnr":"ZH_T19_0996_001:0523b25_18",
    "original":"則流出清淨法界等流教法。",
    "folio":1,
    "analyzed":"則 流 出 清 淨 法 界 等 流 教 法  "
  },
  {
    "segmentnr":"ZH_T19_0996_001:0523b26_7",
    "original":"則成法海出生義。",
    "folio":1,
    "analyzed":"則 成 法 海 出 生 義  "
  },
  {
    "segmentnr":"ZH_T19_0996_001:0523b27_1",
    "original":"達字者文殊師利菩薩種子。",
    "folio":1,
    "analyzed":"達 字 者 文 殊 師 利 菩 薩 種 子  "
  },
  {
    "segmentnr":"ZH_T19_0996_001:0523b28_7",
    "original":"阿暮伽室囉嚩儜。",
    "folio":1,
    "analyzed":"阿 暮 伽 室 囉 嚩 儜  "
  },
  {
    "segmentnr":"ZH_T19_0996_001:0523b28_14",
    "original":"顯句釋阿暮伽。",
    "folio":1,
    "analyzed":"顯 句 釋 阿 暮 伽  "
  },
  {
    "segmentnr":"ZH_T19_0996_001:0523b29_2",
    "original":"古釋不空義。",
    "folio":1,
    "analyzed":"古 釋 不 空 義  "
  },
  {
    "segmentnr":"ZH_T19_0996_001:0523b29_9",
    "original":"今依聲明論釋。",
    "folio":1,
    "analyzed":"今 依 聲 明 論 釋  "
  },
  {
    "segmentnr":"ZH_T19_0996_001:0523b29_13",
    "original":"無間義。",
    "folio":1,
    "analyzed":"無 間 義  "
  },
  {
    "segmentnr":"ZH_T19_0996_001:0523c01_2",
    "original":"阿字一字為種子。",
    "folio":1,
    "analyzed":"阿 字 一 字 為 種 子  "
  },
  {
    "segmentnr":"ZH_T19_0996_001:0523c01_17",
    "original":"阿字者一切法本來寂靜本來涅槃。",
    "folio":1,
    "analyzed":"阿 字 者 一 切 法 本來寂靜 本 來 涅 槃  "
  },
  {
    "segmentnr":"ZH_T19_0996_001:0523c02_6",
    "original":"由證此解脫法印。",
    "folio":1,
    "analyzed":"由 證 此 解 脫 法 印  "
  },
  {
    "segmentnr":"ZH_T19_0996_001:0523c03_1",
    "original":"遍周法界及諸佛剎大集會中。",
    "folio":1,
    "analyzed":"遍 周 法 界 及 諸 佛 剎 大 集 會 中  "
  },
  {
    "segmentnr":"ZH_T19_0996_001:0523c03_9",
    "original":"於佛前所聞教法。",
    "folio":1,
    "analyzed":"於 佛 前 所 聞 教 法  "
  },
  {
    "segmentnr":"ZH_T19_0996_001:0523c04_14",
    "original":"悉皆住持永不忘失摩訶三滿多跋捺囉步彌涅哩野諦。",
    "folio":1,
    "analyzed":"悉 皆 住 持 永 不 忘 失 摩 訶 三 滿 多 跋 捺 囉 步 彌 涅 哩 野 諦  "
  },
  {
    "segmentnr":"ZH_T19_0996_001:0523c05_7",
    "original":"顯句釋出大普賢地義。",
    "folio":1,
    "analyzed":"顯 句 釋 出 大 普 賢 地 義  "
  },
  {
    "segmentnr":"ZH_T19_0996_001:0523c05_18",
    "original":"密句釋摩字一字為種子。",
    "folio":1,
    "analyzed":"密 句 釋 摩 字 一 字 為 種 子  "
  },
  {
    "segmentnr":"ZH_T19_0996_001:0523c06_9",
    "original":"摩字者一切法無我義。",
    "folio":1,
    "analyzed":"摩 字 者 一切法無我 義  "
  },
  {
    "segmentnr":"ZH_T19_0996_001:0523c06_15",
    "original":"無我有二種。",
    "folio":1,
    "analyzed":"無 我 有 二 種  "
  },
  {
    "segmentnr":"ZH_T19_0996_001:0523c07_3",
    "original":"人無我法無我。",
    "folio":1,
    "analyzed":"人 無 我 法 無 我  "
  },
  {
    "segmentnr":"ZH_T19_0996_001:0523c07_12",
    "original":"瑜伽者若證二無我。",
    "folio":1,
    "analyzed":"瑜 伽 者 若 證 二 無 我  "
  },
  {
    "segmentnr":"ZH_T19_0996_001:0523c07_19",
    "original":"則出大普賢地。",
    "folio":1,
    "analyzed":"則 出 大 普 賢 地  "
  },
  {
    "segmentnr":"ZH_T19_0996_001:0523c08_15",
    "original":"證毘盧遮那百福莊嚴圓滿清淨法身。",
    "folio":1,
    "analyzed":"證 毘 盧 遮 那 百 福 莊 嚴 圓 滿 清 淨 法 身  "
  },
  {
    "segmentnr":"ZH_T19_0996_001:0523c09_13",
    "original":"尾野二合羯囉拏跛哩鉢囉跛儞。",
    "folio":1,
    "analyzed":"尾 野 二 合 羯 囉 拏 跛 哩 鉢 囉 跛 儞  "
  },
  {
    "segmentnr":"ZH_T19_0996_001:0523c10_3",
    "original":"顯句釋獲得記別義。",
    "folio":1,
    "analyzed":"顯 句 釋 獲 得 記 別 義  "
  },
  {
    "segmentnr":"ZH_T19_0996_001:0523c10_9",
    "original":"古文授記義。",
    "folio":1,
    "analyzed":"古 文 授 記 義  "
  },
  {
    "segmentnr":"ZH_T19_0996_001:0523c11_3",
    "original":"密句釋尾野二合一字為種子。",
    "folio":1,
    "analyzed":"密 句 釋 尾 野 二 合 一 字 為 種 子  "
  },
  {
    "segmentnr":"ZH_T19_0996_001:0523c12_12",
    "original":"尾野字者一切法遍滿不可得義即知一切法自性寂靜自性涅槃。",
    "folio":1,
    "analyzed":"尾 野 字 者 一 切 法 遍 滿 不 可 得 義 即 知一切法 自 性 寂 靜 自性涅槃  "
  },
  {
    "segmentnr":"ZH_T19_0996_001:0523c13_3",
    "original":"能證所證皆同一性。",
    "folio":1,
    "analyzed":"能 證 所 證 皆 同 一 性  "
  },
  {
    "segmentnr":"ZH_T19_0996_001:0523c13_12",
    "original":"不增不減圓證法界。",
    "folio":1,
    "analyzed":"不增不減 圓 證 法 界  "
  },
  {
    "segmentnr":"ZH_T19_0996_001:0523c14_12",
    "original":"薩嚩悉馱娜麼塞訖哩三合諦。",
    "folio":1,
    "analyzed":"薩 嚩 悉 馱 娜 麼 塞 訖 哩 三 合 諦  "
  },
  {
    "segmentnr":"ZH_T19_0996_001:0523c15_7",
    "original":"顯句釋一切成就者禮敬義。",
    "folio":1,
    "analyzed":"顯 句 釋 一切成就 者 禮 敬 義  "
  },
  {
    "segmentnr":"ZH_T19_0996_001:0523c15_16",
    "original":"成就者菩薩之異名。",
    "folio":1,
    "analyzed":"成 就 者 菩 薩 之 異 名  "
  },
  {
    "segmentnr":"ZH_T19_0996_001:0523c16_8",
    "original":"密句釋薩字一字為種子。",
    "folio":1,
    "analyzed":"密 句 釋 薩 字 一 字 為 種 子  "
  },
  {
    "segmentnr":"ZH_T19_0996_001:0523c17_1",
    "original":"薩字者一切法無堅固義。",
    "folio":1,
    "analyzed":"薩 字 者 一 切 法 無 堅 固 義  "
  },
  {
    "segmentnr":"ZH_T19_0996_001:0523c17_10",
    "original":"念念四相遷流滅壞。",
    "folio":1,
    "analyzed":"念 念 四 相 遷 流 滅 壞  "
  },
  {
    "segmentnr":"ZH_T19_0996_001:0523c17_17",
    "original":"薩字中有婀字。",
    "folio":1,
    "analyzed":"薩 字 中 有 婀 字  "
  },
  {
    "segmentnr":"ZH_T19_0996_001:0523c18_3",
    "original":"若證婀字門。",
    "folio":1,
    "analyzed":"若 證 婀 字 門  "
  },
  {
    "segmentnr":"ZH_T19_0996_001:0523c18_15",
    "original":"本來不生不滅亦常恒堅固。",
    "folio":1,
    "analyzed":"本 來 不生不滅 亦 常 恒 堅 固  "
  },
  {
    "segmentnr":"ZH_T19_0996_001:0523c19_5",
    "original":"喻若金剛心得自在。",
    "folio":1,
    "analyzed":"喻 若 金 剛 心得自在  "
  },
  {
    "segmentnr":"ZH_T19_0996_001:0523c19_11",
    "original":"能現種種身。",
    "folio":1,
    "analyzed":"能 現種種身  "
  },
  {
    "segmentnr":"ZH_T19_0996_001:0523c20_13",
    "original":"薩嚩冒地薩怛嚩二合散惹娜儞。",
    "folio":1,
    "analyzed":"薩 嚩 冒 地 薩 怛 嚩 二 合 散 惹 娜 儞  "
  },
  {
    "segmentnr":"ZH_T19_0996_001:0523c21_6",
    "original":"顯句釋出生一切菩薩義。",
    "folio":1,
    "analyzed":"顯 句 釋 出 生 一切菩薩 義  "
  },
  {
    "segmentnr":"ZH_T19_0996_001:0523c21_17",
    "original":"密句釋薩字一字為種子。",
    "folio":1,
    "analyzed":"密 句 釋 薩 字 一 字 為 種 子  "
  },
  {
    "segmentnr":"ZH_T19_0996_001:0523c22_8",
    "original":"薩字者一切法無等義。",
    "folio":1,
    "analyzed":"薩 字 者 一 切 法 無 等 義  "
  },
  {
    "segmentnr":"ZH_T19_0996_001:0523c22_13",
    "original":"由觀此字。",
    "folio":1,
    "analyzed":"由 觀 此 字  "
  },
  {
    "segmentnr":"ZH_T19_0996_001:0523c23_3",
    "original":"心與般若平等平等。",
    "folio":1,
    "analyzed":"心 與 般 若 平等平等  "
  },
  {
    "segmentnr":"ZH_T19_0996_001:0523c23_14",
    "original":"前剎那後剎那一相清淨。",
    "folio":1,
    "analyzed":"前 剎 那 後 剎 那 一 相 清 淨  "
  },
  {
    "segmentnr":"ZH_T19_0996_001:0523c24_6",
    "original":"能生一切波羅蜜一切地。",
    "folio":1,
    "analyzed":"能 生 一 切 波 羅 蜜 一 切 地  "
  },
  {
    "segmentnr":"ZH_T19_0996_001:0523c24_13",
    "original":"即名般若佛母。",
    "folio":1,
    "analyzed":"即 名 般 若 佛 母  "
  },
  {
    "segmentnr":"ZH_T19_0996_001:0523c25_8",
    "original":"婆誐嚩底沒馱麼諦。",
    "folio":1,
    "analyzed":"婆 誐 嚩 底 沒 馱 麼 諦  "
  },
  {
    "segmentnr":"ZH_T19_0996_001:0523c25_16",
    "original":"顯句釋世尊佛母。",
    "folio":1,
    "analyzed":"顯 句 釋 世 尊 佛 母  "
  },
  {
    "segmentnr":"ZH_T19_0996_001:0523c26_4",
    "original":"婆伽梵男聲。",
    "folio":1,
    "analyzed":"婆 伽 梵 男 聲  "
  },
  {
    "segmentnr":"ZH_T19_0996_001:0523c26_11",
    "original":"婆伽嚩底女聲。",
    "folio":1,
    "analyzed":"婆 伽 嚩 底 女 聲  "
  },
  {
    "segmentnr":"ZH_T19_0996_001:0523c27_2",
    "original":"二俱會意釋名世尊義。",
    "folio":1,
    "analyzed":"二 俱 會 意 釋 名 世 尊 義  "
  },
  {
    "segmentnr":"ZH_T19_0996_001:0523c27_12",
    "original":"依聲明對敵釋不如是。",
    "folio":1,
    "analyzed":"依 聲 明 對 敵 釋 不 如 是  "
  },
  {
    "segmentnr":"ZH_T19_0996_001:0523c27_18",
    "original":"婆伽者破義。",
    "folio":1,
    "analyzed":"婆 伽 者 破 義  "
  },
  {
    "segmentnr":"ZH_T19_0996_001:0523c28_2",
    "original":"梵能義。",
    "folio":1,
    "analyzed":"梵 能 義  "
  },
  {
    "segmentnr":"ZH_T19_0996_001:0523c28_11",
    "original":"能破四魔名婆伽梵。",
    "folio":1,
    "analyzed":"能 破 四 魔 名 婆 伽 梵  "
  },
  {
    "segmentnr":"ZH_T19_0996_001:0523c28_18",
    "original":"又一釋薄阿梵。",
    "folio":1,
    "analyzed":"又 一 釋 薄 阿 梵  "
  },
  {
    "segmentnr":"ZH_T19_0996_001:0523c29_9",
    "original":"依聲論分字釋薄名為破。",
    "folio":1,
    "analyzed":"依 聲 論 分 字 釋 薄 名 為 破  "
  },
  {
    "segmentnr":"ZH_T19_0996_001:0523c29_14",
    "original":"阿梵具知。",
    "folio":1,
    "analyzed":"阿 梵 具 知  "
  },
  {
    "segmentnr":"ZH_T19_0996_001:0524a01_1",
    "original":"阿字云不有。",
    "folio":1,
    "analyzed":"阿 字 云 不 有  "
  },
  {
    "segmentnr":"ZH_T19_0996_001:0524a01_6",
    "original":"亦云不無。",
    "folio":1,
    "analyzed":"亦 云 不 無  "
  },
  {
    "segmentnr":"ZH_T19_0996_001:0524a02_14",
    "original":"佛由悟一切法不生不滅不來不去不一不異不常不斷不增不減。",
    "folio":1,
    "analyzed":"佛 由 悟 一 切 法 不生不滅 不來不去 不 一 不 異 不 常 不 斷 不增不減  "
  },
  {
    "segmentnr":"ZH_T19_0996_001:0524a03_4",
    "original":"佛有如是功德故。",
    "folio":1,
    "analyzed":"佛 有 如 是 功 德 故  "
  },
  {
    "segmentnr":"ZH_T19_0996_001:0524a03_9",
    "original":"名薄伽梵。",
    "folio":1,
    "analyzed":"名 薄 伽 梵  "
  },
  {
    "segmentnr":"ZH_T19_0996_001:0524a04_4",
    "original":"又釋云薄伽梵具福智二種資糧。",
    "folio":1,
    "analyzed":"又 釋 云 薄 伽 梵 具 福 智 二 種 資 糧  "
  },
  {
    "segmentnr":"ZH_T19_0996_001:0524a04_10",
    "original":"二種資糧者。",
    "folio":1,
    "analyzed":"二 種 資 糧 者  "
  },
  {
    "segmentnr":"ZH_T19_0996_001:0524a04_18",
    "original":"婆誐嚩底女聲義。",
    "folio":1,
    "analyzed":"婆 誐 嚩 底 女 聲 義  "
  },
  {
    "segmentnr":"ZH_T19_0996_001:0524a05_2",
    "original":"釋如前。",
    "folio":1,
    "analyzed":"釋 如 前  "
  },
  {
    "segmentnr":"ZH_T19_0996_001:0524a05_13",
    "original":"密句釋婆字一字為種子。",
    "folio":1,
    "analyzed":"密 句 釋 婆 字 一 字 為 種 子  "
  },
  {
    "segmentnr":"ZH_T19_0996_001:0524a06_5",
    "original":"婆字者一切法有不可得。",
    "folio":1,
    "analyzed":"婆 字 者 一 切 法 有 不 可 得  "
  },
  {
    "segmentnr":"ZH_T19_0996_001:0524a06_11",
    "original":"有者三有義。",
    "folio":1,
    "analyzed":"有 者 三 有 義  "
  },
  {
    "segmentnr":"ZH_T19_0996_001:0524a06_18",
    "original":"是故三界唯心。",
    "folio":1,
    "analyzed":"是 故 三界唯心  "
  },
  {
    "segmentnr":"ZH_T19_0996_001:0524a07_7",
    "original":"由心雜染有情雜染。",
    "folio":1,
    "analyzed":"由 心 雜 染 有 情 雜 染  "
  },
  {
    "segmentnr":"ZH_T19_0996_001:0524a07_16",
    "original":"由心清淨有情清淨。",
    "folio":1,
    "analyzed":"由 心 清 淨 有 情 清 淨  "
  },
  {
    "segmentnr":"ZH_T19_0996_001:0524a08_2",
    "original":"若依顯教。",
    "folio":1,
    "analyzed":"若 依 顯 教  "
  },
  {
    "segmentnr":"ZH_T19_0996_001:0524a08_7",
    "original":"觀行般若。",
    "folio":1,
    "analyzed":"觀 行 般 若  "
  },
  {
    "segmentnr":"ZH_T19_0996_001:0524a09_2",
    "original":"作為生因顯因能生一切佛菩薩。",
    "folio":1,
    "analyzed":"作 為 生 因 顯 因 能 生 一 切 佛 菩 薩  "
  },
  {
    "segmentnr":"ZH_T19_0996_001:0524a09_8",
    "original":"是故名佛母。",
    "folio":1,
    "analyzed":"是 故 名 佛 母  "
  },
  {
    "segmentnr":"ZH_T19_0996_001:0524a09_13",
    "original":"從前即說。",
    "folio":1,
    "analyzed":"從 前 即 說  "
  },
  {
    "segmentnr":"ZH_T19_0996_001:0524a09_20",
    "original":"已後至佛母句。",
    "folio":1,
    "analyzed":"已 後 至 佛 母 句  "
  },
  {
    "segmentnr":"ZH_T19_0996_001:0524a10_5",
    "original":"於瑜伽教中。",
    "folio":1,
    "analyzed":"於 瑜 伽 教 中  "
  },
  {
    "segmentnr":"ZH_T19_0996_001:0524a10_13",
    "original":"成普賢行十六行。",
    "folio":1,
    "analyzed":"成 普 賢 行 十 六 行  "
  },
  {
    "segmentnr":"ZH_T19_0996_001:0524a11_6",
    "original":"如聲聞乘見道中十六行也。",
    "folio":1,
    "analyzed":"如 聲 聞 乘 見 道 中 十 六 行 也  "
  },
  {
    "segmentnr":"ZH_T19_0996_001:0524a12_12",
    "original":"阿囉嬭迦囉嬭阿囉拏迦囉嬭。",
    "folio":1,
    "analyzed":"阿 囉 嬭 迦 囉 嬭 阿 囉 拏 迦 囉 嬭  "
  },
  {
    "segmentnr":"ZH_T19_0996_001:0524a13_4",
    "original":"婀字門一切法本不生。",
    "folio":1,
    "analyzed":"婀 字 門 一 切 法 本 不 生  "
  },
  {
    "segmentnr":"ZH_T19_0996_001:0524a14_2",
    "original":"由知一切法本不生即入一切法離塵。",
    "folio":1,
    "analyzed":"由 知一切法 本 不 生 即 入 一 切 法 離 塵  "
  },
  {
    "segmentnr":"ZH_T19_0996_001:0524a14_14",
    "original":"是故囉字門一切法離塵義。",
    "folio":1,
    "analyzed":"是 故 囉 字 門 一 切 法 離 塵 義  "
  },
  {
    "segmentnr":"ZH_T19_0996_001:0524a15_4",
    "original":"由知一切法離塵故。",
    "folio":1,
    "analyzed":"由 知一切法 離 塵 故  "
  },
  {
    "segmentnr":"ZH_T19_0996_001:0524a15_12",
    "original":"即入一切法無諍。",
    "folio":1,
    "analyzed":"即 入 一 切 法 無 諍  "
  },
  {
    "segmentnr":"ZH_T19_0996_001:0524a16_4",
    "original":"是故嬭字門一切法無諍。",
    "folio":1,
    "analyzed":"是 故 嬭 字 門 一 切 法 無 諍  "
  },
  {
    "segmentnr":"ZH_T19_0996_001:0524a16_13",
    "original":"由知一切法無諍故。",
    "folio":1,
    "analyzed":"由 知一切法 無 諍 故  "
  },
  {
    "segmentnr":"ZH_T19_0996_001:0524a17_3",
    "original":"即入一切法無造作。",
    "folio":1,
    "analyzed":"即 入 一 切 法 無 造 作  "
  },
  {
    "segmentnr":"ZH_T19_0996_001:0524a17_15",
    "original":"是故迦字門一切法無造作。",
    "folio":1,
    "analyzed":"是 故 迦 字 門 一 切 法 無 造 作  "
  },
  {
    "segmentnr":"ZH_T19_0996_001:0524a18_6",
    "original":"由知一切法無造作故。",
    "folio":1,
    "analyzed":"由 知一切法 無 造 作 故  "
  },
  {
    "segmentnr":"ZH_T19_0996_001:0524a18_14",
    "original":"即入一切法清淨。",
    "folio":1,
    "analyzed":"即 入 一 切 法 清 淨  "
  },
  {
    "segmentnr":"ZH_T19_0996_001:0524a19_6",
    "original":"是故囉字門一切法清淨。",
    "folio":1,
    "analyzed":"是 故 囉 字 門 一 切 法 清 淨  "
  },
  {
    "segmentnr":"ZH_T19_0996_001:0524a19_15",
    "original":"由知一切法清淨故。",
    "folio":1,
    "analyzed":"由 知一切法 清 淨 故  "
  },
  {
    "segmentnr":"ZH_T19_0996_001:0524a20_4",
    "original":"即入一切法無諍。",
    "folio":1,
    "analyzed":"即 入 一 切 法 無 諍  "
  },
  {
    "segmentnr":"ZH_T19_0996_001:0524a20_15",
    "original":"是故嬭字門一切法無諍。",
    "folio":1,
    "analyzed":"是 故 嬭 字 門 一 切 法 無 諍  "
  },
  {
    "segmentnr":"ZH_T19_0996_001:0524a21_5",
    "original":"由知一切法無諍故。",
    "folio":1,
    "analyzed":"由 知一切法 無 諍 故  "
  },
  {
    "segmentnr":"ZH_T19_0996_001:0524a21_15",
    "original":"即入一切法本來寂靜。",
    "folio":1,
    "analyzed":"即 入 一 切 法 本來寂靜  "
  },
  {
    "segmentnr":"ZH_T19_0996_001:0524a22_9",
    "original":"是故阿字門一切法本來寂靜。",
    "folio":1,
    "analyzed":"是 故 阿 字 門 一 切 法 本來寂靜  "
  },
  {
    "segmentnr":"ZH_T19_0996_001:0524a23_2",
    "original":"由知一切法本來寂靜故。",
    "folio":1,
    "analyzed":"由 知一切法 本來寂靜 故  "
  },
  {
    "segmentnr":"ZH_T19_0996_001:0524a23_10",
    "original":"即入一切法無垢。",
    "folio":1,
    "analyzed":"即 入 一 切 法 無 垢  "
  },
  {
    "segmentnr":"ZH_T19_0996_001:0524a24_3",
    "original":"是故囉字門一切法無垢義。",
    "folio":1,
    "analyzed":"是 故 囉 字 門 一 切 法 無 垢 義  "
  },
  {
    "segmentnr":"ZH_T19_0996_001:0524a24_12",
    "original":"由知一切法無垢故。",
    "folio":1,
    "analyzed":"由 知一切法 無 垢 故  "
  },
  {
    "segmentnr":"ZH_T19_0996_001:0524a25_1",
    "original":"即入一切法無諍。",
    "folio":1,
    "analyzed":"即 入 一 切 法 無 諍  "
  },
  {
    "segmentnr":"ZH_T19_0996_001:0524a25_12",
    "original":"是故拏字門一切法無諍。",
    "folio":1,
    "analyzed":"是 故 拏 字 門 一 切 法 無 諍  "
  },
  {
    "segmentnr":"ZH_T19_0996_001:0524a26_2",
    "original":"由知一切法無諍故。",
    "folio":1,
    "analyzed":"由 知一切法 無 諍 故  "
  },
  {
    "segmentnr":"ZH_T19_0996_001:0524a26_11",
    "original":"即入一切法無造作。",
    "folio":1,
    "analyzed":"即 入 一 切 法 無 造 作  "
  },
  {
    "segmentnr":"ZH_T19_0996_001:0524a27_4",
    "original":"是故迦字門一切法無造作。",
    "folio":1,
    "analyzed":"是 故 迦 字 門 一 切 法 無 造 作  "
  },
  {
    "segmentnr":"ZH_T19_0996_001:0524a27_14",
    "original":"由知一切法無造作故。",
    "folio":1,
    "analyzed":"由 知一切法 無 造 作 故  "
  },
  {
    "segmentnr":"ZH_T19_0996_001:0524a28_2",
    "original":"即入無分別智。",
    "folio":1,
    "analyzed":"即 入 無分別智  "
  },
  {
    "segmentnr":"ZH_T19_0996_001:0524a28_14",
    "original":"是故囉字門一切法無分別。",
    "folio":1,
    "analyzed":"是 故 囉 字 門 一 切 法 無 分 別  "
  },
  {
    "segmentnr":"ZH_T19_0996_001:0524a29_5",
    "original":"由知一切法無分別故。",
    "folio":1,
    "analyzed":"由 知一切法 無 分 別 故  "
  },
  {
    "segmentnr":"ZH_T19_0996_001:0524a29_13",
    "original":"即入一切法無動。",
    "folio":1,
    "analyzed":"即 入 一 切 法 無 動  "
  },
  {
    "segmentnr":"ZH_T19_0996_001:0524b01_5",
    "original":"是故嬭字門一切法無動。",
    "folio":1,
    "analyzed":"是 故 嬭 字 門 一 切 法 無 動  "
  },
  {
    "segmentnr":"ZH_T19_0996_001:0524b01_14",
    "original":"由知一切法無動故。",
    "folio":1,
    "analyzed":"由 知一切法 無 動 故  "
  },
  {
    "segmentnr":"ZH_T19_0996_001:0524b02_5",
    "original":"即證摩賀般若波羅蜜。",
    "folio":1,
    "analyzed":"即 證 摩 賀 般 若 波 羅 蜜  "
  },
  {
    "segmentnr":"ZH_T19_0996_001:0524b03_10",
    "original":"摩賀鉢囉枳穰播囉弭諦。",
    "folio":1,
    "analyzed":"摩 賀 鉢 囉 枳 穰 播 囉 弭 諦  "
  },
  {
    "segmentnr":"ZH_T19_0996_001:0524b04_5",
    "original":"顯句釋摩賀大慧到彼岸。",
    "folio":1,
    "analyzed":"顯 句 釋 摩 賀 大 慧到彼岸  "
  },
  {
    "segmentnr":"ZH_T19_0996_001:0524b04_15",
    "original":"證得大般若波羅蜜故。",
    "folio":1,
    "analyzed":"證 得 大 般 若 波 羅 蜜 故  "
  },
  {
    "segmentnr":"ZH_T19_0996_001:0524b05_3",
    "original":"即依無住涅槃。",
    "folio":1,
    "analyzed":"即 依 無住涅槃  "
  },
  {
    "segmentnr":"ZH_T19_0996_001:0524b05_18",
    "original":"娑嚩二合引賀引顯句釋無住涅槃。",
    "folio":1,
    "analyzed":"娑 嚩 二 合 引 賀 引 顯 句 釋 無住涅槃  "
  },
  {
    "segmentnr":"ZH_T19_0996_001:0524b06_6",
    "original":"則依無住涅槃。",
    "folio":1,
    "analyzed":"則 依 無住涅槃  "
  },
  {
    "segmentnr":"ZH_T19_0996_001:0524b06_13",
    "original":"乃至盡未來際。",
    "folio":1,
    "analyzed":"乃 至 盡未來際  "
  },
  {
    "segmentnr":"ZH_T19_0996_001:0524b07_2",
    "original":"廣利樂無邊有情。",
    "folio":1,
    "analyzed":"廣 利 樂 無 邊 有 情  "
  },
  {
    "segmentnr":"ZH_T19_0996_001:0524b08_100",
    "original":"仁王般若陀羅尼釋一卷",
    "folio":1,
    "analyzed":"仁 王 般 若 陀 羅 尼 釋 一 卷 "
  }
]